Workbook
Name IQ_CH: 110000
Name IQ_CQ: 5000
Name IQ_CY: 10000
Name IQ_DAILY: 500000
Name IQ_FH: 100000
Name IQ_FQ: 500
Name IQ_FY: 1000
Name IQ_LTM: 2000
Name IQ_MONTH: 15000
Name IQ_NTM: 6000
Name IQ_WEEK: 50000
Name IQ_YTD: 3000
Name UPDATE: '[1]Data Sheet'!$E$1
Name UPDATE: 'Data Sheet'!$E$1

Sheet Dupont Analysis>

Sheet Dupont Analysis
B3: ='Data Sheet'!B1 -> ASIAN PAINTS LTD
B4: =CONCATENATE(" ","(",VLOOKUP(B3,'List of Stocks'!A2:C5442,3,1)," | ","BSE Code: ",VLOOKUP(B3,'List of Stocks'!A2:B5442,2,1),")") -> (ASIANPAINT | BSE Code: 500820)
B5: =CONCATENATE(" ","INR "&'Data Sheet'!B8) -> INR 2519
B6: 52 Week (High - INR 3394.90 & Low - 2124.75)
B8: About the company
B9: Asian Paints Ltd is an Indian multinational paint company, headquartered in Mumbai. The company is engaged in the business of manufacturing, selling and distribution of paints, coatings, products related to home décor, bath fittings and providing related services. Asian Paints is India's largest paints company by market share. The company has 27 paint manufacturing facilities in 15 countries, servicing consumers in over 60 countries. Asian Paints is also present in the home improvement and décor space in India.
B14: Financial Summary
B60: Return on Equity (ROE)
C61: =HistoricalFS!F3 -> 43555 | D61: =HistoricalFS!G3 -> 43921 | E61: =HistoricalFS!H3 -> 44286 | F61: =HistoricalFS!I3 -> 44651 | G61: =HistoricalFS!J3 -> 45016 | H61: =HistoricalFS!K3 -> 45382 | I61: =HistoricalFS!L3 -> 45747
B62: Net Profit | C62: =HistoricalFS!F33 -> 2520.79 | D62: =HistoricalFS!G33 -> 2897.44 | E62: =HistoricalFS!H33 -> 3060 | F62: =HistoricalFS!I33 -> 5438.87 | G62: =HistoricalFS!J33 -> 4383.33 | H62: =HistoricalFS!K33 -> 4009.13 | I62: =HistoricalFS!L33 -> 3769.49
B63: Average Shareholder Equity | C63: =(SUM('Data Sheet'!E57:E58)+SUM('Data Sheet'!D57:D58))/2 -> 8940.39 | D63: =(SUM('Data Sheet'!F57:F58)+SUM('Data Sheet'!E57:E58))/2 -> 9800.355 | E63: =(SUM('Data Sheet'!G57:G58)+SUM('Data Sheet'!F57:F58))/2 -> 11468.225 | F63: =(SUM('Data Sheet'!H57:H58)+SUM('Data Sheet'!G57:G58))/2 -> 13308.925 | G63: =(SUM('Data Sheet'!I57:I58)+SUM('Data Sheet'!H57:H58))/2 -> 14901.895 | H63: =(SUM('Data Sheet'!J57:J58)+SUM('Data Sheet'!I57:I58))/2 -> 17360.265 | I63: =(SUM('Data Sheet'!K57:K58)+SUM('Data Sheet'!J57:J58))/2 -> 19064.055
B64: Return on Equity | C64: =C62/C63 -> 0.28195526 | D64: =D62/D63 -> 0.29564643 | E64: =E62/E63 -> 0.2668242 | F64: =F62/F63 -> 0.40866336 | G64: =G62/G63 -> 0.29414581 | H64: =H62/H63 -> 0.23093714 | I64: =I62/I63 -> 0.19772761
B66: ROE - Dupont Equation
C67: =C61 -> 43555 | D67: =D61 -> 43921 | E67: =E61 -> 44286 | F67: =F61 -> 44651 | G67: =G61 -> 45016 | H67: =H61 -> 45382 | I67: =I61 -> 45747
B68: =B62 -> Net Profit | C68: =C62 -> 2520.79 | D68: =D62 -> 2897.44 | E68: =E62 -> 3060 | F68: =F62 -> 5438.87 | G68: =G62 -> 4383.33 | H68: =H62 -> 4009.13 | I68: =I62 -> 3769.49
B69: Revenue | C69: =HistoricalFS!F6 -> 19240.13 | D69: =HistoricalFS!G6 -> 20211.25 | E69: =HistoricalFS!H6 -> 21712.79 | F69: =HistoricalFS!I6 -> 29101.28 | G69: =HistoricalFS!J6 -> 34488.59 | H69: =HistoricalFS!K6 -> 35494.73 | I69: =HistoricalFS!L6 -> 33905.62
B70: Net Profit Margin (A) | C70: =C68/C69 -> 0.13101731 | D70: =D68/D69 -> 0.14335778 | E70: =E68/E69 -> 0.14093076 | F70: =F68/F69 -> 0.18689453 | G70: =G68/G69 -> 0.12709508 | H70: =H68/H69 -> 0.11295001 | I70: =I68/I69 -> 0.11117596
B72: Revenue | C72: =C69 -> 19240.13 | D72: =D69 -> 20211.25 | E72: =E69 -> 21712.79 | F72: =F69 -> 29101.28 | G72: =G69 -> 34488.59 | H72: =H69 -> 35494.73 | I72: =I69 -> 33905.62
B73: Average Total Asset | C73: =('Data Sheet'!E66+'Data Sheet'!D66)/2 -> 15006.16 | D73: =('Data Sheet'!F66+'Data Sheet'!E66)/2 -> 16193.405 | E73: =('Data Sheet'!G66+'Data Sheet'!F66)/2 -> 18246.655 | F73: =('Data Sheet'!H66+'Data Sheet'!G66)/2 -> 21656.885 | G73: =('Data Sheet'!I66+'Data Sheet'!H66)/2 -> 24368.88 | H73: =('Data Sheet'!J66+'Data Sheet'!I66)/2 -> 27840.05 | I73: =('Data Sheet'!K66+'Data Sheet'!J66)/2 -> 30128.01
B74: Asset Turnover Ratio (B) | C74: =C72/C73 -> 1.2821488 | D74: =D72/D73 -> 1.2481161 | E74: =E72/E73 -> 1.18996 | F74: =F72/F73 -> 1.3437426 | G74: =G72/G73 -> 1.4152719 | H74: =H72/H73 -> 1.2749521 | I74: =I72/I73 -> 1.1253853
B76: =B73 -> Average Total Asset | C76: =C73 -> 15006.16 | D76: =D73 -> 16193.405 | E76: =E73 -> 18246.655 | F76: =F73 -> 21656.885 | G76: =G73 -> 24368.88 | H76: =H73 -> 27840.05 | I76: =I73 -> 30128.01
B77: =B63 -> Average Shareholder Equity | C77: =C63 -> 8940.39 | D77: =D63 -> 9800.355 | E77: =E63 -> 11468.225 | F77: =F63 -> 13308.925 | G77: =G63 -> 14901.895 | H77: =H63 -> 17360.265 | I77: =I63 -> 19064.055
B78: Equity Multiplier (C) | C78: =C76/C77 -> 1.6784682 | D78: =D76/D77 -> 1.6523284 | E78: =E76/E77 -> 1.5910618 | F78: =F76/F77 -> 1.6272453 | G78: =G76/G77 -> 1.6352873 | H78: =H76/H77 -> 1.603665 | I78: =I76/I77 -> 1.5803569
B80: Return on Equity (A*B*C) | C80: =C78*C74*C70 -> 0.28195526 | D80: =D78*D74*D70 -> 0.29564643 | E80: =E78*E74*E70 -> 0.2668242 | F80: =F78*F74*F70 -> 0.40866336 | G80: =G78*G74*G70 -> 0.29414581 | H80: =H78*H74*H70 -> 0.23093714 | I80: =I78*I74*I70 -> 0.19772761
B82: Return on Asset
C83: =C67 -> 43555 | D83: =D67 -> 43921 | E83: =E67 -> 44286 | F83: =F67 -> 44651 | G83: =G67 -> 45016 | H83: =H67 -> 45382 | I83: =I67 -> 45747
B84: Net Profit | C84: =C68 -> 2520.79 | D84: =D68 -> 2897.44 | E84: =E68 -> 3060 | F84: =F68 -> 5438.87 | G84: =G68 -> 4383.33 | H84: =H68 -> 4009.13 | I84: =I68 -> 3769.49
B85: =B76 -> Average Total Asset | C85: =C73 -> 15006.16 | D85: =D73 -> 16193.405 | E85: =E73 -> 18246.655 | F85: =F73 -> 21656.885 | G85: =G73 -> 24368.88 | H85: =H73 -> 27840.05 | I85: =I73 -> 30128.01
B86: Return on Asset | C86: =C84/C85 -> 0.16798368 | D86: =D84/D85 -> 0.17892716 | E86: =E84/E85 -> 0.16770197 | F86: =F84/F85 -> 0.25113815 | G86: =G84/G85 -> 0.17987409 | H86: =H84/H85 -> 0.14400585 | I86: =I84/I85 -> 0.1251158
B88: ROA - Dupont Equation
C89: =C83 -> 43555 | D89: =D83 -> 43921 | E89: =E83 -> 44286 | F89: =F83 -> 44651 | G89: =G83 -> 45016 | H89: =H83 -> 45382 | I89: =I83 -> 45747
B90: =B84 -> Net Profit | C90: =C84 -> 2520.79 | D90: =D84 -> 2897.44 | E90: =E84 -> 3060 | F90: =F84 -> 5438.87 | G90: =G84 -> 4383.33 | H90: =H84 -> 4009.13 | I90: =I84 -> 3769.49
B91: Revenue | C91: =C72 -> 19240.13 | D91: =D72 -> 20211.25 | E91: =E72 -> 21712.79 | F91: =F72 -> 29101.28 | G91: =G72 -> 34488.59 | H91: =H72 -> 35494.73 | I91: =I72 -> 33905.62
B92: Net Profit Margin (A) | C92: =C90/C91 -> 0.13101731 | D92: =D90/D91 -> 0.14335778 | E92: =E90/E91 -> 0.14093076 | F92: =F90/F91 -> 0.18689453 | G92: =G90/G91 -> 0.12709508 | H92: =H90/H91 -> 0.11295001 | I92: =I90/I91 -> 0.11117596
B94: Revenue | C94: =C91 -> 19240.13 | D94: =D91 -> 20211.25 | E94: =E91 -> 21712.79 | F94: =F91 -> 29101.28 | G94: =G91 -> 34488.59 | H94: =H91 -> 35494.73 | I94: =I91 -> 33905.62
B95: Average Total Asset | C95: =C85 -> 15006.16 | D95: =D85 -> 16193.405 | E95: =E85 -> 18246.655 | F95: =F85 -> 21656.885 | G95: =G85 -> 24368.88 | H95: =H85 -> 27840.05 | I95: =I85 -> 30128.01
B96: Asset Turnover Ratio (B) | C96: =C94/C95 -> 1.2821488 | D96: =D94/D95 -> 1.2481161 | E96: =E94/E95 -> 1.18996 | F96: =F94/F95 -> 1.3437426 | G96: =G94/G95 -> 1.4152719 | H96: =H94/H95 -> 1.2749521 | I96: =I94/I95 -> 1.1253853
B98: Return on Asset (A*B) | C98: =C96*C92 -> 0.16798368 | D98: =D96*D92 -> 0.17892716 | E98: =E96*E92 -> 0.16770197 | F98: =F96*F92 -> 0.25113815 | G98: =G96*G92 -> 0.17987409 | H98: =H96*H92 -> 0.14400585 | I98: =I96*I92 -> 0.1251158

Sheet Altman Z Score
B3: ='Dupont Analysis'!B3 -> ASIAN PAINTS LTD
B4: =CONCATENATE(" ","(",VLOOKUP(B3,'[2]List of Stocks'!A2:C5442,3,1)," | ","BSE Code: ",VLOOKUP(B3,'[2]List of Stocks'!A2:B5442,2,1),")") -> (ASIANPAINT | BSE Code: 500820)
B5: ='Dupont Analysis'!B5 -> INR 2519
B6: 52 Week (High - INR 3394.90 & Low - 2124.75)
B8: Altman's Z Score Analysis
B10: Financial Summary
B40: Working Capital / Total Assets
C41: ='Dupont Analysis'!C61 -> 43555 | D41: ='Dupont Analysis'!D61 -> 43921 | E41: ='Dupont Analysis'!E61 -> 44286 | F41: ='Dupont Analysis'!F61 -> 44651 | G41: ='Dupont Analysis'!G61 -> 45016 | H41: ='Dupont Analysis'!H61 -> 45382 | I41: ='Dupont Analysis'!I61 -> 45747
B42: Working Capital | C42: ='Data Sheet'!E65-'Data Sheet'!E60 -> 1515.34 | D42: ='Data Sheet'!F65-'Data Sheet'!F60 -> 2817.26 | E42: ='Data Sheet'!G65-'Data Sheet'!G60 -> 3121.11 | F42: ='Data Sheet'!H65-'Data Sheet'!H60 -> 6205.42 | G42: ='Data Sheet'!I65-'Data Sheet'!I60 -> 6873.09 | H42: ='Data Sheet'!J65-'Data Sheet'!J60 -> 6769.77 | I42: ='Data Sheet'!K65-'Data Sheet'!K60 -> 6490.76
B43: Total Assets | C43: ='Data Sheet'!E61 -> 16248.84 | D43: ='Data Sheet'!F61 -> 16137.97 | E43: ='Data Sheet'!G61 -> 20355.34 | F43: ='Data Sheet'!H61 -> 22958.43 | G43: ='Data Sheet'!I61 -> 25779.33 | H43: ='Data Sheet'!J61 -> 29900.77 | I43: ='Data Sheet'!K61 -> 30355.25
B44: Working Capital / Total Assets (A) | C44: =C42/C43 -> 0.09325835 | D44: =D42/D43 -> 0.17457338 | E44: =E42/E43 -> 0.15333126 | F44: =F42/F43 -> 0.27028939 | G44: =G42/G43 -> 0.26661244 | H44: =H42/H43 -> 0.22640788 | I44: =I42/I43 -> 0.2138266
B46: Retained Earnings / Total Assets
C47: =C41 -> 43555 | D47: =D41 -> 43921 | E47: =E41 -> 44286 | F47: =F41 -> 44651 | G47: =G41 -> 45016 | H47: =H41 -> 45382 | I47: =I41 -> 45747
B48: Retained Earnings | C48: =HistoricalFS!F36*HistoricalFS!F38*HistoricalFS!F44 -> 1513.63 | D48: =HistoricalFS!G36*HistoricalFS!G38*HistoricalFS!G44 -> 1746.4 | E48: =HistoricalFS!H36*HistoricalFS!H38*HistoricalFS!H44 -> 1347.83 | F48: =HistoricalFS!I36*HistoricalFS!I38*HistoricalFS!I44 -> 3602 | G48: =HistoricalFS!J36*HistoricalFS!J38*HistoricalFS!J44 -> 1922.98 | H48: =HistoricalFS!K36*HistoricalFS!K38*HistoricalFS!K44 -> 814.99 | I48: =HistoricalFS!L36*HistoricalFS!L38*HistoricalFS!L44 -> 1390.67
B49: Total Assets | C49: =C$43 -> 16248.84 | D49: =D$43 -> 16137.97 | E49: =E$43 -> 20355.34 | F49: =F$43 -> 22958.43 | G49: =G$43 -> 25779.33 | H49: =H$43 -> 29900.77 | I49: =I$43 -> 30355.25
B50: Retained Earnings / Total Assets (B) | C50: =C48/C49 -> 0.093153111 | D50: =D48/D49 -> 0.10821683 | E50: =E48/E49 -> 0.066215057 | F50: =F48/F49 -> 0.15689226 | G50: =G48/G49 -> 0.07459387 | H50: =H48/H49 -> 0.027256489 | I50: =I48/I49 -> 0.045813162
B52: EBIT / Total Assets
C53: =C41 -> 43555 | D53: =D41 -> 43921 | E53: =E41 -> 44286 | F53: =F41 -> 44651 | G53: =G41 -> 45016 | H53: =H41 -> 45382 | I53: =I41 -> 45747
B54: EBIT | C54: =HistoricalFS!F18-HistoricalFS!F24 -> 3729.32 | D54: =HistoricalFS!G18-HistoricalFS!G24 -> 3854.62 | E54: =HistoricalFS!H18-HistoricalFS!H24 -> 4249.23 | F54: =HistoricalFS!I18-HistoricalFS!I24 -> 6637.19 | G54: =HistoricalFS!J18-HistoricalFS!J24 -> 6021.28 | H54: =HistoricalFS!K18-HistoricalFS!K24 -> 6004.38 | I54: =HistoricalFS!L18-HistoricalFS!L24 -> 5389.87
B55: Total Assets | C55: =C$43 -> 16248.84 | D55: =D$43 -> 16137.97 | E55: =E$43 -> 20355.34 | F55: =F$43 -> 22958.43 | G55: =G$43 -> 25779.33 | H55: =H$43 -> 29900.77 | I55: =I$43 -> 30355.25
B56: EBIT/Total Assets (C) | C56: =C54/C55 -> 0.229513 | D56: =D54/D55 -> 0.23885408 | E56: =E54/E55 -> 0.20875259 | F56: =F54/F55 -> 0.28909599 | G56: =G54/G55 -> 0.23357007 | H56: =H54/H55 -> 0.20081021 | I56: =I54/I55 -> 0.17755973
B58: Market Cap / Long term Liabilities
C59: =C41 -> 43555 | D59: =D41 -> 43921 | E59: =E41 -> 44286 | F59: =F41 -> 44651 | G59: =G41 -> 45016 | H59: =H41 -> 45382 | I59: =I41 -> 45747
B60: Market Cap | C60: =('Data Sheet'!E90*'Data Sheet'!E70)/10000000 -> 143179.45 | D60: =('Data Sheet'!F90*'Data Sheet'!F70)/10000000 -> 159850.31 | E60: =('Data Sheet'!G90*'Data Sheet'!G70)/10000000 -> 243386.85 | F60: =('Data Sheet'!H90*'Data Sheet'!H70)/10000000 -> 295428.12 | G60: =('Data Sheet'!I90*'Data Sheet'!I70)/10000000 -> 264896.86 | H60: =('Data Sheet'!J90*'Data Sheet'!J70)/10000000 -> 273059.63 | I60: =('Data Sheet'!K90*'Data Sheet'!K70)/10000000 -> 241621.92
B61: Long term Liabilities | C61: ='Data Sheet'!E59 -> 1319.6 | D61: ='Data Sheet'!F59 -> 1118.5 | E61: ='Data Sheet'!G59 -> 1093.12 | F61: ='Data Sheet'!H59 -> 1586.88 | G61: ='Data Sheet'!I59 -> 1932.62 | H61: ='Data Sheet'!J59 -> 2474.38 | I61: ='Data Sheet'!K59 -> 2290.29
B62: Market Cap / Long term Liabilities (D) | C62: =C60/C61 -> 108.50216 | D62: =D60/D61 -> 142.9149 | E62: =E60/E61 -> 222.65337 | F62: =F60/F61 -> 186.16916 | G62: =G60/G61 -> 137.06619 | H62: =H60/H61 -> 110.35477 | I62: =I60/I61 -> 105.4984
B64: Sales / Total Assets
C65: =C41 -> 43555 | D65: =D41 -> 43921 | E65: =E41 -> 44286 | F65: =F41 -> 44651 | G65: =G41 -> 45016 | H65: =H41 -> 45382 | I65: =I41 -> 45747
B66: Total Sales | C66: =HistoricalFS!F6 -> 19240.13 | D66: =HistoricalFS!G6 -> 20211.25 | E66: =HistoricalFS!H6 -> 21712.79 | F66: =HistoricalFS!I6 -> 29101.28 | G66: =HistoricalFS!J6 -> 34488.59 | H66: =HistoricalFS!K6 -> 35494.73 | I66: =HistoricalFS!L6 -> 33905.62
B67: Total Assets | C67: =C55 -> 16248.84 | D67: =D55 -> 16137.97 | E67: =E55 -> 20355.34 | F67: =F55 -> 22958.43 | G67: =G55 -> 25779.33 | H67: =H55 -> 29900.77 | I67: =I55 -> 30355.25
B68: Return on Asset (E) | C68: =C66/C67 -> 1.1840925 | D68: =D66/D67 -> 1.2524035 | E68: =E66/E67 -> 1.0666877 | F68: =F66/F67 -> 1.267564 | G68: =G66/G67 -> 1.3378389 | H68: =H66/H67 -> 1.1870841 | I68: =I66/I67 -> 1.1169607
B70: Altman's Z Score
C71: =C41 -> 43555 | D71: =D41 -> 43921 | E71: =E41 -> 44286 | F71: =F41 -> 44651 | G71: =G41 -> 45016 | H71: =H41 -> 45382 | I71: =I41 -> 45747
B72: Final Score | C72: =(C44*1.2)+(C50*1.4)+(C56*3.3)+(C62*0.6)*(C68*1) -> 78.085677 | D72: =(D44*1.2)+(D50*1.4)+(D56*3.3)+(D62*0.6)*(D68*1) -> 108.54148 | E72: =(E44*1.2)+(E50*1.4)+(E56*3.3)+(E62*0.6)*(E68*1) -> 143.46654 | F72: =(F44*1.2)+(F50*1.4)+(F56*3.3)+(F62*0.6)*(F68*1) -> 143.08681 | G72: =(G44*1.2)+(G50*1.4)+(G56*3.3)+(G62*0.6)*(G68*1) -> 111.21863 | H72: =(H44*1.2)+(H50*1.4)+(H56*3.3)+(H62*0.6)*(H68*1) -> 79.57276 | I72: =(I44*1.2)+(I50*1.4)+(I56*3.3)+(I62*0.6)*(I68*1) -> 71.609213
B73: Financial Stability | C73: =IF(C72<1.81," Distressed",IF(C72>3,"Strong","Grey Zone")) -> Strong | D73: =IF(D72<1.81," Distressed",IF(D72>3,"Strong","Grey Zone")) -> Strong | E73: =IF(E72<1.81," Distressed",IF(E72>3,"Strong","Grey Zone")) -> Strong | F73: =IF(F72<1.81," Distressed",IF(F72>3,"Strong","Grey Zone")) -> Strong | G73: =IF(G72<1.81," Distressed",IF(G72>3,"Strong","Grey Zone")) -> Strong | H73: =IF(H72<1.81," Distressed",IF(H72>3,"Strong","Grey Zone")) -> Strong | I73: =IF(I72<1.81," Distressed",IF(I72>3,"Strong","Grey Zone")) -> Strong

Sheet VAR>

Sheet Historical Approach
B3: Value at Risk - Asian Paints Ltd. (Historical)
B5: Date | C5: Adj. Close | D5: Returns | E5: Sorted Returns | G5: Calculation of Value at Risk - Asian Paints Ltd.
B7: 43910 | C7: 1745.85 | D7: =(C7-C8)/C8 -> -0.3705473 | E7: 0.089114161 | G7: Mean | K7: =AVERAGE(E7:E2648) -> 0.00057895214
B8: 44330 | C8: 2773.6 | D8: =(C8-C9)/C9 -> 0.53725925 | E8: 0.085090568 | G8: Std. Deviation | K8: =_xlfn.STDEV.S(E7:E2648) -> 0.015516149
B9: 43731 | C9: 1804.25 | D9: =(C9-C10)/C10 -> 0.07887105 | E9: 0.07887105 | G9: Min | K9: =MIN(E7:E2648) -> -0.14153564
B10: 43728 | C10: 1672.35 | D10: =(C10-C11)/C11 -> 0.029740464 | E10: 0.075915978 | G10: Max | K10: =MAX(E7:E2648) -> 0.089114161
B11: 43928 | C11: 1624.05 | D11: =(C11-C12)/C12 -> -0.13031488 | E11: 0.067540919 | G11: CMP | K11: 2519
B12: 43864 | C12: 1867.4 | D12: =(C12-C13)/C13 -> 0.44804591 | E12: 0.063197449
B13: 43231 | C13: 1289.6 | D13: =(C13-C14)/C14 -> 0.14432761 | E13: 0.061661316 | G13: Percentile | H13: Confidence | I13: VAR% | J13: Stock Price | K13: VAR (INR)
B14: 42579 | C14: 1126.95 | D14: =(C14-C15)/C15 -> 0.37516779 | E14: 0.061358071 | G14: 0.05 | H14: =100%-G14 -> 0.95 | I14: =_xlfn.PERCENTILE.INC($E$7:$E$2648,G14) -> -0.022777133 | J14: =$K$11*(1-I14) -> 2576.3756 | K14: =$K$11-J14 -> -57.375597
B15: 42012 | C15: 819.5 | D15: =(C15-C16)/C16 -> -0.74059889 | E15: 0.061116147 | G15: 0.01 | H15: =100%-G15 -> 0.99 | I15: =_xlfn.PERCENTILE.INC($E$7:$E$2648,G15) -> -0.039418631 | J15: =$K$11*(1-I15) -> 2618.2955 | K15: =$K$11-J15 -> -99.295532
B16: 44397 | C16: 3159.2 | D16: =(C16-C17)/C17 -> 0.43720856 | E16: 0.060365516 | G16: 0.005 | H16: =100%-G16 -> 0.995 | I16: =_xlfn.PERCENTILE.INC($E$7:$E$2648,G16) -> -0.051234076 | J16: =$K$11*(1-I16) -> 2648.0586 | K16: =$K$11-J16 -> -129.05864
B17: 44131 | C17: 2198.15 | D17: =(C17-C18)/C18 -> -0.23545268 | E17: 0.056447349 | G17: 0.1 | H17: =100%-G17 -> 0.9 | I17: =_xlfn.PERCENTILE.INC($E$7:$E$2648,G17) -> -0.016193275 | J17: =$K$11*(1-I17) -> 2559.7909 | K17: =$K$11-J17 -> -40.790859
B18: 44629 | C18: 2875.1 | D18: =(C18-C19)/C19 -> 2.4860261 | E18: 0.055605529
B19: 42192 | C19: 824.75 | D19: =(C19-C20)/C20 -> -0.54500317 | E19: 0.052782742
B20: 43943 | C20: 1812.65 | D20: =(C20-C21)/C21 -> 0.15088889 | E20: 0.050446222
B21: 43972 | C21: 1575 | D21: =(C21-C22)/C22 -> -0.36255464 | E21: 0.049685094
B22: 44271 | C22: 2470.8 | D22: =(C22-C23)/C23 -> 1.6444052 | E22: 0.048748912
B23: 42690 | C23: 934.35 | D23: =(C23-C24)/C24 -> -0.58786556 | E23: 0.047242771
B24: 45722 | C24: 2267.1 | D24: =(C24-C25)/C25 -> 0.4222264 | E24: 0.047038448
B25: 43915 | C25: 1594.05 | D25: =(C25-C26)/C26 -> 0.3395941 | E25: 0.045107359
B26: 43397 | C26: 1189.95 | D26: =(C26-C27)/C27 -> 0.41475449 | E26: 0.044915701
B27: 42277 | C27: 841.1 | D27: =(C27-C28)/C28 -> -0.53402953 | E27: 0.044520335
B28: 44050 | C28: 1805.05 | D28: =(C28-C29)/C29 -> -0.078280185 | E28: 0.044438015
B29: 44064 | C29: 1958.35 | D29: =(C29-C30)/C30 -> -0.36709004 | E29: 0.044314091
... B39: 44292 | C39: 2612.65 | D39: =(C39-C40)/C40 -> 0.97337513 | E39: 0.040689106
B40: 43445 | C40: 1323.95 | D40: =(C40-C42)/C42 -> 0.090074513 | E40: 0.04026872
B42: 42979 | C42: 1214.55 | D42: =(C42-C43)/C43 -> -0.38603276 | E42: 0.039720926
B43: 44075 | C43: 1978.2 | D43: =(C43-C44)/C44 -> 0.11275489 | E43: 0.039298098
B44: 44039 | C44: 1777.75 | D44: =(C44-C45)/C45 -> -0.23250443 | E44: 0.039042637
B45: 44167 | C45: 2316.3 | D45: =(C45-C46)/C46 -> 1.4576127 | E45: 0.038839306
B46: 42697 | C46: 942.5 | D46: =(C46-C47)/C47 -> -0.36472095 | E46: 0.038739186
B47: 43670 | C47: 1483.6 | D47: =(C47-C48)/C48 -> -0.48466428 | E47: 0.038680996
B48: 45425 | C48: 2878.9 | D48: =(C48-C49)/C49 -> 1.6928257 | E48: 0.03826457
B49: 42808 | C49: 1069.1 | D49: =(C49-C50)/C50 -> -0.17647512 | E49: 0.038061948
B50: 43413 | C50: 1298.2 | D50: =(C50-C51)/C51 -> -0.60229153 | E50: 0.037854259
B51: 44607 | C51: 3264.2 | D51: =(C51-C52)/C52 -> 0.38135037 | E51: 0.037604501
B52: 44256 | C52: 2363.05 | D52: =(C52-C53)/C53 -> 0.8732065 | E52: 0.037585897
B53: 43385 | C53: 1261.5 | D53: =(C53-C54)/C54 -> -0.27765689 | E53: 0.037375108
... B2648: 43913 | C2648: 1498.75 | D2648: =(C2648-C2649)/C2649 -> #DIV/0! | E2648: -0.14153564

Sheet Monte Carlo
B3: Value at Risk - Asian Paints Ltd. (Monte Carlo)
B5: Date | C5: Adj. Close | D5: Returns | E5: Sorted Returns | G5: Replication | H5: Simulation Returns | J5: Calculation of Value at Risk - Asian Paints Ltd.
B7: 43910 | C7: 1745.85 | D7: =(C7-C8)/C8 -> -0.3705473 | E7: 0.089114161 | G7: 1 | H7: =_xlfn.NORM.INV(RAND(),N$9,N$10) -> 0.0070364041
B8: 44330 | C8: 2773.6 | D8: =(C8-C9)/C9 -> 0.53725925 | E8: 0.085090568 | G8: 2 | H8: =_xlfn.NORM.INV(RAND(),N$9,N$10) -> -0.0069259517 | J8: Historical Approach
B9: 43731 | C9: 1804.25 | D9: =(C9-C10)/C10 -> 0.07887105 | E9: 0.07887105 | G9: 3 | H9: =_xlfn.NORM.INV(RAND(),N$9,N$10) -> 0.018246025 | J9: Mean | N9: =AVERAGE(E7:E2647) -> 0.00057895214
B10: 43728 | C10: 1672.35 | D10: =(C10-C11)/C11 -> 0.029740464 | E10: 0.075915978 | G10: 4 | H10: =_xlfn.NORM.INV(RAND(),N$9,N$10) -> -0.020941179 | J10: Std. Deviation | N10: =_xlfn.STDEV.S(E7:E2647) -> 0.015516149
B11: 43928 | C11: 1624.05 | D11: =(C11-C12)/C12 -> -0.13031488 | E11: 0.067540919 | G11: 5 | H11: =_xlfn.NORM.INV(RAND(),N$9,N$10) -> -0.009682489 | J11: Min | N11: =MIN(E7:E2647) -> -0.14153564
B12: 43864 | C12: 1867.4 | D12: =(C12-C13)/C13 -> 0.44804591 | E12: 0.063197449 | G12: 6 | H12: =_xlfn.NORM.INV(RAND(),N$9,N$10) -> -0.012052257 | J12: Max | N12: =MAX(E7:E2647) -> 0.089114161
B13: 43231 | C13: 1289.6 | D13: =(C13-C14)/C14 -> 0.14432761 | E13: 0.061661316 | G13: 7 | H13: =_xlfn.NORM.INV(RAND(),N$9,N$10) -> 0.013586859 | J13: CMP | N13: 2519
B14: 42579 | C14: 1126.95 | D14: =(C14-C15)/C15 -> 0.37516779 | E14: 0.061358071 | G14: 8 | H14: =_xlfn.NORM.INV(RAND(),N$9,N$10) -> -0.020294313
B15: 42012 | C15: 819.5 | D15: =(C15-C16)/C16 -> -0.74059889 | E15: 0.061116147 | G15: 9 | H15: =_xlfn.NORM.INV(RAND(),N$9,N$10) -> -0.0166487 | J15: Monte Carlo Simulation
B16: 44397 | C16: 3159.2 | D16: =(C16-C17)/C17 -> 0.43720856 | E16: 0.060365516 | G16: 10 | H16: =_xlfn.NORM.INV(RAND(),N$9,N$10) -> 0.0060725629 | J16: Mean | N16: =AVERAGE(H7:H10006) -> 0.00046064922
B17: 44131 | C17: 2198.15 | D17: =(C17-C18)/C18 -> -0.23545268 | E17: 0.056447349 | G17: 11 | H17: =_xlfn.NORM.INV(RAND(),N$9,N$10) -> 0.041200783 | J17: Std. Deviation | N17: =_xlfn.STDEV.S(H7:H10006) -> 0.01537875
B18: 44629 | C18: 2875.1 | D18: =(C18-C19)/C19 -> 2.4860261 | E18: 0.055605529 | G18: 12 | H18: =_xlfn.NORM.INV(RAND(),N$9,N$10) -> 0.026310555 | J18: Min | N18: =MIN(H7:H10006) -> -0.05707688
B19: 42192 | C19: 824.75 | D19: =(C19-C20)/C20 -> -0.54500317 | E19: 0.052782742 | G19: 13 | H19: =_xlfn.NORM.INV(RAND(),N$9,N$10) -> -0.0082735113 | J19: Max | N19: =MAX(H7:H10006) -> 0.060625364
B20: 43943 | C20: 1812.65 | D20: =(C20-C21)/C21 -> 0.15088889 | E20: 0.050446222 | G20: 14 | H20: =_xlfn.NORM.INV(RAND(),N$9,N$10) -> -0.015613953 | J20: CMP | N20: 2519
B21: 43972 | C21: 1575 | D21: =(C21-C22)/C22 -> -0.36255464 | E21: 0.049685094 | G21: 15 | H21: =_xlfn.NORM.INV(RAND(),N$9,N$10) -> -0.018863177
B22: 44271 | C22: 2470.8 | D22: =(C22-C23)/C23 -> 1.6444052 | E22: 0.048748912 | G22: 16 | H22: =_xlfn.NORM.INV(RAND(),N$9,N$10) -> 0.011156055 | J22: Percentile | K22: Confidence | L22: VAR% | M22: Stock Price | N22: VAR (INR)
B23: 42690 | C23: 934.35 | D23: =(C23-C24)/C24 -> -0.58786556 | E23: 0.047242771 | G23: 17 | H23: =_xlfn.NORM.INV(RAND(),N$9,N$10) -> -0.027792355 | J23: 0.05 | K23: =100%-J23 -> 0.95 | L23: =_xlfn.PERCENTILE.INC($H$7:$H$10006,J23) -> -0.024675891 | M23: =$N$13*(1-L23) -> 2581.1586 | N23: =$N$13-M23 -> -62.158569
B24: 45722 | C24: 2267.1 | D24: =(C24-C25)/C25 -> 0.4222264 | E24: 0.047038448 | G24: 18 | H24: =_xlfn.NORM.INV(RAND(),N$9,N$10) -> 0.0057045031 | J24: 0.01 | K24: =100%-J24 -> 0.99 | L24: =_xlfn.PERCENTILE.INC($H$7:$H$10006,J24) -> -0.033929517 | M24: =$N$13*(1-L24) -> 2604.4685 | N24: =$N$13-M24 -> -85.468452
B25: 43915 | C25: 1594.05 | D25: =(C25-C26)/C26 -> 0.3395941 | E25: 0.045107359 | G25: 19 | H25: =_xlfn.NORM.INV(RAND(),N$9,N$10) -> 0.0203278 | J25: 0.005 | K25: =100%-J25 -> 0.995 | L25: =_xlfn.PERCENTILE.INC($H$7:$H$10006,J25) -> -0.037780465 | M25: =$N$13*(1-L25) -> 2614.169 | N25: =$N$13-M25 -> -95.168992
B26: 43397 | C26: 1189.95 | D26: =(C26-C27)/C27 -> 0.41475449 | E26: 0.044915701 | G26: 20 | H26: =_xlfn.NORM.INV(RAND(),N$9,N$10) -> -0.015865195 | J26: 0.1 | K26: =100%-J26 -> 0.9 | L26: =_xlfn.PERCENTILE.INC($H$7:$H$10006,J26) -> -0.019151081 | M26: =$N$13*(1-L26) -> 2567.2416 | N26: =$N$13-M26 -> -48.241572
B27: 42277 | C27: 841.1 | D27: =(C27-C28)/C28 -> -0.53402953 | E27: 0.044520335 | G27: 21 | H27: =_xlfn.NORM.INV(RAND(),N$9,N$10) -> -0.0033514734
B28: 44050 | C28: 1805.05 | D28: =(C28-C29)/C29 -> -0.078280185 | E28: 0.044438015 | G28: 22 | H28: =_xlfn.NORM.INV(RAND(),N$9,N$10) -> -0.018364327
B29: 44064 | C29: 1958.35 | D29: =(C29-C30)/C30 -> -0.36709004 | E29: 0.044314091 | G29: 23 | H29: =_xlfn.NORM.INV(RAND(),N$9,N$10) -> -0.011254337
B30: 44496 | C30: 3094.2 | D30: =(C30-C31)/C31 -> 0.85648287 | E30: 0.044226583 | G30: 24 | H30: =_xlfn.NORM.INV(RAND(),N$9,N$10) -> 0.023081111
B31: 43921 | C31: 1666.7 | D31: =(C31-C32)/C32 -> -0.33453115 | E31: 0.043546317 | G31: 25 | H31: =_xlfn.NORM.INV(RAND(),N$9,N$10) -> 0.0099956519
B32: 44281 | C32: 2504.55 | D32: =(C32-C33)/C33 -> 0.21409181 | E32: 0.042758707 | G32: 26 | H32: =_xlfn.NORM.INV(RAND(),N$9,N$10) -> 0.013949466
B33: 44084 | C33: 2062.9 | D33: =(C33-C34)/C34 -> 1.368699 | E33: 0.042500505 | G33: 27 | H33: =_xlfn.NORM.INV(RAND(),N$9,N$10) -> -0.034644527
B34: 42345 | C34: 870.9 | D34: =(C34-C35)/C35 -> -0.36558004 | E34: 0.041621816 | G34: 28 | H34: =_xlfn.NORM.INV(RAND(),N$9,N$10) -> -0.011693497
B35: 43605 | C35: 1372.75 | D35: =(C35-C36)/C36 -> 0.72792498 | E35: 0.041421689 | G35: 29 | H35: =_xlfn.NORM.INV(RAND(),N$9,N$10) -> 0.0066497025
B36: 42138 | C36: 794.45 | D36: =(C36-C37)/C37 -> -0.34907825 | E36: 0.041218873 | G36: 30 | H36: =_xlfn.NORM.INV(RAND(),N$9,N$10) -> 0.019048309
B37: 43032 | C37: 1220.5 | D37: =(C37-C38)/C38 -> -0.49374702 | E37: 0.041026953 | G37: 31 | H37: =_xlfn.NORM.INV(RAND(),N$9,N$10) -> 0.0091883428
B38: 44168 | C38: 2410.85 | D38: =(C38-C39)/C39 -> -0.077239584 | E38: 0.04081941 | G38: 32 | H38: =_xlfn.NORM.INV(RAND(),N$9,N$10) -> -0.011257909
... B2647: 43913 | C2647: 1498.75 | D2647: =(C2647-C2648)/C2648 -> #DIV/0! | E2647: -0.14153564 | G2647: 2641 | H2647: =_xlfn.NORM.INV(RAND(),N$9,N$10) -> 0.0071825011
G2648: 2642 | H2648: =_xlfn.NORM.INV(RAND(),N$9,N$10) -> 0.015382464
G2649: 2643 | H2649: =_xlfn.NORM.INV(RAND(),N$9,N$10) -> 0.00076792231
G2650: 2644 | H2650: =_xlfn.NORM.INV(RAND(),N$9,N$10) -> -0.017972665
G2651: 2645 | H2651: =_xlfn.NORM.INV(RAND(),N$9,N$10) -> -0.0092114577
G2652: 2646 | H2652: =_xlfn.NORM.INV(RAND(),N$9,N$10) -> -0.033672363
G2653: 2647 | H2653: =_xlfn.NORM.INV(RAND(),N$9,N$10) -> 0.010871575
G2654: 2648 | H2654: =_xlfn.NORM.INV(RAND(),N$9,N$10) -> -0.0020128262
G2655: 2649 | H2655: =_xlfn.NORM.INV(RAND(),N$9,N$10) -> -0.003714088
G2656: 2650 | H2656: =_xlfn.NORM.INV(RAND(),N$9,N$10) -> -0.00052879333
G2657: 2651 | H2657: =_xlfn.NORM.INV(RAND(),N$9,N$10) -> 0.016264065
G2658: 2652 | H2658: =_xlfn.NORM.INV(RAND(),N$9,N$10) -> -0.013572908
G2659: 2653 | H2659: =_xlfn.NORM.INV(RAND(),N$9,N$10) -> -0.0085556228
... G10006: 10000 | H10006: =_xlfn.NORM.INV(RAND(),N$9,N$10) -> 0.04050103

Sheet Stk Data
A2: Date | B2: Adj. Close | M2: Date | N2: Total Turnover (Rs.)
A3: 44197 | B3: 2775 | M3: 44197 | N3: 144.66687 | O3: 1000000
A4: 44200 | B4: 2754.8 | M4: 44200 | N4: 126.01642
A5: 44201 | B5: 2793.25 | M5: 44201 | N5: 206.81007
A6: 44202 | B6: 2803.15 | M6: 44202 | N6: 121.21768
A7: 44203 | B7: 2791.35 | M7: 44203 | N7: 2360.0694
A8: 44204 | B8: 2844 | M8: 44204 | N8: 94.850617
A9: 44207 | B9: 2849.2 | M9: 44207 | N9: 138.57914
A10: 44208 | B10: 2737.3 | M10: 44208 | N10: 498.14647
A11: 44209 | B11: 2704.5 | M11: 44209 | N11: 317.39955
A12: 44210 | B12: 2663.5 | M12: 44210 | N12: 529.5037
A13: 44211 | B13: 2590 | M13: 44211 | N13: 158.76397
A14: 44214 | B14: 2589.05 | M14: 44214 | N14: 178.14425
A15: 44215 | B15: 2645.6 | M15: 44215 | N15: 327.6484
... A1158: 45898 | B1158: 2517.4 | M1158: 45898 | N1158: 137.32995

Sheet DCF>

Sheet WACC
B3: Weighted Average Cost of Capital
B5: All figures are in INR unless stated otherwise.
B6: Amount in crores
B7: Peer Comps
G8: Debt/ | H8: Debt/ | I8: Levered | J8: Unlevered
B9: Name | C9: Country | D9: Total Debt | E9: Total Equity | F9: Tax Rate 1 | G9: Equity | H9: Capital | I9: Beta 2 | J9: Beta 3
B11: ='Beta Comps'!D4 -> Asian Paints | C11: India | D11: ='Beta Comps'!G4 -> 2290.29 | E11: ='Beta Comps'!F4 -> 238614.8 | F11: 0.3 | G11: =D11/E11 -> 0.009598273 | H11: =D11/(D11+E11) -> 0.009507022 | I11: ='Beta - Regression'!M7 -> 0.16859133 | J11: =I11/(1+(1-F11)*G11) -> 0.16746616
B12: ='Beta Comps'!D5 -> Berger Paints | C12: India | D12: ='Beta Comps'!G5 -> 670.27 | E12: ='Beta Comps'!F5 -> 61280.41 | F12: 0.3 | G12: =D12/E12 -> 0.010937753 | H12: =D12/(D12+E12) -> 0.010819413 | I12: 0.752 | J12: =I12/(1+(1-F12)*G12) -> 0.74628611
B13: ='Beta Comps'!D6 -> Kansai Nerolac | C13: India | D13: ='Beta Comps'!G6 -> 296.39 | E13: ='Beta Comps'!F6 -> 18926.24 | F13: 0.3 | G13: =D13/E13 -> 0.015660268 | H13: =D13/(D13+E13) -> 0.015418806 | I13: 0.88 | J13: =I13/(1+(1-F13)*G13) -> 0.87045788
B14: ='Beta Comps'!D7 -> Akzo Nobel | C14: India | D14: ='Beta Comps'!G7 -> 62.1 | E14: ='Beta Comps'!F7 -> 15646.37 | F14: 0.3 | G14: =D14/E14 -> 0.0039689717 | H14: =D14/(D14+E14) -> 0.0039532813 | I14: 0.04 | J14: =I14/(1+(1-F14)*G14) -> 0.039889177
B15: ='Beta Comps'!D8 -> Indigo Paints | C15: India | D15: ='Beta Comps'!G8 -> 19.7 | E15: ='Beta Comps'!F8 -> 5271.68 | F15: 0.3 | G15: =D15/E15 -> 0.0037369491 | H15: =D15/(D15+E15) -> 0.0037230363 | I15: 0.97 | J15: =I15/(1+(1-F15)*G15) -> 0.96746923
E17: Average | F17: =AVERAGE(F11:F15) -> 0.3 | G17: =AVERAGE(G11:G15) -> 0.0087804431 | H17: =AVERAGE(H11:H15) -> 0.0086843117 | I17: =AVERAGE(I11:I15) -> 0.56211827 | J17: =AVERAGE(J11:J15) -> 0.55831371
E18: Median | F18: =MEDIAN(F11:F15) -> 0.3 | G18: =MEDIAN(G11:G15) -> 0.009598273 | H18: =MEDIAN(H11:H15) -> 0.009507022 | I18: =MEDIAN(I11:I15) -> 0.752 | J18: =MEDIAN(J11:J15) -> 0.74628611
B21: Cost of Debt | G21: Cost of Equity
B23: Pre-tax Cost of Debt | E23: =227/2290.29 -> 0.099114086 | G23: Risk Free Rate | J23: 0.0662
B24: Tax Rate | E24: =F18 -> 0.3 | G24: Equity Risk Premium | J24: =Rm!F8-J23 -> 0.087148
B25: After Tax Cost of Debt | E25: =E23*(1-E24) -> 0.06937986 | G25: Levered Beta 4 | J25: =J34 -> 0.96821062
G26: Cost of Equity | J26: =J23+(J24*J25) -> 0.15057762
B29: Capital Structure | G29: Levered Beta
D31: Current | E31: Target | G31: Comps Median Unlevered Beta | J31: =J18 -> 0.74628611
B32: Total Debt | C32: =D11 -> 2290.29 | D32: =C32/$C$34 -> 0.009507022 | E32: =H17 -> 0.0086843117 | G32: Target Debt/ Equity | J32: =E36 -> 0.0087603897
B33: Market Capitalization | C33: =E11 -> 238614.8 | D33: =C33/$C$34 -> 0.99049298 | E33: =E34-E32 -> 0.99131569 | G33: Tax Rate | J33: =E24 -> 0.3
B34: Total Capitalization | C34: =SUM(C32:C33) -> 240905.09 | D34: =C34/$C$34 -> 1 | E34: =D34 -> 1 | G34: Levered Beta | J34: =J31*(1+(1-J32)*J33) -> 0.96821062
B36: Debt / Equity | D36: =D32/D33 -> 0.009598273 | E36: =E32/E33 -> 0.0087603897 | G36: Weighted Average Cost of Capital
B38: 1. Tax Rate considered as Marginal Tax Rate for the country | G38: Cost of Equity | J38: =J26 -> 0.15057762
B39: 2. Levered Beta is based on 5 year monthly data | G39: Equity Weight | J39: =E33 -> 0.99131569
B40: 3. Unlevered Beta = Levered Beta/(1+(1-Tax Rate) x Debt/Equity)
B41: 3. Levered Beta = Unlevered Beta/(1+(1-Tax Rate) x Debt/Equity) | G41: Cost of Debt | J41: =E25 -> 0.06937986
G42: Debt Weight | J42: =E32 -> 0.0086843117
G44: WACC | J44: =(J38*J39)+(J41*J42) -> 0.14987247

Sheet Data>

Sheet Beta - Regression
B2: Regression Beta - 2 Years Weekly
B4: Asian Paints Ltd. Weekly Returns | F4: Nifty Returns | I4: Beta Drifting | L4: Beta 1 | M4: =SLOPE(D8:D111,G8:G111) -> 0.16859133
L5: Beta 2 | M5: =_xlfn.COVARIANCE.S(D8:D111,G8:G111)/_xlfn.VAR.S(G8:G111) -> 0.16859133
B6: Date | C6: Closing Price | D6: Returns | F6: Closing Price | G6: Returns | I6: Levered Beta | J6: =M7 -> 0.16859133
B7: 45165 | C7: 3259.55 | F7: 24695.9 | I7: Raw Beta Weight | J7: 0.75 | L7: Beta 3 | M7: =M27 -> 0.16859133
B8: 45172 | C8: 3238.05 | D8: =C8/C7-1 -> -0.0065960025 | F8: 24870.1 | G8: =F8/F7-1 -> 0.0070538025
B9: 45179 | C9: 3196.65 | D9: =C9/C8-1 -> -0.012785473 | F9: 24631.3 | G9: =F9/F8-1 -> -0.0096018914 | I9: Market Beta | J9: 1
B10: 45186 | C10: 3274.85 | D10: =C10/C9-1 -> 0.02446311 | F10: 24363.3 | G10: =F10/F9-1 -> -0.010880465 | I10: Market Beta Weight | J10: 0.25 | L10: SUMMARY OUTPUT
B11: 45193 | C11: 3161.05 | D11: =C11/C10-1 -> -0.034749683 | F11: 24565.35 | G11: =F11/F10-1 -> 0.0082932115
B12: 45200 | C12: 3195.75 | D12: =C12/C11-1 -> 0.010977365 | F12: 24837 | G12: =F12/F11-1 -> 0.011058259 | I12: Adjusted Beta | J12: =(J6*J7)+(J9*J10) -> 0.3764435 | L12: Regression Statistics
B13: 45207 | C13: 3148.8 | D13: =C13/C12-1 -> -0.014691387 | F13: 24968.4 | G13: =F13/F12-1 -> 0.005290494 | L13: Multiple R | M13: 0.10866336
B14: 45214 | C14: 3105.85 | D14: =C14/C13-1 -> -0.013640117 | F14: 25149.85 | G14: =F14/F13-1 -> 0.0072671857 | L14: R Square | M14: 0.011807726
B15: 45221 | C15: 2955.15 | D15: =C15/C14-1 -> -0.048521339 | F15: 25461 | G15: =F15/F14-1 -> 0.012371843 | L15: Adjusted R Square | M15: 0.0021195663
B16: 45228 | C16: 2977.85 | D16: =C16/C15-1 -> 0.0076815052 | F16: 25637.8 | G16: =F16/F15-1 -> 0.0069439535 | L16: Standard Error | M16: 0.02674078
B17: 45235 | C17: 3076.45 | D17: =C17/C16-1 -> 0.033111137 | F17: 25112.4 | G17: =F17/F16-1 -> -0.020493178 | L17: Observations | M17: 104
B18: 45242 | C18: 3168.9 | D18: =C18/C17-1 -> 0.03005087 | F18: 24718.6 | G18: =F18/F17-1 -> -0.015681496
B19: 45249 | C19: 3136.15 | D19: =C19/C18-1 -> -0.010334816 | F19: 25003.05 | G19: =F19/F18-1 -> 0.011507529 | L19: ANOVA
B20: 45256 | C20: 3173.4 | D20: =C20/C19-1 -> 0.011877621 | F20: 24750.7 | G20: =F20/F19-1 -> -0.010092769 | M20: df | N20: SS | O20: MS | P20: F | Q20: Significance F
B21: 45263 | C21: 3232 | D21: =C21/C20-1 -> 0.018465999 | F21: 24853.15 | G21: =F21/F20-1 -> 0.0041392769 | L21: Regression | M21: 1 | N21: 0.00087151152 | O21: 0.00087151152 | P21: 1.218779 | Q21: 0.27219801
B22: 45270 | C22: 3313.9 | D22: =C22/C21-1 -> 0.025340347 | F22: 25019.8 | G22: =F22/F21-1 -> 0.0067053874 | L22: Residual | M22: 102 | N22: 0.072937072 | O22: 0.00071506933
B23: 45277 | C23: 3341.3 | D23: =C23/C22-1 -> 0.0082682036 | F23: 24008 | G23: =F23/F22-1 -> -0.040439972 | L23: Total | M23: 103 | N23: 0.073808583
B24: 45284 | C24: 3402.4 | D24: =C24/C23-1 -> 0.018286296 | F24: 24346.7 | G24: =F24/F23-1 -> 0.014107797
B25: 45291 | C25: 3355.55 | D25: =C25/C24-1 -> -0.013769692 | F25: 24039.35 | G25: =F25/F24-1 -> -0.012623887 | M25: Coefficients | N25: Standard Error | O25: t Stat | P25: P-value | Q25: Lower 95% | R25: Upper 95% | S25: Lower 95.0% | T25: Upper 95.0%
B26: 45298 | C26: 3277.8 | D26: =C26/C25-1 -> -0.023170568 | F26: 23851.65 | G26: =F26/F25-1 -> -0.0078080314 | L26: Intercept | M26: -0.0019008789 | N26: 0.002642691 | O26: -0.7192967 | P26: 0.4736029 | Q26: -0.007142644 | R26: 0.0033408861 | S26: -0.007142644 | T26: 0.0033408861
B27: 45305 | C27: 3165.85 | D27: =C27/C26-1 -> -0.034154006 | F27: 22828.55 | G27: =F27/F26-1 -> -0.042894307 | L27: X Variable 1 | M27: 0.16859133 | N27: 0.15271186 | O27: 1.1039833 | P27: 0.27219801 | Q27: -0.13431191 | R27: 0.47149457 | S27: -0.13431191 | T27: 0.47149457
B28: 45312 | C28: 2949.2 | D28: =C28/C27-1 -> -0.068433438 | F28: 22904.45 | G28: =F28/F27-1 -> 0.0033247841
B29: 45319 | C29: 2936.3 | D29: =C29/C28-1 -> -0.0043740675 | F29: 23519.35 | G29: =F29/F28-1 -> 0.026846312
B30: 45326 | C30: 2951.65 | D30: =C30/C29-1 -> 0.0052276675 | F30: 23350.4 | G30: =F30/F29-1 -> -0.0071834468
B31: 45333 | C31: 3007.9 | D31: =C31/C30-1 -> 0.019057138 | F31: 22397.2 | G31: =F31/F30-1 -> -0.040821571
B32: 45340 | C32: 2985.95 | D32: =C32/C31-1 -> -0.00729745 | F32: 22552.5 | G32: =F32/F31-1 -> 0.0069339025
B33: 45347 | C33: 2831.75 | D33: =C33/C32-1 -> -0.051641856 | F33: 22124.7 | G33: =F33/F32-1 -> -0.018969072
B34: 45354 | C34: 2870.55 | D34: =C34/C33-1 -> 0.013701775 | F34: 22795.9 | G34: =F34/F33-1 -> 0.030337135
B35: 45361 | C35: 2867.55 | D35: =C35/C34-1 -> -0.0010450959 | F35: 22929.25 | G35: =F35/F34-1 -> 0.0058497361
B36: 45368 | C36: 2841.5 | D36: =C36/C35-1 -> -0.00908441 | F36: 23559.95 | G36: =F36/F35-1 -> 0.027506351
B37: 45375 | C37: 2846.75 | D37: =C37/C36-1 -> 0.0018476157 | F37: 23508.4 | G37: =F37/F36-1 -> -0.0021880352
B38: 45382 | C38: 2883.45 | D38: =C38/C37-1 -> 0.012891894 | F38: 23092.2 | G38: =F38/F37-1 -> -0.01770431
B39: 45389 | C39: 2854.5 | D39: =C39/C38-1 -> -0.010040056 | F39: 23203.2 | G39: =F39/F38-1 -> 0.0048068179
... B111: 45893 | C111: 2479.9 | D111: =C111/C110-1 -> -0.0098223198 | F111: 19435.3 | G111: =F111/F110-1 -> -0.019407213

Sheet Beta Comps
C3: S.No. | D3: Name | E3: CMP Rs. | F3: Mar Cap Rs.Cr. | G3: Debt Rs.Cr. | H3: Debt / Eq
C4: 1 | D4: Asian Paints | E4: 2487.45 | F4: 238614.8 | G4: 2290.29 | H4: 0.12
C5: 2 | D5: Berger Paints | E5: 526.1 | F5: 61280.41 | G5: 670.27 | H5: 0.11
C6: 3 | D6: Kansai Nerolac | E6: 234.1 | F6: 18926.24 | G6: 296.39 | H6: 0.05
C7: 4 | D7: Akzo Nobel | E7: 3430.9 | F7: 15646.37 | G7: 62.1 | H7: 0.05
C8: 5 | D8: Indigo Paints | E8: 1106 | F8: 5271.68 | G8: 19.7 | H8: 0.02

Sheet Rm
B4: Returns on Markets
B6: Year | C6: Annual | E6: Average Return | F6: =AVERAGE(C7:C31)/100 -> 0.153348
B7: 2000 | C7: -14.65 | E7: Dividend Yield | F7: 1.38% 1
B8: 2001 | C8: -16.18 | E8: Total Market Return | F8: =SUM(F6:F7) -> 0.153348
B9: 2002 | C9: 3.25
B10: 2003 | C10: 71.9
B11: 2004 | C11: 10.68
B12: 2005 | C12: 36.34
B13: 2006 | C13: 39.83
B14: 2007 | C14: 54.77
B15: 2008 | C15: -51.79
B16: 2009 | C16: 75.76
B17: 2010 | C17: 17.95
B18: 2011 | C18: -24.62
B19: 2012 | C19: 27.7
B20: 2013 | C20: 6.76
... B31: 2024 | C31: 8.75

Sheet Intrinsic Growth
B2: ="Instrinsic Growth"&" - "&'Data Sheet'!B1 -> Instrinsic Growth - ASIAN PAINTS LTD
B4: Calculation of ROIC | G4: ='Raw FS'!H2 -> 44256 | H4: ='Raw FS'!I2 -> 44621 | I4: ='Raw FS'!J2 -> 44986 | J4: ='Raw FS'!K2 -> 45352 | K4: ='Raw FS'!L2 -> 45717
B5: Amount in crores
B6: Current Assets
B7: ='Raw FS'!B35 -> Inventories | G7: ='Raw FS'!H35 -> 3799 | H7: ='Raw FS'!I35 -> 6153 | I7: ='Raw FS'!J35 -> 6211 | J7: ='Raw FS'!K35 -> 5923 | K7: ='Raw FS'!L35 -> 6719
B8: ='Raw FS'!B36 -> Trade receivables | G8: ='Raw FS'!H36 -> 2602 | H8: ='Raw FS'!I36 -> 3871 | I8: ='Raw FS'!J36 -> 4637 | J8: ='Raw FS'!K36 -> 4889 | K8: ='Raw FS'!L36 -> 4314
B9: ='Raw FS'!B38 -> Loans n Advances | G9: ='Raw FS'!H38 -> 11 | H9: ='Raw FS'!I38 -> 8 | I9: ='Raw FS'!J38 -> 12 | J9: ='Raw FS'!K38 -> 17 | K9: ='Raw FS'!L38 -> 22
B10: ='[3]Raw FS'!$B$39 -> Other asset items | G10: ='Raw FS'!H39 -> 2555 | H10: ='Raw FS'!I39 -> 2869 | I10: ='Raw FS'!J39 -> 3024 | J10: ='Raw FS'!K39 -> 3555 | K10: ='Raw FS'!L39 -> 3319
B11: Total Current Assets | G11: =SUM(G7:G10) -> 8967 | H11: =SUM(H7:H10) -> 12901 | I11: =SUM(I7:I10) -> 13884 | J11: =SUM(J7:J10) -> 14384 | K11: =SUM(K7:K10) -> 14374
B13: Current Liabilities
B14: ='Raw FS'!B13 -> Trade Payables | G14: ='Raw FS'!H13 -> 3379 | H14: ='Raw FS'!I13 -> 4164 | I14: ='Raw FS'!J13 -> 3635 | J14: ='Raw FS'!K13 -> 3831 | K14: ='Raw FS'!L13 -> 3848
B15: ='Raw FS'!B14 -> Advance from Customers | G15: ='Raw FS'!H14 -> 41 | H15: ='Raw FS'!I14 -> 76 | I15: ='Raw FS'!J14 -> 108 | J15: ='Raw FS'!K14 -> 154 | K15: ='Raw FS'!L14 -> 173
B16: ='Raw FS'!B15 -> Other liability items | G16: ='Raw FS'!H15 -> 2613 | H16: ='Raw FS'!I15 -> 2932 | I16: ='Raw FS'!J15 -> 3657 | J16: ='Raw FS'!K15 -> 4017 | K16: ='Raw FS'!L15 -> 3985
B17: Total Current Liabilities | G17: =SUM(G14:G16) -> 6033 | H17: =SUM(H14:H16) -> 7172 | I17: =SUM(I14:I16) -> 7400 | J17: =SUM(J14:J16) -> 8002 | K17: =SUM(K14:K16) -> 8006
B19: Net Working Capital | G19: =G11-G17 -> 2934 | H19: =H11-H17 -> 5729 | I19: =I11-I17 -> 6484 | J19: =J11-J17 -> 6382 | K19: =K11-K17 -> 6368
B21: Non Current Assets
B22: ='Raw FS'!B19 -> Land | G22: ='Raw FS'!H19 -> 644 | H22: ='Raw FS'!I19 -> 644 | I22: ='Raw FS'!J19 -> 804 | J22: ='Raw FS'!K19 -> 1126 | K22: ='Raw FS'!L19 -> 1050
B23: ='Raw FS'!B20 -> Building | G23: ='Raw FS'!H20 -> 2249 | H23: ='Raw FS'!I20 -> 2325 | I23: ='Raw FS'!J20 -> 2883 | J23: ='Raw FS'!K20 -> 3390 | K23: ='Raw FS'!L20 -> 4136
B24: ='Raw FS'!B21 -> Plant Machinery | G24: ='Raw FS'!H21 -> 4340 | H24: ='Raw FS'!I21 -> 4531 | I24: ='Raw FS'!J21 -> 4825 | J24: ='Raw FS'!K21 -> 5422 | K24: ='Raw FS'!L21 -> 7576
B25: ='Raw FS'!B22 -> Equipments | G25: ='Raw FS'!H22 -> 243 | H25: ='Raw FS'!I22 -> 253 | I25: ='Raw FS'!J22 -> 270 | J25: ='Raw FS'!K22 -> 298 | K25: ='Raw FS'!L22 -> 325
B26: ='Raw FS'!B23 -> Furniture n fittings | G26: ='Raw FS'!H23 -> 99 | H26: ='Raw FS'!I23 -> 113 | I26: ='Raw FS'!J23 -> 146 | J26: ='Raw FS'!K23 -> 175 | K26: ='Raw FS'!L23 -> 203
B27: ='Raw FS'!B24 -> Vehicles | G27: ='Raw FS'!H24 -> 38 | H27: ='Raw FS'!I24 -> 32 | I27: ='Raw FS'!J24 -> 36 | J27: ='Raw FS'!K24 -> 40 | K27: ='Raw FS'!L24 -> 39
B28: ='Raw FS'!B25 -> Intangible Assets | G28: ='Raw FS'!H25 -> 476 | H28: ='Raw FS'!I25 -> 345 | I28: ='Raw FS'!J25 -> 422 | J28: ='Raw FS'!K25 -> 850 | K28: ='Raw FS'!L25 -> 827
B29: ='Raw FS'!B26 -> Other fixed assets | G29: ='Raw FS'!H26 -> 302 | H29: ='Raw FS'!I26 -> 294 | I29: ='Raw FS'!J26 -> 289 | J29: ='Raw FS'!K26 -> 321 | K29: ='Raw FS'!L26 -> 328
B31: Gross Block | G31: =SUM(G22:G30) -> 8391 | H31: =SUM(H22:H30) -> 8537 | I31: =SUM(I22:I30) -> 9675 | J31: =SUM(J22:J30) -> 11622 | K31: =SUM(K22:K30) -> 14484
B32: Accumulated Depreciation | G32: ='Raw FS'!H28 -> 2533 | H32: ='Raw FS'!I28 -> 3019 | I32: ='Raw FS'!J28 -> 3905 | J32: ='Raw FS'!K28 -> 4475 | K32: ='Raw FS'!L28 -> 5264
B33: Net Non Current Assets | G33: =SUM(G31:G32) -> 10924 | H33: =SUM(H31:H32) -> 11556 | I33: =SUM(I31:I32) -> 13580 | J33: =SUM(J31:J32) -> 16097 | K33: =SUM(K31:K32) -> 19748
B35: Invested Capital | G35: =G33+G19 -> 13858 | H35: =H33+H19 -> 17285 | I35: =I33+I19 -> 20064 | J35: =J33+J19 -> 22479 | K35: =K33+K19 -> 26116
B36: EBIT | G36: =HistoricalFS!H18-HistoricalFS!H24 -> 4249.23 | H36: =HistoricalFS!I18-HistoricalFS!I24 -> 6637.19 | I36: =HistoricalFS!J18-HistoricalFS!J24 -> 6021.28 | J36: =HistoricalFS!K18-HistoricalFS!K24 -> 6004.38 | K36: =HistoricalFS!L18-HistoricalFS!L24 -> 5389.87
B38: ROIC | G38: =G36/G35 -> 0.3066265 | H38: =H36/H35 -> 0.38398554 | I38: =I36/I35 -> 0.30010367 | J38: =J36/J35 -> 0.26711064 | K38: =K36/K35 -> 0.20638191
B41: Calculation of Reinvestment Rate | G41: =G4 -> 44256 | H41: =H4 -> 44621 | I41: =I4 -> 44986 | J41: =J4 -> 45352 | K41: =K4 -> 45717
B43: Net Capex | G43: =SUM(HistoricalFS!H82:H83) -> -1681 | H43: =SUM(HistoricalFS!I82:I83) -> -2216 | I43: =SUM(HistoricalFS!J82:J83) -> -3424 | J43: =SUM(HistoricalFS!K82:K83) -> -4187 | K43: =SUM(HistoricalFS!L82:L83) -> -3975
B44: Change in Working Capital | H44: =H19-G19 -> 2795 | I44: =I19-H19 -> 755 | J44: =J19-I19 -> -102 | K44: =K19-J19 -> -14
B46: EBIT | G46: =G36 -> 4249.23 | H46: =H36 -> 6637.19 | I46: =I36 -> 6021.28 | J46: =J36 -> 6004.38 | K46: =K36 -> 5389.87
B47: Marginal Tax Rate | G47: 0.25 | H47: 0.25 | I47: 0.25 | J47: 0.25 | K47: 0.25
B48: EBIT(1-T) | G48: =G46*(1-G47) -> 3186.9225 | H48: =H46*(1-H47) -> 4977.8925 | I48: =I46*(1-I47) -> 4515.96 | J48: =J46*(1-J47) -> 4503.285 | K48: =K46*(1-K47) -> 4042.4025
B50: Reinvestment | H50: =SUM(H43:H44) -> 579 | I50: =SUM(I43:I44) -> -2669 | J50: =SUM(J43:J44) -> -4289 | K50: =SUM(K43:K44) -> -3989
B52: Reinvestment Rate | H52: =H50/H48 -> 0.11631428 | I52: =I50/I48 -> -0.59101498 | J52: =J50/J48 -> -0.95241585 | K52: =K50/K48 -> -0.98678942
J54: 4 Year Average | K54: =AVERAGE(H52:K52) -> -0.60347649
J55: 4 Year Median | K55: =MEDIAN(H52:K52) -> -0.77171541
B57: Calculation of Growth Rate | G57: =G4 -> 44256 | H57: =H4 -> 44621 | I57: =I4 -> 44986 | J57: =J4 -> 45352 | K57: =K4 -> 45717
B59: Reinvestment Rate | H59: =H52 -> 0.11631428 | I59: =I52 -> -0.59101498 | J59: =J52 -> -0.95241585 | K59: =K52 -> -0.98678942
B60: ROIC | H60: =H38 -> 0.38398554 | I60: =I38 -> 0.30010367 | J60: =J38 -> 0.26711064 | K60: =K38 -> 0.20638191
B62: Intrinsic Growth | H62: =H59*H60 -> 0.044663003 | I62: =I59*I60 -> -0.17736576 | J62: =J59*J60 -> -0.2544004 | K62: =K59*K60 -> -0.20365549
J64: 4 Year Average | K64: =AVERAGE(H62:K62) -> -0.14768966
J65: 4 Year Median | K65: =MEDIAN(H62:K62) -> -0.19051062

Sheet DCF
B3: ="DCF Valuation and Sensitivity Analysis"&" - "&'Data Sheet'!B1 -> DCF Valuation and Sensitivity Analysis - ASIAN PAINTS LTD
B4: Amount in crores | F4: 0 | G4: 0.5 | H4: 1.5 | I4: 2.5 | J4: 3.5 | K4: 4.5
B5: Calculation of PV of FCFF | F5: ='Intrinsic Growth'!K4 -> 45717 | G5: =F5+365 -> 46082 | H5: =G5+365 -> 46447 | I5: =H5+365 -> 46812 | J5: =I5+365 -> 47177 | K5: =J5+365 -> 47542
B7: EBIT | F7: ='Intrinsic Growth'!K36 -> 5389.87 | G7: =F7*(1+$E$21) -> 6508.268 | H7: =G7*(1+$E$21) -> 7858.7336 | I7: =H7*(1+$E$21) -> 9489.4209 | J7: =I7*(1+$E$21) -> 11458.476 | K7: =J7*(1+$E$21) -> 13836.109
B9: Tax Rate | F9: 0.25 | G9: =F9 -> 0.25 | H9: =G9 -> 0.25 | I9: =H9 -> 0.25 | J9: =I9 -> 0.25 | K9: =J9 -> 0.25
B11: EBIT (1-T) | F11: =F7*(1-F9) -> 4042.4025 | G11: =G7*(1-G9) -> 4881.201 | H11: =H7*(1-H9) -> 5894.0502 | I11: =I7*(1-I9) -> 7117.0657 | J11: =J7*(1-J9) -> 8593.8568 | K11: =K7*(1-K9) -> 10377.082
B13: Less: Reinvestment Rate | F13: ='Intrinsic Growth'!K55 -> -0.77171541 | G13: =F13 -> -0.77171541 | H13: =G13 -> -0.77171541 | I13: =H13 -> -0.77171541 | J13: =I13 -> -0.77171541 | K13: =J13 -> -0.77171541
B15: Free Cash Flow to Firm | F15: =F11*(1-F13) -> 7161.9868 | G15: =G11*(1-G13) -> 8648.0991 | H15: =H11*(1-H13) -> 10442.58 | I15: =I11*(1-I13) -> 12609.415 | J15: =J11*(1-J13) -> 15225.869 | K15: =K11*(1-K13) -> 18385.236
B17: Discounting Factor | F17: =1/(1+$E$28)^F4 -> 1 | G17: =1/(1+$E$28)^G4 -> 0.93255652 | H17: =1/(1+$E$28)^H4 -> 0.81100865 | I17: =1/(1+$E$28)^I4 -> 0.70530312 | J17: =1/(1+$E$28)^J4 -> 0.61337508 | K17: =1/(1+$E$28)^K4 -> 0.53342879
B19: PV of FCFF | F19: =F17*F15 -> 7161.9868 | G19: =G17*G15 -> 8064.8412 | H19: =H17*H15 -> 8469.0224 | I19: =I17*I15 -> 8893.4597 | J19: =J17*J15 -> 9339.1684 | K19: =K17*K15 -> 9807.2143
B21: Expected Growth | E21: 0.2075
B22: Terminal Growth | E22: 0.064
B25: Calculation of Terminal Value | G25: Sensitivity Analysis
G26: =E44 -> 1977.3551 | H26: 0.13 | I26: 0.14 | J26: =E28 -> 0.14987247 | K26: 0.16 | L26: 0.17
B27: FCFF (n+1) | E27: =K15*(1+E21) -> 22200.173 | G27: 0.04 | H27: 2045.0843 | I27: 1833.5683 | J27: 1833.5683 | K27: 1517.9739 | L27: 1397.3163
B28: WACC | E28: =WACC!J44 -> 0.14987247 | G28: 0.05 | H28: 2230.6564 | I28: 1976.2551 | J28: 1976.2551 | K28: 1607.9368 | L28: 1470.5545
B29: Terminal Growth Rate | E29: =E22 -> 0.064 | G29: =E29 -> 0.064 | H29: 2230.6564 | I29: 1976.2551 | J29: 1976.2551 | K29: 1607.9368 | L29: 1470.5545
G30: 0.07 | H30: 2787.3728 | I30: 2383.9318 | J30: 2383.9318 | K30: 1847.8378 | L30: 1660.9736
B31: Terminal Value | E31: =E27/(E28-E29) -> 258524.9 | G31: 0.08 | H31: 3232.7458 | I31: 2689.6893 | J31: 2689.6893 | K31: 2012.7697 | L31: 1787.9197
B34: Calculation of Enterprise Value
B36: PV of FCFF | E36: =SUM(F19:K19) -> 51735.693
B37: PV of Terminal Value | E37: =E31*K17 -> 137904.63
B38: Value of Operating Asset | E38: =SUM(E36:E37) -> 189640.32
B40: Add: Cash | E40: =HistoricalFS!L62 -> 781.98
B41: Less: Debt | E41: =SUM('Raw FS'!L7:L8) -> 864
B42: Value of Equity | E42: =(E38+E40)-E41 -> 189558.3
B43: No. of Shares | E43: ='Data Sheet'!B6 -> 95.864573
B44: Value per Share | E44: =E42/E43 -> 1977.3551

Sheet Comps_Val
B2: Amount in crores
B3: Comparable Company Valuation
D5: Market Data | K5: Financials | O5: Valuation
B6: Company | C6: Ticker | D6: Share Price | E6: Shares Outstanding | F6: Equity Value | G6: Net Debt | H6: Enterprise Value | K6: Revenue | L6: EBITDA | M6: Net Income | O6: EV/Revenue | P6: EV/EBITDA | Q6: P/E
B8: =Data!C3 -> Asian Paints | D8: =Data!D3 -> 2518.6 | E8: =Data!E3 -> 95.92 | F8: =E8*D8 -> 241584.11 | G8: =Data!I3 -> 1508.31 | H8: =+F8+G8 -> 243092.42 | K8: =Data!K3 -> 33874.44 | L8: =Data!L3 -> 6686.91 | M8: =Data!O3 -> 3639.97 | O8: =$H8/K8 -> 7.1762787 | P8: =$H8/L8 -> 36.353476 | Q8: =F8/M8 -> 66.369809
B9: =Data!C4 -> Berger Paints | D9: =Data!D4 -> 533 | E9: =Data!E4 -> 116.59 | F9: =E9*D9 -> 62142.47 | G9: =Data!I4 -> 169.79 | H9: =+F9+G9 -> 62312.26 | K9: =Data!K4 -> 11654.46 | L9: =Data!L4 -> 1985.61 | M9: =Data!O4 -> 1143.82 | O9: =$H9/K9 -> 5.346645 | P9: =$H9/L9 -> 31.381923 | Q9: =F9/M9 -> 54.328889
B10: =Data!C5 -> Kansai Nerolac | D10: =Data!D5 -> 239.99 | E10: =Data!E5 -> 80.85 | F10: =E10*D10 -> 19403.192 | G10: =Data!I5 -> 6.33 | H10: =+F10+G10 -> 19409.522 | K10: =Data!K5 -> 7851.94 | L10: =Data!L5 -> 1073.79 | M10: =Data!O5 -> 1100.05 | O10: =$H10/K10 -> 2.4719396 | P10: =$H10/L10 -> 18.075715 | Q10: =F10/M10 -> 17.638463
B11: =Data!C6 -> Akzo Nobel | D11: =Data!D6 -> 3410.6 | E11: =Data!E6 -> 4.55 | F11: =E11*D11 -> 15518.23 | G11: =Data!I6 -> -237.4 | H11: =+F11+G11 -> 15280.83 | K11: =Data!K6 -> 4050 | L11: =Data!L6 -> 633.7 | M11: =Data!O6 -> 405 | O11: =$H11/K11 -> 3.7730444 | P11: =$H11/L11 -> 24.113666 | Q11: =F11/M11 -> 38.316617
B12: =Data!C7 -> Indigo Paints | D12: =Data!D7 -> 1099.7 | E12: =Data!E7 -> 4.76 | F12: =E12*D12 -> 5234.572 | G12: =Data!I7 -> -17.4 | H12: =+F12+G12 -> 5217.172 | K12: =Data!K7 -> 1278.1 | L12: =Data!L7 -> 248.54 | M12: =Data!O7 -> 143.84 | O12: =$H12/K12 -> 4.0819748 | P12: =$H12/L12 -> 20.991277 | Q12: =F12/M12 -> 36.39163
B13: =Data!C8 -> Sirca Paints | D13: =Data!D8 -> 462.75 | E13: =Data!E8 -> 5.48 | F13: =E13*D13 -> 2535.87 | G13: =Data!I8 -> -54.16 | H13: =+F13+G13 -> 2481.71 | K13: =Data!K8 -> 409.37 | L13: =Data!L8 -> 79.9 | M13: =Data!O8 -> 53.11 | O13: =$H13/K13 -> 6.0622664 | P13: =$H13/L13 -> 31.0602 | Q13: =F13/M13 -> 47.747505
B14: =Data!C9 -> Shalimar Paints | D14: =Data!D9 -> 71.73 | E14: =Data!E9 -> 8.37 | F14: =E14*D14 -> 600.3801 | G14: =Data!I9 -> 118.39 | H14: =+F14+G14 -> 718.7701 | K14: =Data!K9 -> 624.19 | L14: =Data!L9 -> -32.52 | M14: =Data!O9 -> -69.79 | O14: =$H14/K14 -> 1.1515245 | P14: =$H14/L14 -> -22.102402 | Q14: =F14/M14 -> -8.6026666
B15: =Data!C10 -> Kamdhenu Venture | D15: =Data!D10 -> 10.21 | E15: =Data!E10 -> 31.44 | F15: =E15*D15 -> 321.0024 | G15: =Data!I10 -> 21.08 | H15: =+F15+G15 -> 342.0824 | K15: =Data!K10 -> 261.89 | L15: =Data!L10 -> 16.77 | M15: =Data!O10 -> 5.94 | O15: =$H15/K15 -> 1.3062064 | P15: =$H15/L15 -> 20.398473 | Q15: =F15/M15 -> 54.040808
B16: =Data!C11 -> Siddhika Coatins | D16: =Data!D11 -> 190 | E16: =Data!E11 -> 0.62 | F16: =E16*D16 -> 117.8 | G16: =Data!I11 -> -5.76 | H16: =+F16+G16 -> 112.04 | K16: =Data!K11 -> 48.01 | L16: =Data!L11 -> 10.44 | M16: =Data!O11 -> 8.03 | O16: =$H16/K16 -> 2.3336805 | P16: =$H16/L16 -> 10.731801 | Q16: =F16/M16 -> 14.669988
B17: =Data!C12 -> Retina Paints | D17: =Data!D12 -> 76.5 | E17: =Data!E12 -> 1.53 | F17: =E17*D17 -> 117.045 | G17: =Data!I12 -> 7.76 | H17: =+F17+G17 -> 124.805 | K17: =Data!K12 -> 11.66 | L17: =Data!L12 -> 2.02 | M17: =Data!O12 -> 0.74 | O17: =$H17/K17 -> 10.703688 | P17: =$H17/L17 -> 61.784653 | Q17: =F17/M17 -> 158.16892
B19: High | O19: =MAX(O8:O17) -> 10.703688 | P19: =MAX(P8:P17) -> 61.784653 | Q19: =MAX(Q8:Q17) -> 158.16892
B20: 75th Percentile | O20: =QUARTILE(O8:O17,3) -> 5.8833611 | P20: =QUARTILE(P8:P17,3) -> 31.301492 | Q20: =QUARTILE(Q8:Q17,3) -> 54.256869
B21: Average | O21: =AVERAGE(O8:O17) -> 4.4407248 | P21: =AVERAGE(P8:P17) -> 23.278878 | Q21: =AVERAGE(Q8:Q17) -> 47.906996
B22: Median | O22: =MEDIAN(O8:O17) -> 3.9275096 | P22: =MEDIAN(P8:P17) -> 22.552471 | Q22: =MEDIAN(Q8:Q17) -> 43.032061
B23: 25th Percentile | O23: =QUARTILE(O8:O17,1) -> 2.3682453 | P23: =QUARTILE(P8:P17,1) -> 18.656404 | Q23: =QUARTILE(Q8:Q17,1) -> 22.326755
B24: Low | O24: =MIN(O8:O17) -> 1.1515245 | P24: =MIN(P8:P17) -> -22.102402 | Q24: =MIN(Q8:Q17) -> -8.6026666
B26: Asian Paints Comparable Valuation | O26: EV/Revenue | P26: EV/EBITDA | Q26: P/E
B28: Implied Enterprise Value | O28: =O$22*K8 -> 133042.19 | P28: =P$22*L8 -> 150806.35 | Q28: =+Q30+Q29 -> 158143.72
B29: Net Debt | O29: =$G$8 -> 1508.31 | P29: =$G$8 -> 1508.31 | Q29: =$G$8 -> 1508.31
B30: Implied Market Value | O30: =O28-O29 -> 131533.88 | P30: =P28-P29 -> 149298.04 | Q30: =Q22*M8 -> 156635.41
B31: Shares Outstanding | O31: =$E$8 -> 95.92 | P31: =$E$8 -> 95.92 | Q31: =$E$8 -> 95.92
B33: Implied Value per Share | O33: =O30/O31 -> 1371.2873 | P33: =P30/P31 -> 1556.485 | Q33: =Q30/Q31 -> 1632.9797
B35: Source: Screener.in
O36: =IF(O33>$D$8,"Undervalued","Overvalued") -> Overvalued | P36: =IF(P33>$D$8,"Undervalued","Overvalued") -> Overvalued | Q36: =IF(Q33>$D$8,"Undervalued","Overvalued") -> Overvalued

Sheet Football Field Analysis
B4: ="Football Field Analysis"&" - "&'Data Sheet'!B1 -> Football Field Analysis - ASIAN PAINTS LTD
B23: Football Field Analysis - Data
C24: Open Low | D24: Low | E24: Open High | F24: High
B25: Comps | C25: =Comps_Val!O33 -> 1371.2873 | D25: =C25 -> 1371.2873 | E25: =Comps_Val!Q33 -> 1632.9797 | F25: =E25 -> 1632.9797
B26: DCF Bear | C26: 1396.512 | D26: 1396.512 | E26: 1786.8905 | F26: 1786.8905
B27: DCF Base | C27: 1832.5129 | D27: 1832.5129 | E27: 2688.141 | F27: 2688.141
B28: DCF Bull | C28: 2043.9071 | D28: 2043.9071 | E28: 3230.885 | F28: 3230.885
B29: 52W H/L | C29: 2124.75 | D29: 2124.75 | E29: 3394.9 | F29: 3394.9

Sheet Ratio Analysis
B2: ="Ratio Analysis - "&'Data Sheet'!B1 -> Ratio Analysis - ASIAN PAINTS LTD
B3: Years | C3: ='Data Sheet'!B16 -> 42460 | D3: ='Data Sheet'!C16 -> 42825 | E3: ='Data Sheet'!D16 -> 43190 | F3: ='Data Sheet'!E16 -> 43555 | G3: ='Data Sheet'!F16 -> 43921 | H3: ='Data Sheet'!G16 -> 44286 | I3: ='Data Sheet'!H16 -> 44651 | J3: ='Data Sheet'!I16 -> 45016 | ... L3: ='Data Sheet'!K16 -> 45747 | M3: Trend | N3: Mean | O3: Median
B5: SalesGrowth | D5: =IFERROR(HistoricalFS!D7,0) -> 0.055390152 | E5: =IFERROR(HistoricalFS!E7,0) -> 0.11702039 | F5: =IFERROR(HistoricalFS!F7,0) -> 0.14357472 | G5: =IFERROR(HistoricalFS!G7,0) -> 0.050473671 | H5: =IFERROR(HistoricalFS!H7,0) -> 0.074292288 | I5: =IFERROR(HistoricalFS!I7,0) -> 0.34028285 | J5: =IFERROR(HistoricalFS!J7,0) -> 0.18512278 | K5: =IFERROR(HistoricalFS!K7,0) -> 0.029173127 | L5: =IFERROR(HistoricalFS!L7,0) -> -0.044770308 | N5: =IFERROR(AVERAGE(D5:L5),0) -> 0.10561774 | O5: =IFERROR(MEDIAN(C5:L5),0) -> 0.074292288
B6: EBITDA Growth | D6: =IFERROR(HistoricalFS!D18/HistoricalFS!C18-1,0) -> 0.74131483 | E6: =IFERROR(HistoricalFS!E18/HistoricalFS!D18-1,0) -> -0.27924492 | F6: =IFERROR(HistoricalFS!F18/HistoricalFS!E18-1,0) -> 0.49035363 | G6: =IFERROR(HistoricalFS!G18/HistoricalFS!F18-1,0) -> 0.065187316 | H6: =IFERROR(HistoricalFS!H18/HistoricalFS!G18-1,0) -> 0.087458361 | I6: =IFERROR(HistoricalFS!I18/HistoricalFS!H18-1,0) -> 0.47873227 | J6: =IFERROR(HistoricalFS!J18/HistoricalFS!I18-1,0) -> -0.077043825 | K6: =IFERROR(HistoricalFS!K18/HistoricalFS!J18-1,0) -> -0.0031863707 | L6: =IFERROR(HistoricalFS!L18/HistoricalFS!K18-1,0) -> -0.064335067 | N6: =IFERROR(AVERAGE(D6:L6),0) -> 0.15991514 | O6: =IFERROR(MEDIAN(C6:L6),0) -> 0.065187316
B7: EBIT Growth | D7: =IFERROR(HistoricalFS!D27/HistoricalFS!C27-1,0) -> 0.83776601 | E7: =IFERROR(HistoricalFS!E27/HistoricalFS!D27-1,0) -> -0.31559676 | F7: =IFERROR(HistoricalFS!F27/HistoricalFS!E27-1,0) -> 0.43730067 | G7: =IFERROR(HistoricalFS!G27/HistoricalFS!F27-1,0) -> 0.036873592 | H7: =IFERROR(HistoricalFS!H27/HistoricalFS!G27-1,0) -> 0.1080167 | I7: =IFERROR(HistoricalFS!I27/HistoricalFS!H27-1,0) -> 0.57345103 | J7: =IFERROR(HistoricalFS!J27/HistoricalFS!I27-1,0) -> -0.10164665 | K7: =IFERROR(HistoricalFS!K27/HistoricalFS!J27-1,0) -> -0.013207801 | L7: =IFERROR(HistoricalFS!L27/HistoricalFS!K27-1,0) -> -0.10973219 | N7: =IFERROR(AVERAGE(D7:L7),0) -> 0.1614694 | O7: =IFERROR(MEDIAN(C7:L7),0) -> 0.036873592
B8: Net Profit Growth | D8: =IFERROR(HistoricalFS!D33/HistoricalFS!C33-1,0) -> 1.3637141 | E8: =IFERROR(HistoricalFS!E33/HistoricalFS!D33-1,0) -> -0.46012685 | F8: =IFERROR(HistoricalFS!F33/HistoricalFS!E33-1,0) -> 0.70686935 | G8: =IFERROR(HistoricalFS!G33/HistoricalFS!F33-1,0) -> 0.14941744 | H8: =IFERROR(HistoricalFS!H33/HistoricalFS!G33-1,0) -> 0.056104699 | I8: =IFERROR(HistoricalFS!I33/HistoricalFS!H33-1,0) -> 0.7774085 | J8: =IFERROR(HistoricalFS!J33/HistoricalFS!I33-1,0) -> -0.1940734 | K8: =IFERROR(HistoricalFS!K33/HistoricalFS!J33-1,0) -> -0.085368886 | L8: =IFERROR(HistoricalFS!L33/HistoricalFS!K33-1,0) -> -0.059773567 | N8: =IFERROR(AVERAGE(D8:L8),0) -> 0.25046349 | O8: =IFERROR(MEDIAN(C8:L8),0) -> 0.056104699
B9: Dividend Growth | D9: =IFERROR(HistoricalFS!D41/HistoricalFS!C41-1,0) -> 0.37333889 | E9: =IFERROR(HistoricalFS!E41/HistoricalFS!D41-1,0) -> -0.15534727 | F9: =IFERROR(HistoricalFS!F41/HistoricalFS!E41-1,0) -> 0.20690234 | G9: =IFERROR(HistoricalFS!G41/HistoricalFS!F41-1,0) -> 0.14285714 | H9: =IFERROR(HistoricalFS!H41/HistoricalFS!G41-1,0) -> 0.48749826 | I9: =IFERROR(HistoricalFS!I41/HistoricalFS!H41-1,0) -> 0.072831553 | J9: =IFERROR(HistoricalFS!J41/HistoricalFS!I41-1,0) -> 0.33942522 | K9: =IFERROR(HistoricalFS!K41/HistoricalFS!J41-1,0) -> 0.29824618 | L9: =IFERROR(HistoricalFS!L41/HistoricalFS!K41-1,0) -> -0.25525494 | N9: =IFERROR(AVERAGE(D9:L9),0) -> 0.16783304 | O9: =IFERROR(MEDIAN(C9:L9),0) -> 0.20690234
B11: Gross Margin | C11: =IFERROR(HistoricalFS!C13,0) -> 0.3124404 | D11: =IFERROR(HistoricalFS!D13,0) -> 0.42401635 | E11: =IFERROR(HistoricalFS!E13,0) -> 0.31775709 | F11: =IFERROR(HistoricalFS!F13,0) -> 0.35970859 | G11: =IFERROR(HistoricalFS!G13,0) -> 0.37264048 | H11: =IFERROR(HistoricalFS!H13,0) -> 0.36211929 | I11: =IFERROR(HistoricalFS!I13,0) -> 0.38351062 | J11: =IFERROR(HistoricalFS!J13,0) -> 0.32884354 | ... L11: =IFERROR(HistoricalFS!L13,0) -> 0.34136966 | N11: =IFERROR(AVERAGE(C11:L11),0) -> 0.35336422 | O11: =IFERROR(MEDIAN(C11:L11),0) -> 0.35053912
B12: EBITDA Margin | C12: =IFERROR(HistoricalFS!C19,0) -> 0.16300891 | D12: =IFERROR(HistoricalFS!D19,0) -> 0.26895251 | E12: =IFERROR(HistoricalFS!E19,0) -> 0.17354105 | F12: =IFERROR(HistoricalFS!F19,0) -> 0.22616583 | G12: =IFERROR(HistoricalFS!G19,0) -> 0.22933366 | H12: =IFERROR(HistoricalFS!H19,0) -> 0.23214428 | I12: =IFERROR(HistoricalFS!I19,0) -> 0.25612447 | J12: =IFERROR(HistoricalFS!J19,0) -> 0.19946597 | ... L12: =IFERROR(HistoricalFS!L19,0) -> 0.18923736 | N12: =IFERROR(AVERAGE(C12:L12),0) -> 0.21311684 | O12: =IFERROR(MEDIAN(C12:L12),0) -> 0.2128159
B13: EBIT Margin | C13: =IFERROR((HistoricalFS!C18-HistoricalFS!C24)/HistoricalFS!C6,0) -> 0.14369908 | D13: =IFERROR((HistoricalFS!D18-HistoricalFS!D24)/HistoricalFS!D6,0) -> 0.24672503 | E13: =IFERROR((HistoricalFS!E18-HistoricalFS!E24)/HistoricalFS!E6,0) -> 0.15211581 | F13: =IFERROR((HistoricalFS!F18-HistoricalFS!F24)/HistoricalFS!F6,0) -> 0.19383029 | G13: =IFERROR((HistoricalFS!G18-HistoricalFS!G24)/HistoricalFS!G6,0) -> 0.19071656 | H13: =IFERROR((HistoricalFS!H18-HistoricalFS!H24)/HistoricalFS!H6,0) -> 0.1957017 | I13: =IFERROR((HistoricalFS!I18-HistoricalFS!I24)/HistoricalFS!I6,0) -> 0.2280721 | J13: =IFERROR((HistoricalFS!J18-HistoricalFS!J24)/HistoricalFS!J6,0) -> 0.1745876 | ... L13: =IFERROR((HistoricalFS!L18-HistoricalFS!L24)/HistoricalFS!L6,0) -> 0.15896686 | N13: =IFERROR(AVERAGE(C13:L13),0) -> 0.18535776 | O13: =IFERROR(MEDIAN(C13:L13),0) -> 0.18265208
B14: EBT Margin | C14: =IFERROR(HistoricalFS!C28,0) -> 0.14026566 | D14: =IFERROR(HistoricalFS!D28,0) -> 0.24424661 | E14: =IFERROR(HistoricalFS!E28,0) -> 0.14965096 | F14: =IFERROR(HistoricalFS!F28,0) -> 0.18808865 | G14: =IFERROR(HistoricalFS!G28,0) -> 0.18565353 | H14: =IFERROR(HistoricalFS!H28,0) -> 0.19148161 | I14: =IFERROR(HistoricalFS!I28,0) -> 0.22479355 | J14: =IFERROR(HistoricalFS!J28,0) -> 0.17039925 | ... L14: =IFERROR(HistoricalFS!L28,0) -> 0.15227122 | N14: =IFERROR(AVERAGE(C14:L14),0) -> 0.18102333 | O14: =IFERROR(MEDIAN(C14:L14),0) -> 0.17802639
B15: Net Profit Margin | C15: =IFERROR(HistoricalFS!C34,0) -> 0.081092444 | D15: =IFERROR(HistoricalFS!D34,0) -> 0.18161943 | E15: =IFERROR(HistoricalFS!E34,0) -> 0.087779465 | F15: =IFERROR(HistoricalFS!F34,0) -> 0.13101731 | G15: =IFERROR(HistoricalFS!G34,0) -> 0.14335778 | H15: =IFERROR(HistoricalFS!H34,0) -> 0.14093076 | I15: =IFERROR(HistoricalFS!I34,0) -> 0.18689453 | J15: =IFERROR(HistoricalFS!J34,0) -> 0.12709508 | ... L15: =IFERROR(HistoricalFS!L34,0) -> 0.11117596 | N15: =IFERROR(AVERAGE(C15:L15),0) -> 0.13039128 | O15: =IFERROR(MEDIAN(C15:L15),0) -> 0.12905619
B17: SalesExpenses%Sales | C17: =IFERROR(HistoricalFS!C16,0) -> 0.14943149 | D17: =IFERROR(HistoricalFS!D16,0) -> 0.15506384 | E17: =IFERROR(HistoricalFS!E16,0) -> 0.14421604 | F17: =IFERROR(HistoricalFS!F16,0) -> 0.13354276 | G17: =IFERROR(HistoricalFS!G16,0) -> 0.14330682 | H17: =IFERROR(HistoricalFS!H16,0) -> 0.12997501 | I17: =IFERROR(HistoricalFS!I16,0) -> 0.12738615 | J17: =IFERROR(HistoricalFS!J16,0) -> 0.12937757 | ... L17: =IFERROR(HistoricalFS!L16,0) -> 0.1521323 | N17: =IFERROR(AVERAGE(C17:L17),0) -> 0.14024739 | O17: =IFERROR(MEDIAN(C17:L17),0) -> 0.14067436
B18: Depreciation%Sales | C18: =IFERROR(HistoricalFS!C25,0) -> 0.019309827 | D18: =IFERROR(HistoricalFS!D25,0) -> 0.022227475 | E18: =IFERROR(HistoricalFS!E25,0) -> 0.021425239 | F18: =IFERROR(HistoricalFS!F25,0) -> 0.03233554 | G18: =IFERROR(HistoricalFS!G25,0) -> 0.038617107 | H18: =IFERROR(HistoricalFS!H25,0) -> 0.036442576 | I18: =IFERROR(HistoricalFS!I25,0) -> 0.028052374 | J18: =IFERROR(HistoricalFS!J25,0) -> 0.024878373 | ... L18: =IFERROR(HistoricalFS!L25,0) -> 0.030270498 | N18: =IFERROR(AVERAGE(C18:L18),0) -> 0.027759074 | O18: =IFERROR(MEDIAN(C18:L18),0) -> 0.026465374
B19: OperatingIncome%Sales | C19: =C13 -> 0.14369908 | D19: =D13 -> 0.24672503 | E19: =E13 -> 0.15211581 | F19: =F13 -> 0.19383029 | G19: =G13 -> 0.19071656 | H19: =H13 -> 0.1957017 | I19: =I13 -> 0.2280721 | J19: =J13 -> 0.1745876 | ... L19: =L13 -> 0.15896686 | N19: =IFERROR(AVERAGE(C19:L19),0) -> 0.18535776 | O19: =IFERROR(MEDIAN(C19:L19),0) -> 0.18265208
B21: Return on Capital Employed | C21: =IFERROR((HistoricalFS!C18-HistoricalFS!C24)/(SUM(HistoricalFS!C48:C50)),0) -> 0.29946949 | D21: =IFERROR((HistoricalFS!D18-HistoricalFS!D24)/(SUM(HistoricalFS!D48:D50)),0) -> 0.45517703 | E21: =IFERROR((HistoricalFS!E18-HistoricalFS!E24)/(SUM(HistoricalFS!E48:E50)),0) -> 0.28615578 | F21: =IFERROR((HistoricalFS!F18-HistoricalFS!F24)/(SUM(HistoricalFS!F48:F50)),0) -> 0.34562263 | G21: =IFERROR((HistoricalFS!G18-HistoricalFS!G24)/(SUM(HistoricalFS!G48:G50)),0) -> 0.34267371 | H21: =IFERROR((HistoricalFS!H18-HistoricalFS!H24)/(SUM(HistoricalFS!H48:H50)),0) -> 0.30571298 | I21: =IFERROR((HistoricalFS!I18-HistoricalFS!I24)/(SUM(HistoricalFS!I48:I50)),0) -> 0.43103003 | J21: =IFERROR((HistoricalFS!J18-HistoricalFS!J24)/(SUM(HistoricalFS!J48:J50)),0) -> 0.33591801 | ... L21: =IFERROR((HistoricalFS!L18-HistoricalFS!L24)/(SUM(HistoricalFS!L48:L50)),0) -> 0.24849447 | N21: =IFERROR(AVERAGE(C21:L21),0) -> 0.33334438 | O21: =IFERROR(MEDIAN(C21:L21),0) -> 0.32081549
B22: Retained Earnings% | C22: =IFERROR(HistoricalFS!C44,0) -> 0.37838608 | D22: =IFERROR(HistoricalFS!D44,0) -> 0.6388368 | E22: =IFERROR(HistoricalFS!E44,0) -> 0.434946 | F22: =IFERROR(HistoricalFS!F44,0) -> 0.60045859 | G22: =IFERROR(HistoricalFS!G44,0) -> 0.60273897 | H22: =IFERROR(HistoricalFS!H44,0) -> 0.44046732 | I22: =IFERROR(HistoricalFS!I44,0) -> 0.66226992 | J22: =IFERROR(HistoricalFS!J44,0) -> 0.438703 | ... L22: =IFERROR(HistoricalFS!L44,0) -> 0.36892789 | N22: =IFERROR(AVERAGE(C22:L22),0) -> 0.47690181 | O22: =IFERROR(MEDIAN(C22:L22),0) -> 0.43958516
B23: Return on Equity% | C23: =IFERROR(HistoricalFS!C38/SUM(HistoricalFS!C48:C49),0) -> 0.0018491494 | D23: =IFERROR(HistoricalFS!D38/SUM(HistoricalFS!D48:D49),0) -> 0.0037505906 | E23: =IFERROR(HistoricalFS!E38/SUM(HistoricalFS!E48:E49),0) -> 0.0018307091 | F23: =IFERROR(HistoricalFS!F38/SUM(HistoricalFS!F48:F49),0) -> 0.0027749317 | G23: =IFERROR(HistoricalFS!G38/SUM(HistoricalFS!G48:G49),0) -> 0.0029818719 | H23: =IFERROR(HistoricalFS!H38/SUM(HistoricalFS!H48:H49),0) -> 0.0024910872 | I23: =IFERROR(HistoricalFS!I38/SUM(HistoricalFS!I48:I49),0) -> 0.0041054123 | J23: =IFERROR(HistoricalFS!J38/SUM(HistoricalFS!J48:J49),0) -> 0.0028574982 | ... L23: =IFERROR(HistoricalFS!L38/SUM(HistoricalFS!L48:L49),0) -> 0.0020257038 | N23: =IFERROR(AVERAGE(C23:L23),0) -> 0.0026898689 | O23: =IFERROR(MEDIAN(C23:L23),0) -> 0.0026330094
B24: Self Sustained Growth Rate | C24: =IFERROR(C22*C23,0) -> 0.0006996924 | D24: =IFERROR(D22*D23,0) -> 0.0023960153 | E24: =IFERROR(E22*E23,0) -> 0.00079625961 | F24: =IFERROR(F22*F23,0) -> 0.0016662316 | G24: =IFERROR(G22*G23,0) -> 0.0017972904 | H24: =IFERROR(H22*H23,0) -> 0.0010972425 | I24: =IFERROR(I22*I23,0) -> 0.002718891 | J24: =IFERROR(J22*J23,0) -> 0.001253593 | ... L24: =IFERROR(L22*L23,0) -> 0.00074733864 | N24: =IFERROR(AVERAGE(C24:L24),0) -> 0.0013626229 | O24: =IFERROR(MEDIAN(C24:L24),0) -> 0.0011754178
B25: Interest Coverage Ratio | C25: =IFERROR((HistoricalFS!C18-HistoricalFS!C24)/HistoricalFS!C21,0) -> 41.853061 | D25: =IFERROR((HistoricalFS!D18-HistoricalFS!D24)/HistoricalFS!D21,0) -> 99.549156 | E25: =IFERROR((HistoricalFS!E18-HistoricalFS!E24)/HistoricalFS!E21,0) -> 61.71401 | F25: =IFERROR((HistoricalFS!F18-HistoricalFS!F24)/HistoricalFS!F21,0) -> 33.758668 | G25: =IFERROR((HistoricalFS!G18-HistoricalFS!G24)/HistoricalFS!G21,0) -> 37.668523 | H25: =IFERROR((HistoricalFS!H18-HistoricalFS!H24)/HistoricalFS!H21,0) -> 46.373786 | I25: =IFERROR((HistoricalFS!I18-HistoricalFS!I24)/HistoricalFS!I21,0) -> 69.56493 | J25: =IFERROR((HistoricalFS!J18-HistoricalFS!J24)/HistoricalFS!J21,0) -> 41.684181 | ... L25: =IFERROR((HistoricalFS!L18-HistoricalFS!L24)/HistoricalFS!L21,0) -> 23.741829 | N25: =IFERROR(AVERAGE(C25:L25),0) -> 48.517353 | O25: =IFERROR(MEDIAN(C25:L25),0) -> 41.768621
B27: Debtor Turnover Ratio | C27: =IFERROR(HistoricalFS!C6/HistoricalFS!C60,0) -> 12.02478 | D27: =IFERROR(HistoricalFS!D6/HistoricalFS!D60,0) -> 10.411994 | E27: =IFERROR(HistoricalFS!E6/HistoricalFS!E60,0) -> 9.7216332 | F27: =IFERROR(HistoricalFS!F6/HistoricalFS!F60,0) -> 10.087468 | G27: =IFERROR(HistoricalFS!G6/HistoricalFS!G60,0) -> 11.258369 | H27: =IFERROR(HistoricalFS!H6/HistoricalFS!H60,0) -> 8.344109 | I27: =IFERROR(HistoricalFS!I6/HistoricalFS!I60,0) -> 7.5169136 | J27: =IFERROR(HistoricalFS!J6/HistoricalFS!J60,0) -> 7.4377909 | ... L27: =IFERROR(HistoricalFS!L6/HistoricalFS!L60,0) -> 7.8600767 | N27: =IFERROR(AVERAGE(C27:L27),0) -> 9.1923181 | O27: =IFERROR(MEDIAN(C27:L27),0) -> 9.0328711
B28: Creditor Turnover Ratio | C28: =IFERROR(HistoricalFS!C6/HistoricalFS!C51,0) -> 3.8458091 | D28: =IFERROR(HistoricalFS!D6/HistoricalFS!D51,0) -> 3.551552 | E28: =IFERROR(HistoricalFS!E6/HistoricalFS!E51,0) -> 3.4907009 | F28: =IFERROR(HistoricalFS!F6/HistoricalFS!F51,0) -> 3.524679 | G28: =IFERROR(HistoricalFS!G6/HistoricalFS!G51,0) -> 4.1337633 | H28: =IFERROR(HistoricalFS!H6/HistoricalFS!H51,0) -> 3.3632319 | I28: =IFERROR(HistoricalFS!I6/HistoricalFS!I51,0) -> 3.8493808 | J28: =IFERROR(HistoricalFS!J6/HistoricalFS!J51,0) -> 4.390945 | ... L28: =IFERROR(HistoricalFS!L6/HistoricalFS!L51,0) -> 3.9128717 | N28: =IFERROR(AVERAGE(C28:L28),0) -> 3.8143684 | O28: =IFERROR(MEDIAN(C28:L28),0) -> 3.8475949
B29: Inventory Turnover | C29: =IFERROR(HistoricalFS!C6/HistoricalFS!C61,0) -> 7.14203 | D29: =IFERROR(HistoricalFS!D6/HistoricalFS!D61,0) -> 5.7336635 | E29: =IFERROR(HistoricalFS!E6/HistoricalFS!E61,0) -> 6.3290399 | F29: =IFERROR(HistoricalFS!F6/HistoricalFS!F61,0) -> 6.1082493 | G29: =IFERROR(HistoricalFS!G6/HistoricalFS!G61,0) -> 5.9623548 | H29: =IFERROR(HistoricalFS!H6/HistoricalFS!H61,0) -> 5.715998 | I29: =IFERROR(HistoricalFS!I6/HistoricalFS!I61,0) -> 4.7296237 | J29: =IFERROR(HistoricalFS!J6/HistoricalFS!J61,0) -> 5.5531459 | ... L29: =IFERROR(HistoricalFS!L6/HistoricalFS!L61,0) -> 5.0460273 | N29: =IFERROR(AVERAGE(C29:L29),0) -> 5.8312412 | O29: =IFERROR(MEDIAN(C29:L29),0) -> 5.8480092
B30: Fixed Asset Turnover | C30: =IFERROR(HistoricalFS!C6/HistoricalFS!C54,0) -> 4.1774086 | D30: =IFERROR(HistoricalFS!D6/HistoricalFS!D54,0) -> 4.5590724 | E30: =IFERROR(HistoricalFS!E6/HistoricalFS!E54,0) -> 4.5078961 | F30: =IFERROR(HistoricalFS!F6/HistoricalFS!F54,0) -> 2.9615874 | G30: =IFERROR(HistoricalFS!G6/HistoricalFS!G54,0) -> 3.2222977 | H30: =IFERROR(HistoricalFS!H6/HistoricalFS!H54,0) -> 3.7061903 | I30: =IFERROR(HistoricalFS!I6/HistoricalFS!I54,0) -> 5.2728689 | J30: =IFERROR(HistoricalFS!J6/HistoricalFS!J54,0) -> 5.9767488 | ... L30: =IFERROR(HistoricalFS!L6/HistoricalFS!L54,0) -> 3.6773592 | N30: =IFERROR(AVERAGE(C30:L30),0) -> 4.3028075 | O30: =IFERROR(MEDIAN(C30:L30),0) -> 4.3426524
B31: Capital Turnover Ratio | C31: =IFERROR(HistoricalFS!C6/SUM(HistoricalFS!C48:C49),0) -> 2.1872619 | D31: =IFERROR(HistoricalFS!D6/SUM(HistoricalFS!D48:D49),0) -> 1.9808269 | E31: =IFERROR(HistoricalFS!E6/SUM(HistoricalFS!E48:E49),0) -> 2.0004863 | F31: =IFERROR(HistoricalFS!F6/SUM(HistoricalFS!F48:F49),0) -> 2.0315747 | G31: =IFERROR(HistoricalFS!G6/SUM(HistoricalFS!G48:G49),0) -> 1.995156 | H31: =IFERROR(HistoricalFS!H6/SUM(HistoricalFS!H48:H49),0) -> 1.6954785 | I31: =IFERROR(HistoricalFS!I6/SUM(HistoricalFS!I48:I49),0) -> 2.1070234 | J31: =IFERROR(HistoricalFS!J6/SUM(HistoricalFS!J48:J49),0) -> 2.1565842 | ... L31: =IFERROR(HistoricalFS!L6/SUM(HistoricalFS!L48:L49),0) -> 1.7477295 | N31: =IFERROR(AVERAGE(C31:L31),0) -> 1.9797367 | O31: =IFERROR(MEDIAN(C31:L31),0) -> 1.9978212
B33: Debtor Days | C33: =IFERROR(365/C27,0) -> 30.353985 | D33: =IFERROR(365/D27,0) -> 35.055726 | E33: =IFERROR(365/E27,0) -> 37.545132 | F33: =IFERROR(365/F27,0) -> 36.183511 | G33: =IFERROR(365/G27,0) -> 32.420325 | H33: =IFERROR(365/H27,0) -> 43.743436 | I33: =IFERROR(365/I27,0) -> 48.557163 | J33: =IFERROR(365/J27,0) -> 49.073711 | ... L33: =IFERROR(365/L27,0) -> 46.437206 | N33: =IFERROR(AVERAGE(C33:L33),0) -> 40.964536 | O33: =IFERROR(MEDIAN(C33:L33),0) -> 40.644284
B34: Payable Days | C34: =IFERROR(365/C28,0) -> 94.908506 | D34: =IFERROR(365/D28,0) -> 102.77197 | E34: =IFERROR(365/E28,0) -> 104.56353 | F34: =IFERROR(365/F28,0) -> 103.55553 | G34: =IFERROR(365/G28,0) -> 88.297268 | H34: =IFERROR(365/H28,0) -> 108.52656 | I34: =IFERROR(365/I28,0) -> 94.820446 | J34: =IFERROR(365/J28,0) -> 83.125613 | ... L34: =IFERROR(365/L28,0) -> 93.281873 | N34: =IFERROR(AVERAGE(C34:L34),0) -> 96.329564 | O34: =IFERROR(MEDIAN(C34:L34),0) -> 94.864476
B35: Inventory Days | C35: =IFERROR(365/C29,0) -> 51.105918 | D35: =IFERROR(365/D29,0) -> 63.659125 | E35: =IFERROR(365/E29,0) -> 57.670675 | F35: =IFERROR(365/F29,0) -> 59.755256 | G35: =IFERROR(365/G29,0) -> 61.217423 | H35: =IFERROR(365/H29,0) -> 63.855866 | I35: =IFERROR(365/I29,0) -> 77.173159 | J35: =IFERROR(365/J29,0) -> 65.728509 | ... L35: =IFERROR(365/L29,0) -> 72.334131 | N35: =IFERROR(AVERAGE(C35:L35),0) -> 63.341177 | O35: =IFERROR(MEDIAN(C35:L35),0) -> 62.438274
B36: Cash Conversion Cycle (in days) | C36: =IFERROR((SUM(C33+C35))-C34,0) -> -13.448603 | D36: =IFERROR((SUM(D33+D35))-D34,0) -> -4.0571199 | E36: =IFERROR((SUM(E33+E35))-E34,0) -> -9.347721 | F36: =IFERROR((SUM(F33+F35))-F34,0) -> -7.6167625 | G36: =IFERROR((SUM(G33+G35))-G34,0) -> 5.3404812 | H36: =IFERROR((SUM(H33+H35))-H34,0) -> -0.92725992 | I36: =IFERROR((SUM(I33+I35))-I34,0) -> 30.909876 | J36: =IFERROR((SUM(J33+J35))-J34,0) -> 31.676607 | ... L36: =IFERROR((SUM(L33+L35))-L34,0) -> 25.489463 | N36: =IFERROR(AVERAGE(C36:L36),0) -> 7.9761485 | O36: =IFERROR(MEDIAN(C36:L36),0) -> 2.2066106
B38: CFO/Sales | C38: =IFERROR(HistoricalFS!C79/HistoricalFS!C6,0) -> -5.9754798 | D38: =IFERROR(HistoricalFS!D79/HistoricalFS!D6,0) -> 0.90784817 | E38: =IFERROR(HistoricalFS!E79/HistoricalFS!E6,0) -> 0.45772398 | F38: =IFERROR(HistoricalFS!F79/HistoricalFS!F6,0) -> -8.1985413 | G38: =IFERROR(HistoricalFS!G79/HistoricalFS!G6,0) -> -3.8406828 | H38: =IFERROR(HistoricalFS!H79/HistoricalFS!H6,0) -> 1.4901816 | I38: =IFERROR(HistoricalFS!I79/HistoricalFS!I6,0) -> -2.7442436 | J38: =IFERROR(HistoricalFS!J79/HistoricalFS!J6,0) -> -0.62997646 | ... L38: =IFERROR(HistoricalFS!L79/HistoricalFS!L6,0) -> 4.6171992 | N38: =IFERROR(AVERAGE(C38:L38),0) -> -1.4779113 | O38: =IFERROR(MEDIAN(C38:L38),0) -> -0.74655934
B39: CFO/Total Assets | C39: =IFERROR(HistoricalFS!C79/HistoricalFS!C65,0) -> -8.0764047 | D39: =IFERROR(HistoricalFS!D79/HistoricalFS!D65,0) -> 1.1022806 | E39: =IFERROR(HistoricalFS!E79/HistoricalFS!E65,0) -> 0.55952419 | F39: =IFERROR(HistoricalFS!F79/HistoricalFS!F65,0) -> -9.7078315 | G39: =IFERROR(HistoricalFS!G79/HistoricalFS!G65,0) -> -4.8100845 | H39: =IFERROR(HistoricalFS!H79/HistoricalFS!H65,0) -> 1.5895583 | I39: =IFERROR(HistoricalFS!I79/HistoricalFS!I65,0) -> -3.4785044 | J39: =IFERROR(HistoricalFS!J79/HistoricalFS!J65,0) -> -0.84280701 | ... L39: =IFERROR(HistoricalFS!L79/HistoricalFS!L65,0) -> 5.1572298 | N39: =IFERROR(AVERAGE(C39:L39),0) -> -1.9531662 | O39: =IFERROR(MEDIAN(C39:L39),0) -> -0.93371473
B40: CFO/Total Debt | C40: =IFERROR(HistoricalFS!C79/HistoricalFS!C50,0) -> -263.78484 | D40: =IFERROR(HistoricalFS!D79/HistoricalFS!D50,0) -> 24.403041 | E40: =IFERROR(HistoricalFS!E79/HistoricalFS!E50,0) -> 14.436758 | F40: =IFERROR(HistoricalFS!F79/HistoricalFS!F50,0) -> -119.53698 | G40: =IFERROR(HistoricalFS!G79/HistoricalFS!G50,0) -> -69.400983 | H40: =IFERROR(HistoricalFS!H79/HistoricalFS!H50,0) -> 29.599678 | I40: =IFERROR(HistoricalFS!I79/HistoricalFS!I50,0) -> -50.325797 | J40: =IFERROR(HistoricalFS!J79/HistoricalFS!J50,0) -> -11.242251 | ... L40: =IFERROR(HistoricalFS!L79/HistoricalFS!L50,0) -> 68.353353 | N40: =IFERROR(AVERAGE(C40:L40),0) -> -38.987971 | O40: =IFERROR(MEDIAN(C40:L40),0) -> -11.811969

Sheet Common Size Statement
B3: ="Common Size Income Statement"&" - "&'Data Sheet'!$B$1 -> Common Size Income Statement - ASIAN PAINTS LTD
B5: Particulars | C5: ='Data Sheet'!B16 -> 42460 | D5: ='Data Sheet'!C16 -> 42825 | E5: ='Data Sheet'!D16 -> 43190 | F5: ='Data Sheet'!E16 -> 43555 | G5: ='Data Sheet'!F16 -> 43921 | H5: ='Data Sheet'!G16 -> 44286 | I5: ='Data Sheet'!H16 -> 44651 | J5: ='Data Sheet'!I16 -> 45016 | ... L5: ='Data Sheet'!K16 -> 45747
B7: Sales | C7: ='Data Sheet'!B17/'Data Sheet'!$B$17 -> 1 | D7: ='Data Sheet'!C17/'Data Sheet'!$C$17 -> 1 | E7: ='Data Sheet'!D17/'Data Sheet'!$D$17 -> 1 | F7: ='Data Sheet'!E17/'Data Sheet'!$E$17 -> 1 | G7: ='Data Sheet'!F17/'Data Sheet'!$F$17 -> 1 | H7: ='Data Sheet'!G17/'Data Sheet'!$G$17 -> 1 | I7: ='Data Sheet'!H17/'Data Sheet'!$H$17 -> 1 | J7: ='Data Sheet'!I17/'Data Sheet'!$I$17 -> 1 | K7: ='Data Sheet'!J17/'Data Sheet'!$J$17 -> 1 | L7: ='Data Sheet'!K17/'Data Sheet'!$K$17 -> 1
B8: Raw Material Cost | C8: ='Data Sheet'!B18/'Data Sheet'!$B$17 -> 0.46034647 | D8: ='Data Sheet'!C18/'Data Sheet'!$C$17 -> 0.49479518 | E8: ='Data Sheet'!D18/'Data Sheet'!$D$17 -> 0.48311366 | F8: ='Data Sheet'!E18/'Data Sheet'!$E$17 -> 0.51841646 | G8: ='Data Sheet'!F18/'Data Sheet'!$F$17 -> 0.49388286 | H8: ='Data Sheet'!G18/'Data Sheet'!$G$17 -> 0.48015709 | I8: ='Data Sheet'!H18/'Data Sheet'!$H$17 -> 0.58840195 | J8: ='Data Sheet'!I18/'Data Sheet'!$I$17 -> 0.55048728 | K8: ='Data Sheet'!J18/'Data Sheet'!$J$17 -> 0.49051902 | L8: ='Data Sheet'!K18/'Data Sheet'!$K$17 -> 0.51627164
B9: Change in Inventory | C9: ='Data Sheet'!B19/'Data Sheet'!$B$17 -> -0.013967007 | D9: ='Data Sheet'!C19/'Data Sheet'!$C$17 -> 0.035094964 | E9: ='Data Sheet'!D19/'Data Sheet'!$D$17 -> -0.0084477742 | F9: ='Data Sheet'!E19/'Data Sheet'!$E$17 -> 0.015242101 | G9: ='Data Sheet'!F19/'Data Sheet'!$F$17 -> 0.011832519 | H9: ='Data Sheet'!G19/'Data Sheet'!$G$17 -> 0.0042578591 | I9: ='Data Sheet'!H19/'Data Sheet'!$H$17 -> 0.045529612 | J9: ='Data Sheet'!I19/'Data Sheet'!$I$17 -> 0.0089806513 | K9: ='Data Sheet'!J19/'Data Sheet'!$J$17 -> -0.010249409 | L9: ='Data Sheet'!K19/'Data Sheet'!$K$17 -> 0.0060461953
B10: Power and Fuel | C10: ='Data Sheet'!B20/'Data Sheet'!$B$17 -> 0.0080215871 | D10: ='Data Sheet'!C20/'Data Sheet'!$C$17 -> 0.0070389105 | E10: ='Data Sheet'!D20/'Data Sheet'!$D$17 -> 0.006555896 | F10: ='Data Sheet'!E20/'Data Sheet'!$E$17 -> 0.0062177335 | G10: ='Data Sheet'!F20/'Data Sheet'!$F$17 -> 0.0048383945 | H10: ='Data Sheet'!G20/'Data Sheet'!$G$17 -> 0.0039631019 | I10: ='Data Sheet'!H20/'Data Sheet'!$H$17 -> 0.0040283451 | J10: ='Data Sheet'!I20/'Data Sheet'!$I$17 -> 0.0040097319 | K10: ='Data Sheet'!J20/'Data Sheet'!$J$17 -> 0.0037540784 | L10: ='Data Sheet'!K20/'Data Sheet'!$K$17 -> 0.0043821644
B11: Other Mfr. Exp | C11: ='Data Sheet'!B21/'Data Sheet'!$B$17 -> 0.10757251 | D11: ='Data Sheet'!C21/'Data Sheet'!$C$17 -> 0.11039378 | E11: ='Data Sheet'!D21/'Data Sheet'!$D$17 -> 0.10054831 | F11: ='Data Sheet'!E21/'Data Sheet'!$E$17 -> 0.096795084 | G11: ='Data Sheet'!F21/'Data Sheet'!$F$17 -> 0.096288948 | H11: ='Data Sheet'!G21/'Data Sheet'!$G$17 -> 0.09525768 | I11: ='Data Sheet'!H21/'Data Sheet'!$H$17 -> 0.098980182 | J11: ='Data Sheet'!I21/'Data Sheet'!$I$17 -> 0.084555501 | K11: ='Data Sheet'!J21/'Data Sheet'!$J$17 -> 0.077960306 | L11: ='Data Sheet'!K21/'Data Sheet'!$K$17 -> 0.079261196
B12: Employee Cost | C12: ='Data Sheet'!B22/'Data Sheet'!$B$17 -> 0.069718018 | D12: ='Data Sheet'!C22/'Data Sheet'!$C$17 -> 0.069040678 | E12: ='Data Sheet'!D22/'Data Sheet'!$D$17 -> 0.066681724 | F12: ='Data Sheet'!E22/'Data Sheet'!$E$17 -> 0.064588441 | G12: ='Data Sheet'!F22/'Data Sheet'!$F$17 -> 0.067846867 | H12: ='Data Sheet'!G22/'Data Sheet'!$G$17 -> 0.071276423 | I12: ='Data Sheet'!H22/'Data Sheet'!$H$17 -> 0.061667734 | J12: ='Data Sheet'!I22/'Data Sheet'!$I$17 -> 0.059045905 | K12: ='Data Sheet'!J22/'Data Sheet'!$J$17 -> 0.06578216 | L12: ='Data Sheet'!K22/'Data Sheet'!$K$17 -> 0.076853926
B13: Selling and admin | C13: ='Data Sheet'!B23/'Data Sheet'!$B$17 -> 0.27413396 | D13: ='Data Sheet'!C23/'Data Sheet'!$C$17 -> 0.28973861 | E13: ='Data Sheet'!D23/'Data Sheet'!$D$17 -> 0.13402558 | F13: ='Data Sheet'!E23/'Data Sheet'!$E$17 -> 0.12301736 | G13: ='Data Sheet'!F23/'Data Sheet'!$F$17 -> 0.11436749 | H13: ='Data Sheet'!G23/'Data Sheet'!$G$17 -> 0.10342706 | I13: ='Data Sheet'!H23/'Data Sheet'!$H$17 -> 0.10109452 | J13: ='Data Sheet'!I23/'Data Sheet'!$I$17 -> 0.10150719 | K13: ='Data Sheet'!J23/'Data Sheet'!$J$17 -> 0.10739228 | L13: ='Data Sheet'!K23/'Data Sheet'!$K$17 -> 0.11428607
B14: Other Expenses | C14: ='Data Sheet'!B24/'Data Sheet'!$B$17 -> -0.12470247 | D14: ='Data Sheet'!C24/'Data Sheet'!$C$17 -> -0.13467477 | E14: ='Data Sheet'!D24/'Data Sheet'!$D$17 -> 0.010190466 | F14: ='Data Sheet'!E24/'Data Sheet'!$E$17 -> 0.010525397 | G14: ='Data Sheet'!F24/'Data Sheet'!$F$17 -> 0.028939328 | H14: ='Data Sheet'!G24/'Data Sheet'!$G$17 -> 0.026547947 | I14: ='Data Sheet'!H24/'Data Sheet'!$H$17 -> 0.026291627 | J14: ='Data Sheet'!I24/'Data Sheet'!$I$17 -> 0.027870377 | K14: ='Data Sheet'!J24/'Data Sheet'!$J$17 -> 0.03064962 | L14: ='Data Sheet'!K24/'Data Sheet'!$K$17 -> 0.037846233
B15: Other Income | C15: ='Data Sheet'!B25/'Data Sheet'!$B$17 -> 0.014952188 | D15: ='Data Sheet'!C25/'Data Sheet'!$C$17 -> 0.022433955 | E15: ='Data Sheet'!D25/'Data Sheet'!$D$17 -> 0.019995186 | F15: ='Data Sheet'!E25/'Data Sheet'!$E$17 -> 0.014229114 | G15: ='Data Sheet'!F25/'Data Sheet'!$F$17 -> 0.017566949 | H15: ='Data Sheet'!G25/'Data Sheet'!$G$17 -> 0.015274407 | I15: ='Data Sheet'!H25/'Data Sheet'!$H$17 -> 0.01016725 | J15: ='Data Sheet'!I25/'Data Sheet'!$I$17 -> 0.012510224 | K15: ='Data Sheet'!J25/'Data Sheet'!$J$17 -> 0.023129067 | L15: ='Data Sheet'!K25/'Data Sheet'!$K$17 -> 0.010329261
B16: Depreciation | C16: ='Data Sheet'!B26/'Data Sheet'!$B$17 -> 0.019309827 | D16: ='Data Sheet'!C26/'Data Sheet'!$C$17 -> 0.022227475 | E16: ='Data Sheet'!D26/'Data Sheet'!$D$17 -> 0.021425239 | F16: ='Data Sheet'!E26/'Data Sheet'!$E$17 -> 0.03233554 | G16: ='Data Sheet'!F26/'Data Sheet'!$F$17 -> 0.038617107 | H16: ='Data Sheet'!G26/'Data Sheet'!$G$17 -> 0.036442576 | I16: ='Data Sheet'!H26/'Data Sheet'!$H$17 -> 0.028052374 | J16: ='Data Sheet'!I26/'Data Sheet'!$I$17 -> 0.024878373 | K16: ='Data Sheet'!J26/'Data Sheet'!$J$17 -> 0.024031737 | L16: ='Data Sheet'!K26/'Data Sheet'!$K$17 -> 0.030270498
B17: Interest | C17: ='Data Sheet'!B27/'Data Sheet'!$B$17 -> 0.0034334187 | D17: ='Data Sheet'!C27/'Data Sheet'!$C$17 -> 0.0024784242 | E17: ='Data Sheet'!D27/'Data Sheet'!$D$17 -> 0.0024648505 | F17: ='Data Sheet'!E27/'Data Sheet'!$E$17 -> 0.0057416452 | G17: ='Data Sheet'!F27/'Data Sheet'!$F$17 -> 0.0050630218 | H17: ='Data Sheet'!G27/'Data Sheet'!$G$17 -> 0.0042200933 | I17: ='Data Sheet'!H27/'Data Sheet'!$H$17 -> 0.0032785499 | J17: ='Data Sheet'!I27/'Data Sheet'!$I$17 -> 0.0041883417 | K17: ='Data Sheet'!J27/'Data Sheet'!$J$17 -> 0.0057802947 | L17: ='Data Sheet'!K27/'Data Sheet'!$K$17 -> 0.0066956451
B18: Profit before tax | C18: ='Data Sheet'!B28/'Data Sheet'!$B$17 -> 0.18315186 | D18: ='Data Sheet'!C28/'Data Sheet'!$C$17 -> 0.19649064 | E18: ='Data Sheet'!D28/'Data Sheet'!$D$17 -> 0.18654169 | F18: ='Data Sheet'!E28/'Data Sheet'!$E$17 -> 0.17183356 | G18: ='Data Sheet'!F28/'Data Sheet'!$F$17 -> 0.17955545 | H18: ='Data Sheet'!G28/'Data Sheet'!$G$17 -> 0.1982403 | I18: ='Data Sheet'!H28/'Data Sheet'!$H$17 -> 0.14390157 | J18: ='Data Sheet'!I28/'Data Sheet'!$I$17 -> 0.16494818 | K18: ='Data Sheet'!J28/'Data Sheet'!$J$17 -> 0.20701017 | L18: ='Data Sheet'!K28/'Data Sheet'!$K$17 -> 0.15050809
... B22: EBITDA | C22: ='Data Sheet'!B32/'Data Sheet'!$B$17 -> 0.16300891 | D22: ='Data Sheet'!C32/'Data Sheet'!$C$17 -> 0.26895251 | E22: ='Data Sheet'!D32/'Data Sheet'!$D$17 -> 0.17354105 | F22: ='Data Sheet'!E32/'Data Sheet'!$E$17 -> 0.22616583 | G22: ='Data Sheet'!F32/'Data Sheet'!$F$17 -> 0.22933366 | H22: ='Data Sheet'!G32/'Data Sheet'!$G$17 -> 0.23214428 | I22: ='Data Sheet'!H32/'Data Sheet'!$H$17 -> 0.25612447 | J22: ='Data Sheet'!I32/'Data Sheet'!$I$17 -> 0.19946597 | K22: ='Data Sheet'!J32/'Data Sheet'!$J$17 -> 0.19319431 | L22: ='Data Sheet'!K32/'Data Sheet'!$K$17 -> 0.18923736
B24: ="Common Size Balance Sheet"&" - "&'Data Sheet'!$B$1 -> Common Size Balance Sheet - ASIAN PAINTS LTD
B26: Particulars | C26: =C5 -> 42460 | D26: =D5 -> 42825 | E26: =E5 -> 43190 | F26: =F5 -> 43555 | G26: =G5 -> 43921 | H26: =H5 -> 44286 | I26: =I5 -> 44651 | J26: =J5 -> 45016 | ... L26: =L5 -> 45747
B28: Total Liabilities | C28: =HistoricalFS!C52/HistoricalFS!$C$52 -> 1 | D28: =HistoricalFS!D52/HistoricalFS!$D$52 -> 1 | E28: =HistoricalFS!E52/HistoricalFS!$E$52 -> 1 | F28: =HistoricalFS!F52/HistoricalFS!$F$52 -> 1 | G28: =HistoricalFS!G52/HistoricalFS!$G$52 -> 1 | H28: =HistoricalFS!H52/HistoricalFS!$H$52 -> 1 | I28: =HistoricalFS!I52/HistoricalFS!$I$52 -> 1 | J28: =HistoricalFS!J52/HistoricalFS!$J$52 -> 1 | K28: =HistoricalFS!K52/HistoricalFS!$K$52 -> 1 | L28: =HistoricalFS!L52/HistoricalFS!$L$52 -> 1
B29: Equity Share Capital | C29: =HistoricalFS!C48/HistoricalFS!$C$52 -> 0.0090841678 | D29: =HistoricalFS!D48/HistoricalFS!$C$52 -> 0.0090841678 | E29: =HistoricalFS!E48/HistoricalFS!$C$52 -> 0.0090841678 | F29: =HistoricalFS!F48/HistoricalFS!$C$52 -> 0.0090841678 | G29: =HistoricalFS!G48/HistoricalFS!$C$52 -> 0.0090841678 | H29: =HistoricalFS!H48/HistoricalFS!$C$52 -> 0.0090841678 | I29: =HistoricalFS!I48/HistoricalFS!$C$52 -> 0.0090841678 | J29: =HistoricalFS!J48/HistoricalFS!$C$52 -> 0.0090841678 | ... L29: =HistoricalFS!L48/HistoricalFS!$C$52 -> 0.0090841678
B30: Reserves | C30: =HistoricalFS!C49/HistoricalFS!$C$52 -> 0.60885328 | D30: =HistoricalFS!D49/HistoricalFS!$C$52 -> 0.71104732 | E30: =HistoricalFS!E49/HistoricalFS!$C$52 -> 0.78741229 | F30: =HistoricalFS!F49/HistoricalFS!$C$52 -> 0.88783061 | G30: =HistoricalFS!G49/HistoricalFS!$C$52 -> 0.95029941 | H30: =HistoricalFS!H49/HistoricalFS!$C$52 -> 1.2037441 | I30: =HistoricalFS!I49/HistoricalFS!$C$52 -> 1.2989489 | J30: =HistoricalFS!J49/HistoricalFS!$C$52 -> 1.5054707 | ... L30: =HistoricalFS!L49/HistoricalFS!$C$52 -> 1.8281878
B31: Borrowings | C31: =HistoricalFS!C50/HistoricalFS!$C$52 -> 0.030617396 | D31: =HistoricalFS!D50/HistoricalFS!$C$52 -> 0.053067375 | E31: =HistoricalFS!E50/HistoricalFS!$C$52 -> 0.050518845 | F31: =HistoricalFS!F50/HistoricalFS!$C$52 -> 0.1249736 | G31: =HistoricalFS!G50/HistoricalFS!$C$52 -> 0.10592829 | H31: =HistoricalFS!H50/HistoricalFS!$C$52 -> 0.10352466 | I31: =HistoricalFS!I50/HistoricalFS!$C$52 -> 0.15028653 | J31: =HistoricalFS!J50/HistoricalFS!$C$52 -> 0.18303007 | ... L31: =HistoricalFS!L50/HistoricalFS!$C$52 -> 0.21690345
B32: Other Liabilities | C32: =HistoricalFS!C51/HistoricalFS!$C$52 -> 0.35144516 | D32: =HistoricalFS!D51/HistoricalFS!$C$52 -> 0.40164295 | E32: =HistoricalFS!E51/HistoricalFS!$C$52 -> 0.45646428 | F32: =HistoricalFS!F51/HistoricalFS!$C$52 -> 0.51696889 | G32: =HistoricalFS!G51/HistoricalFS!$C$52 -> 0.46304537 | H32: =HistoricalFS!H51/HistoricalFS!$C$52 -> 0.61141317 | I32: =HistoricalFS!I51/HistoricalFS!$C$52 -> 0.71597391 | J32: =HistoricalFS!J51/HistoricalFS!$C$52 -> 0.74386378 | ... L32: =HistoricalFS!L51/HistoricalFS!$C$52 -> 0.82063883
B34: Total Assets | C34: =HistoricalFS!C65/HistoricalFS!$C$65 -> 1 | D34: =HistoricalFS!D65/HistoricalFS!$D$65 -> 1 | E34: =HistoricalFS!E65/HistoricalFS!$E$65 -> 1 | F34: =HistoricalFS!F65/HistoricalFS!$F$65 -> 1 | G34: =HistoricalFS!G65/HistoricalFS!$G$65 -> 1 | H34: =HistoricalFS!H65/HistoricalFS!$H$65 -> 1 | I34: =HistoricalFS!I65/HistoricalFS!$I$65 -> 1 | J34: =HistoricalFS!J65/HistoricalFS!$J$65 -> 1 | K34: =HistoricalFS!K65/HistoricalFS!$K$65 -> 1 | L34: =HistoricalFS!L65/HistoricalFS!$L$65 -> 1
B35: Net Block | C35: =HistoricalFS!C54/HistoricalFS!$C$65 -> 0.32354771 | D35: =HistoricalFS!D54/HistoricalFS!$C$65 -> 0.31288291 | E35: =HistoricalFS!E54/HistoricalFS!$C$65 -> 0.35346429 | F35: =HistoricalFS!F54/HistoricalFS!$C$65 -> 0.61526106 | G35: =HistoricalFS!G54/HistoricalFS!$C$65 -> 0.59402331 | H35: =HistoricalFS!H54/HistoricalFS!$C$65 -> 0.55483506 | I35: =HistoricalFS!I54/HistoricalFS!$C$65 -> 0.52268627 | J35: =HistoricalFS!J54/HistoricalFS!$C$65 -> 0.54649527 | ... L35: =HistoricalFS!L54/HistoricalFS!$C$65 -> 0.87319574
B36: Capital Work in Progress | C36: =HistoricalFS!C55/HistoricalFS!$C$65 -> 0.010094677 | D36: =HistoricalFS!D55/HistoricalFS!$C$65 -> 0.024390498 | E36: =HistoricalFS!E55/HistoricalFS!$C$65 -> 0.13307188 | F36: =HistoricalFS!F55/HistoricalFS!$C$65 -> 0.019856938 | G36: =HistoricalFS!G55/HistoricalFS!$C$65 -> 0.013281523 | H36: =HistoricalFS!H55/HistoricalFS!$C$65 -> 0.017329243 | I36: =HistoricalFS!I55/HistoricalFS!$C$65 -> 0.040385338 | J36: =HistoricalFS!J55/HistoricalFS!$C$65 -> 0.096560953 | ... L36: =HistoricalFS!L55/HistoricalFS!$C$65 -> 0.11880731
B37: Investments | C37: =HistoricalFS!C56/HistoricalFS!$C$65 -> 0.25685409 | D37: =HistoricalFS!D56/HistoricalFS!$C$65 -> 0.25115849 | E37: =HistoricalFS!E56/HistoricalFS!$C$65 -> 0.20273643 | F37: =HistoricalFS!F56/HistoricalFS!$C$65 -> 0.24325909 | G37: =HistoricalFS!G56/HistoricalFS!$C$65 -> 0.19119654 | H37: =HistoricalFS!H56/HistoricalFS!$C$65 -> 0.44860181 | I37: =HistoricalFS!I56/HistoricalFS!$C$65 -> 0.3075595 | J37: =HistoricalFS!J56/HistoricalFS!$C$65 -> 0.4036081 | ... L37: =HistoricalFS!L56/HistoricalFS!$C$65 -> 0.44746061
B38: Other Assets | C38: =HistoricalFS!C57/HistoricalFS!$C$65 -> 0.067684248 | D38: =HistoricalFS!D57/HistoricalFS!$C$65 -> 0.12474347 | E38: =HistoricalFS!E57/HistoricalFS!$C$65 -> 0.16022684 | F38: =HistoricalFS!F57/HistoricalFS!$C$65 -> 0.13940296 | G38: =HistoricalFS!G57/HistoricalFS!$C$65 -> 0.16466569 | H38: =HistoricalFS!H57/HistoricalFS!$C$65 -> 0.24296929 | I38: =HistoricalFS!I57/HistoricalFS!$C$65 -> 0.27243601 | J38: =HistoricalFS!J57/HistoricalFS!$C$65 -> 0.28754251 | ... L38: =HistoricalFS!L57/HistoricalFS!$C$65 -> 0.31641259
B39: Receivables | C39: =HistoricalFS!C60/HistoricalFS!$C$65 -> 0.11240048 | D39: =HistoricalFS!D60/HistoricalFS!$C$65 -> 0.13700122 | E39: =HistoricalFS!E60/HistoricalFS!$C$65 -> 0.16390047 | F39: =HistoricalFS!F60/HistoricalFS!$C$65 -> 0.18063496 | G39: =HistoricalFS!G60/HistoricalFS!$C$65 -> 0.17001751 | H39: =HistoricalFS!H60/HistoricalFS!$C$65 -> 0.24644025 | I39: =HistoricalFS!I60/HistoricalFS!$C$65 -> 0.36664732 | J39: =HistoricalFS!J60/HistoricalFS!$C$65 -> 0.4391445 | ... L39: =HistoricalFS!L60/HistoricalFS!$C$65 -> 0.40852711
B40: Inventory | C40: =HistoricalFS!C61/HistoricalFS!$C$65 -> 0.18924466 | D40: =HistoricalFS!D61/HistoricalFS!$C$65 -> 0.24878611 | E40: =HistoricalFS!E61/HistoricalFS!$C$65 -> 0.25175703 | F40: =HistoricalFS!F61/HistoricalFS!$C$65 -> 0.2983096 | G40: =HistoricalFS!G61/HistoricalFS!$C$65 -> 0.32103422 | H40: =HistoricalFS!H61/HistoricalFS!$C$65 -> 0.35974895 | I40: =HistoricalFS!I61/HistoricalFS!$C$65 -> 0.58272209 | J40: =HistoricalFS!J61/HistoricalFS!$C$65 -> 0.58818282 | ... L40: =HistoricalFS!L61/HistoricalFS!$C$65 -> 0.63635296
B41: Cash & Bank | C41: =HistoricalFS!C62/HistoricalFS!$C$65 -> 0.040174145 | D41: =HistoricalFS!D62/HistoricalFS!$C$65 -> 0.075879129 | E41: =HistoricalFS!E62/HistoricalFS!$C$65 -> 0.038322649 | F41: =HistoricalFS!F62/HistoricalFS!$C$65 -> 0.042132658 | G41: =HistoricalFS!G62/HistoricalFS!$C$65 -> 0.074138439 | H41: =HistoricalFS!H62/HistoricalFS!$C$65 -> 0.057841487 | I41: =HistoricalFS!I62/HistoricalFS!$C$65 -> 0.081856951 | J41: =HistoricalFS!J62/HistoricalFS!$C$65 -> 0.079914538 | ... L41: =HistoricalFS!L62/HistoricalFS!$C$65 -> 0.074057939

Sheet Forecasting
B3: ="Forecasting"&" - "&'Data Sheet'!B1 -> Forecasting - ASIAN PAINTS LTD
B6: ='Data Sheet'!$B$1&" - " &'Data Sheet'!A17 -> ASIAN PAINTS LTD - Sales | G6: ='Data Sheet'!$B$1&" - "&HistoricalFS!B18&" Forecasting" -> ASIAN PAINTS LTD - EBITDA Forecasting | L6: ='Data Sheet'!$B$1&" - "&HistoricalFS!B38&" Forecasting" -> ASIAN PAINTS LTD - Earnings per Share Forecasting
B7: Year Weight | C7: Year | D7: Sales | E7: Sales Growth | G7: Year Weight | H7: Year | I7: EBITDA | J7: EBITDA Growth | L7: Year Weight | M7: Year | N7: EPS | O7: EPS Growth
B8: 1 | C8: ='Data Sheet'!B16 -> 42460 | D8: {=TRANSPOSE('Data Sheet'!B17:K17)} -> 14271.49 | G8: 1 | H8: =$C8 -> 42460 | I8: {=TRANSPOSE(HistoricalFS!C18:L18)} -> 2326.38 | L8: 1 | M8: =$C8 -> 42460 | N8: {=TRANSPOSE(HistoricalFS!C38:L38)} -> 12.065367
B9: 2 | C9: =C8+365 -> 42825 | D9: 15061.99 | E9: =D9/D8-1 -> 0.055390152 | G9: 2 | H9: =H8+365 -> 42825 | I9: 4050.96 | J9: =I9/I8-1 -> 0.74131483 | L9: 2 | M9: =M8+365 -> 42825 | N9: 28.519078 | O9: =N9/N8-1 -> 1.3637141
B10: 3 | C10: =C9+365 -> 43190 | D10: 16824.55 | E10: =D10/D9-1 -> 0.11702039 | G10: 3 | H10: =H9+365 -> 43190 | I10: 2919.75 | J10: =I10/I9-1 -> -0.27924492 | L10: 3 | M10: =M9+365 -> 43190 | N10: 15.396685 | O10: =N10/N9-1 -> -0.46012685
B11: 4 | C11: =C10+365 -> 43555 | D11: 19240.13 | E11: =D11/D10-1 -> 0.14357472 | G11: 4 | H11: =H10+365 -> 43555 | I11: 4351.46 | J11: =I11/I10-1 -> 0.49035363 | L11: 4 | M11: =M10+365 -> 43555 | N11: 26.280129 | O11: =N11/N10-1 -> 0.70686935
B12: 5 | C12: =C11+365 -> 43920 | D12: 20211.25 | E12: =D12/D11-1 -> 0.050473671 | G12: 5 | H12: =H11+365 -> 43920 | I12: 4635.12 | J12: =I12/I11-1 -> 0.065187316 | L12: 5 | M12: =M11+365 -> 43920 | N12: 30.206839 | O12: =N12/N11-1 -> 0.14941744
B13: 6 | C13: =C12+365 -> 44285 | D13: 21712.79 | E13: =D13/D12-1 -> 0.074292288 | G13: 6 | H13: =H12+365 -> 44285 | I13: 5040.5 | J13: =I13/I12-1 -> 0.087458361 | L13: 6 | M13: =M12+365 -> 44285 | N13: 31.901585 | O13: =N13/N12-1 -> 0.056104699
B14: 7 | C14: =C13+365 -> 44650 | D14: 29101.28 | E14: =D14/D13-1 -> 0.34028285 | G14: 7 | H14: =H13+365 -> 44650 | I14: 7453.55 | J14: =I14/I13-1 -> 0.47873227 | L14: 7 | M14: =M13+365 -> 44650 | N14: 56.702148 | O14: =N14/N13-1 -> 0.7774085
B15: 8 | C15: =C14+365 -> 45015 | D15: 34488.59 | E15: =D15/D14-1 -> 0.18512278 | G15: 8 | H15: =H14+365 -> 45015 | I15: 6879.3 | J15: =I15/I14-1 -> -0.077043825 | L15: 8 | M15: =M14+365 -> 45015 | N15: 45.697769 | O15: =N15/N14-1 -> -0.1940734
B16: 9 | C16: =C15+365 -> 45380 | D16: 35494.73 | E16: =D16/D15-1 -> 0.029173127 | G16: 9 | H16: =H15+365 -> 45380 | I16: 6857.38 | J16: =I16/I15-1 -> -0.0031863707 | L16: 9 | M16: =M15+365 -> 45380 | N16: 41.796601 | O16: =N16/N15-1 -> -0.085368886
B17: 10 | C17: =C16+365 -> 45745 | D17: 33905.62 | E17: =D17/D16-1 -> -0.044770308 | G17: 10 | H17: =H16+365 -> 45745 | I17: 6416.21 | J17: =I17/I16-1 -> -0.064335067 | L17: 10 | M17: =M16+365 -> 45745 | N17: 39.298269 | O17: =N17/N16-1 -> -0.059773567
B18: 11 | C18: =C17+365 -> 46110 | D18: =FORECAST(B18,$D$8:$D$17,$B$8:$B$17) -> 38669.293 | E18: =D18/D17-1 -> 0.14049805 | G18: 11 | H18: =H17+365 -> 46110 | I18: =FORECAST(G18,$I$8:$I$17,$G$8:$G$17) -> 7958.488 | J18: =I18/I17-1 -> 0.24037212 | L18: 11 | M18: =M17+365 -> 46110 | N18: =FORECAST(L18,$N$8:$N$17,$L$8:$L$17) -> 52.203281 | O18: =N18/N17-1 -> 0.32838625
B19: 12 | C19: =C18+365 -> 46475 | D19: =FORECAST(B19,$D$8:$D$17,$B$8:$B$17) -> 41330.757 | E19: =D19/D18-1 -> 0.068826287 | G19: 12 | H19: =H18+365 -> 46475 | I19: =FORECAST(G19,$I$8:$I$17,$G$8:$G$17) -> 8479.4747 | J19: =I19/I18-1 -> 0.065463029 | L19: 12 | M19: =M18+365 -> 46475 | N19: =FORECAST(L19,$N$8:$N$17,$L$8:$L$17) -> 55.733614 | O19: =N19/N18-1 -> 0.067626657
B20: 13 | C20: =C19+365 -> 46840 | D20: =FORECAST(B20,$D$8:$D$17,$B$8:$B$17) -> 43992.221 | E20: =D20/D19-1 -> 0.064394269 | G20: 13 | H20: =H19+365 -> 46840 | I20: =FORECAST(G20,$I$8:$I$17,$G$8:$G$17) -> 9000.4615 | J20: =I20/I19-1 -> 0.06144092 | L20: 13 | M20: =M19+365 -> 46840 | N20: =FORECAST(L20,$N$8:$N$17,$L$8:$L$17) -> 59.263947 | O20: =N20/N19-1 -> 0.063342983
B21: 14 | C21: =C20+365 -> 47205 | D21: =FORECAST(B21,$D$8:$D$17,$B$8:$B$17) -> 46653.685 | E21: =D21/D20-1 -> 0.060498511 | G21: 14 | H21: =H20+365 -> 47205 | I21: =FORECAST(G21,$I$8:$I$17,$G$8:$G$17) -> 9521.4482 | J21: =I21/I20-1 -> 0.057884446 | L21: 14 | M21: =M20+365 -> 47205 | N21: =FORECAST(L21,$N$8:$N$17,$L$8:$L$17) -> 62.794281 | O21: =N21/N20-1 -> 0.059569663
B22: 15 | C22: =C21+365 -> 47570 | D22: =FORECAST(B22,$D$8:$D$17,$B$8:$B$17) -> 49315.149 | E22: =D22/D21-1 -> 0.057047238 | G22: 15 | H22: =H21+365 -> 47570 | I22: =FORECAST(G22,$I$8:$I$17,$G$8:$G$17) -> 10042.435 | J22: =I22/I21-1 -> 0.054717173 | L22: 15 | M22: =M21+365 -> 47570 | N22: =FORECAST(L22,$N$8:$N$17,$L$8:$L$17) -> 66.324614 | O22: =N22/N21-1 -> 0.05622062

Sheet One page Summary
B2: ='Data Sheet'!B1&" - "&"One Page Profile" -> ASIAN PAINTS LTD - One Page Profile
C4: ='Input sheet'!E3 -> Asian Paints is the largest home decor company in India. The 80+yr old company has major brands like Asian Paints, Apco, etc under its umbrella. The co. is into wall paints, wall coverings, waterproofing, texture painting, wall stickers, mechanized tools, adhesives, modular kitchens, sanitaryware, lightings, soft furnishings, and uPVC windows.
B5: INR (Crs)
B6: Key Financial Metrics | C6: ='Data Sheet'!G16 -> 44286 | D6: ='Data Sheet'!H16 -> 44651 | E6: ='Data Sheet'!I16 -> 45016 | F6: ='Data Sheet'!J16 -> 45382 | G6: ='Data Sheet'!K16 -> 45747 | I6: Share Price - 5Y
B8: Total Sales | C8: ='Data Sheet'!G17 -> 21712.79 | D8: ='Data Sheet'!H17 -> 29101.28 | E8: ='Data Sheet'!I17 -> 34488.59 | F8: ='Data Sheet'!J17 -> 35494.73 | G8: ='Data Sheet'!K17 -> 33905.62
B9: Sales Growth (y-o-y) | C9: =HistoricalFS!H7 -> 0.074292288 | D9: =HistoricalFS!I7 -> 0.34028285 | E9: =HistoricalFS!J7 -> 0.18512278 | F9: =HistoricalFS!K7 -> 0.029173127 | G9: =HistoricalFS!L7 -> -0.044770308
B10: Gross Profit Margins (%) | C10: =HistoricalFS!H13 -> 0.36211929 | D10: =HistoricalFS!I13 -> 0.38351062 | E10: =HistoricalFS!J13 -> 0.32884354 | F10: =HistoricalFS!K13 -> 0.33123621 | G10: =HistoricalFS!L13 -> 0.34136966
B11: EBITDA Margins (%) | C11: =HistoricalFS!H19 -> 0.23214428 | D11: =HistoricalFS!I19 -> 0.25612447 | E11: =HistoricalFS!J19 -> 0.19946597 | F11: =HistoricalFS!K19 -> 0.19319431 | G11: =HistoricalFS!L19 -> 0.18923736
B12: EBIT Margins (%) | C12: ='Input sheet'!G6 -> 0.1957017 | D12: ='Input sheet'!H6 -> 0.2280721 | E12: ='Input sheet'!I6 -> 0.1745876 | F12: ='Input sheet'!J6 -> 0.16916258 | G12: ='Input sheet'!K6 -> 0.15896686
B13: Net Margins (%) | C13: =HistoricalFS!H34 -> 0.14093076 | D13: =HistoricalFS!I34 -> 0.18689453 | E13: =HistoricalFS!J34 -> 0.12709508 | F13: =HistoricalFS!K34 -> 0.11295001 | G13: =HistoricalFS!L34 -> 0.11117596
B14: Earnings Per Share (In Rs) | C14: =HistoricalFS!H38 -> 31.901585 | D14: =HistoricalFS!I38 -> 56.702148 | E14: =HistoricalFS!J38 -> 45.697769 | F14: =HistoricalFS!K38 -> 41.796601 | G14: =HistoricalFS!L38 -> 39.298269
B15: EPS Growth (y-o-y) | C15: =HistoricalFS!H39 -> 0.056104699 | D15: =HistoricalFS!I39 -> 0.7774085 | E15: =HistoricalFS!J39 -> -0.1940734 | F15: =HistoricalFS!K39 -> -0.085368886 | G15: =HistoricalFS!L39 -> -0.059773567
B16: Dividend Per Share (In Rs) | C16: =HistoricalFS!H41 -> 17.849979 | D16: =HistoricalFS!I41 -> 19.150021 | E16: =HistoricalFS!J41 -> 25.650021 | F16: =HistoricalFS!K41 -> 33.300042 | G16: =HistoricalFS!L41 -> 24.800042
B17: EPS Growth (y-o-y) | C17: ='Input sheet'!G8 -> 0.48749826 | D17: ='Input sheet'!H8 -> 0.072831553 | E17: ='Input sheet'!I8 -> 0.33942522 | F17: ='Input sheet'!J8 -> 0.29824618 | G17: ='Input sheet'!K8 -> -0.25525494
B19: Key Financial Ratios | C19: =C6 -> 44286 | D19: =D6 -> 44651 | E19: =E6 -> 45016 | F19: =F6 -> 45382 | G19: =G6 -> 45747 | I19: Volume - 5Y
B21: Price to Earnings | C21: ='Data Sheet'!G96 -> 79.538369 | D21: ='Data Sheet'!H96 -> 54.318048 | E21: ='Data Sheet'!I96 -> 60.432928 | F21: ='Data Sheet'!J96 -> 68.109605 | G21: ='Data Sheet'!K96 -> 64.099515 | H21: ='Data Sheet'!L96 -> 0
B22: EV/EBITDA | C22: ='Data Sheet'!G103 -> 48.382061 | D22: ='Data Sheet'!H103 -> 39.732926 | E22: ='Data Sheet'!I103 -> 38.664729 | F22: ='Data Sheet'!J103 -> 40.022666 | G22: ='Data Sheet'!K103 -> 37.89321
B23: EV/Sales | C23: ='Data Sheet'!G104 -> 11.231619 | D23: ='Data Sheet'!H104 -> 10.176575 | E23: ='Data Sheet'!I104 -> 7.7122975 | F23: ='Data Sheet'!J104 -> 7.7321515 | G23: ='Data Sheet'!K104 -> 7.1708109
B24: Price to Book Value | C24: ='Data Sheet'!G107 -> 19.005302 | D24: ='Data Sheet'!H107 -> 21.389966 | E24: ='Data Sheet'!I107 -> 16.564136 | F24: ='Data Sheet'!J107 -> 14.580088 | G24: ='Data Sheet'!K107 -> 12.454889
B25: Return on Equity (%) | C25: ='Dupont Analysis'!$E$80 -> 0.2668242 | D25: ='Dupont Analysis'!$E$80 -> 0.2668242 | E25: ='Dupont Analysis'!$E$80 -> 0.2668242 | F25: ='Dupont Analysis'!$E$80 -> 0.2668242 | G25: ='Dupont Analysis'!$E$80 -> 0.2668242
B26: Return on Captial Employed (%) | C26: ='Data Sheet'!G111 -> 0.30571298 | D26: ='Data Sheet'!H111 -> 0.43103003 | E26: ='Data Sheet'!I111 -> 0.33591801 | F26: ='Data Sheet'!J111 -> 0.28318967 | G26: ='Data Sheet'!K111 -> 0.24849447
B28: Top 10 Shareholders | C28: ='Input sheet'!C13 -> N. Shares (in Crs) | E28: ='Input sheet'!D13 -> % Holding | F28: ='Input sheet'!E13 -> Market Value (in Crs) | I28: Shareholding Pattern
B29: ='Input sheet'!B14 -> Life Insurance Corporation of India | C29: ='Input sheet'!C14 -> 8.1643998 | E29: ='Input sheet'!D14 -> 0.0851 | F29: ='Input sheet'!E14 -> 20982.507
B30: ='Input sheet'!B15 -> Sattva Holding and Trading Pvt. Ltd. | C30: ='Input sheet'!C15 -> 5.4789183 | E30: ='Input sheet'!D15 -> 0.0571 | F30: ='Input sheet'!E15 -> 14080.82
B31: ='Input sheet'!B16 -> Smiti Holding and Trading Co. Pvt. Ltd. | C31: ='Input sheet'!C16 -> 5.1767638 | E31: ='Input sheet'!D16 -> 0.054 | F31: ='Input sheet'!E16 -> 13304.283
B32: ='Input sheet'!B17 -> SBI Mutual Fund | C32: ='Input sheet'!C17 -> 5.1682395 | E32: ='Input sheet'!D17 -> 0.0539 | F32: ='Input sheet'!E17 -> 13282.376
B33: ='Input sheet'!B18 -> Geetanjali Trading and Investments Pvt. Ltd. | C33: ='Input sheet'!C18 -> 4.570614 | E33: ='Input sheet'!D18 -> 0.0477 | F33: ='Input sheet'!E18 -> 11746.478
B34: ='Input sheet'!B19 -> Elcid Investments Limited | C34: ='Input sheet'!C19 -> 2.831386 | E34: ='Input sheet'!D19 -> 0.0295 | F34: ='Input sheet'!E19 -> 7276.662
B35: ='Input sheet'!B20 -> Shubhit Holdings Pvt. Ltd. | C35: ='Input sheet'!C20 -> 2.315073 | E35: ='Input sheet'!D20 -> 0.0241 | F35: ='Input sheet'!E20 -> 5949.7376
B36: ='Input sheet'!B21 -> ICICI Prudential Mutual Fund | C36: ='Input sheet'!C21 -> 2.1276094 | E36: ='Input sheet'!D21 -> 0.0222 | F36: ='Input sheet'!E21 -> 5467.9562
B37: ='Input sheet'!B22 -> Sudhanva Investments & Trading Co. Pvt. Ltd. | C37: ='Input sheet'!C22 -> 1.900176 | E37: ='Input sheet'!D22 -> 0.0198 | F37: ='Input sheet'!E22 -> 4883.4523
B38: ='Input sheet'!B23 -> Rupen Investment & Industries Pvt. Ltd. | C38: ='Input sheet'!C23 -> 1.8849825 | E38: ='Input sheet'!D23 -> 0.0197 | F38: ='Input sheet'!E23 -> 4844.405
B40: Managerial Remuneration | C40: Designation | E40: Remuneration | F40: X of Median Salary | I40: Capital Structure
B42: R. Seshasayee | C42: Chairman | E42: 0.86 | F42: 6.93 | I42: Share Price as on 31/08 | K42: ='Data Sheet'!B8 -> 2519
B43: Manish Choksi | C43: Vice-Chairman | E43: 0.79 | F43: 6.37 | I43: Number of Share o/s | K43: ='Data Sheet'!B6 -> 95.864573
B44: Amit Syngle | C44: MD & CEO | E44: 11.197222 | F44: 90.25 | I44: Market Capitalization | K44: =K42*K43 -> 241482.86
B45: R. J. Jeyamurugan | C45: CFO, CS & CO | E45: 5.3196548 | F45: 42.88 | I45: Less: Cash & Equivalents | K45: ='Data Sheet'!K69*-1 -> -781.98
I46: Add: Total Debt | K46: ='Data Sheet'!K59 -> 2290.29
I47: Add: Minority Interest | K47: 659.24
I48: Enterprise Value | K48: =SUM(K44:K47) -> 243650.41
B50: Recent Updates
B52: ='Input sheet'!B49 -> Asian Paints’ Q1 FY26 profit fell 6% YoY to ₹1,100 crore, though decorative paint volumes grew 4% on resilient retail demand. Brokerages remain mixed, with targets ranging from ₹2,300 to ₹2,500.
B53: ='Input sheet'!B50 -> In broader industry conditions & outlook June quarter was hit by early monsoon and price wars, weighing on earnings across paint companies. Still, urban markets showed some recovery, and the festive season is expected to lift demand.
B54: ='Input sheet'!B51 -> On September 1, 2025, Asian Paints rose 2.13% to ₹2,571.10, though still 24% below its 52-week high. In late August, the stock also posted smaller gains of 1.05% and 0.15%, closing at ₹2,517.40 and ₹2,491.15.
B57: Sources: Company Annual Report FY25, Screener.in, Times of India, NSE
B58: Prepared by: Aditya Sakpal

Sheet 1
L50: Prepared By: Aditya Sakpal

Sheet Table
B3: TABLE OF CONTENTS

Sheet Input sheet
E3: Asian Paints is the largest home decor company in India. The 80+yr old company has major brands like Asian Paints, Apco, etc under its umbrella. The co. is into wall paints, wall coverings, waterproofing, texture painting, wall stickers, mechanized tools, adhesives, modular kitchens, sanitaryware, lightings, soft furnishings, and uPVC windows.
F6: EBIT M | G6: =(HistoricalFS!H18-HistoricalFS!H24)/HistoricalFS!H6 -> 0.1957017 | H6: =(HistoricalFS!I18-HistoricalFS!I24)/HistoricalFS!I6 -> 0.2280721 | I6: =(HistoricalFS!J18-HistoricalFS!J24)/HistoricalFS!J6 -> 0.1745876 | J6: =(HistoricalFS!K18-HistoricalFS!K24)/HistoricalFS!K6 -> 0.16916258 | K6: =(HistoricalFS!L18-HistoricalFS!L24)/HistoricalFS!L6 -> 0.15896686
F8: Dividend Growth | G8: =HistoricalFS!H41/HistoricalFS!G41-1 -> 0.48749826 | H8: =HistoricalFS!I41/HistoricalFS!H41-1 -> 0.072831553 | I8: =HistoricalFS!J41/HistoricalFS!I41-1 -> 0.33942522 | J8: =HistoricalFS!K41/HistoricalFS!J41-1 -> 0.29824618 | K8: =HistoricalFS!L41/HistoricalFS!K41-1 -> -0.25525494
D9: 100
D11: 10000000
B13: Shareholder's name | C13: N. Shares (in Crs) | D13: % Holding | E13: Market Value (in Crs)
B14: Life Insurance Corporation of India | C14: 8.1643998 | D14: 0.0851 | E14: =2570*C14 -> 20982.507
B15: Sattva Holding and Trading Pvt. Ltd. | C15: 5.4789183 | D15: 0.0571 | E15: =2570*C15 -> 14080.82
B16: Smiti Holding and Trading Co. Pvt. Ltd. | C16: 5.1767638 | D16: 0.054 | E16: =2570*C16 -> 13304.283
B17: SBI Mutual Fund | C17: 5.1682395 | D17: 0.0539 | E17: =2570*C17 -> 13282.376
B18: Geetanjali Trading and Investments Pvt. Ltd. | C18: 4.570614 | D18: 0.0477 | E18: =2570*C18 -> 11746.478
B19: Elcid Investments Limited | C19: 2.831386 | D19: 0.0295 | E19: =2570*C19 -> 7276.662
B20: Shubhit Holdings Pvt. Ltd. | C20: 2.315073 | D20: 0.0241 | E20: =2570*C20 -> 5949.7376
B21: ICICI Prudential Mutual Fund | C21: 2.1276094 | D21: 0.0222 | E21: =2570*C21 -> 5467.9562
B22: Sudhanva Investments & Trading Co. Pvt. Ltd. | C22: 1.900176 | D22: 0.0198 | E22: =2570*C22 -> 4883.4523
B23: Rupen Investment & Industries Pvt. Ltd. | C23: 1.8849825 | D23: 0.0197 | E23: =2570*C23 -> 4844.405
C25: FII | D25: 0.1185
C26: DII | D26: 0.2098
C27: Promoters | D27: 0.5263
C28: Public & Govt. | D28: =14.41%+0.06% -> 0.1447
B49: Asian Paints’ Q1 FY26 profit fell 6% YoY to ₹1,100 crore, though decorative paint volumes grew 4% on resilient retail demand. Brokerages remain mixed, with targets ranging from ₹2,300 to ₹2,500.
B50: In broader industry conditions & outlook June quarter was hit by early monsoon and price wars, weighing on earnings across paint companies. Still, urban markets showed some recovery, and the festive season is expected to lift demand.
B51: On September 1, 2025, Asian Paints rose 2.13% to ₹2,571.10, though still 24% below its 52-week high. In late August, the stock also posted smaller gains of 1.05% and 0.15%, closing at ₹2,517.40 and ₹2,491.15.

Sheet HistoricalFS
B2: ="Historical Financial Statement - "&'Data Sheet'!B1 -> Historical Financial Statement - ASIAN PAINTS LTD
B3: Years | C3: ='Data Sheet'!B16 -> 42460 | D3: ='Data Sheet'!C16 -> 42825 | E3: ='Data Sheet'!D16 -> 43190 | F3: ='Data Sheet'!E16 -> 43555 | G3: ='Data Sheet'!F16 -> 43921 | H3: ='Data Sheet'!G16 -> 44286 | I3: ='Data Sheet'!H16 -> 44651 | J3: ='Data Sheet'!I16 -> 45016 | ... L3: ='Data Sheet'!K16 -> 45747
B4: Amount in crores
B5: Income Statement
B6: Sales | C6: =IFERROR('Data Sheet'!B17,0) -> 14271.49 | D6: =IFERROR('Data Sheet'!C17,0) -> 15061.99 | E6: =IFERROR('Data Sheet'!D17,0) -> 16824.55 | F6: =IFERROR('Data Sheet'!E17,0) -> 19240.13 | G6: =IFERROR('Data Sheet'!F17,0) -> 20211.25 | H6: =IFERROR('Data Sheet'!G17,0) -> 21712.79 | I6: =IFERROR('Data Sheet'!H17,0) -> 29101.28 | J6: =IFERROR('Data Sheet'!I17,0) -> 34488.59 | ... L6: =IFERROR('Data Sheet'!K17,0) -> 33905.62
B7: Sales Growth | C7: - | D7: =D6/C6-1 -> 0.055390152 | E7: =E6/D6-1 -> 0.11702039 | F7: =F6/E6-1 -> 0.14357472 | G7: =G6/F6-1 -> 0.050473671 | H7: =H6/G6-1 -> 0.074292288 | I7: =I6/H6-1 -> 0.34028285 | J7: =J6/I6-1 -> 0.18512278 | K7: =K6/J6-1 -> 0.029173127 | L7: =L6/K6-1 -> -0.044770308
B9: COGS | C9: {=IFERROR(SUM('Data Sheet'!B18,'Data Sheet'!B20:B22-1*'Data Sheet'!B19),0)} -> 9812.5 | D9: {=IFERROR(SUM('Data Sheet'!C18,'Data Sheet'!C20:C22-1*'Data Sheet'!C19),0)} -> 8675.46 | E9: {=IFERROR(SUM('Data Sheet'!D18,'Data Sheet'!D20:D22-1*'Data Sheet'!D19),0)} -> 11478.43 | F9: {=IFERROR(SUM('Data Sheet'!E18,'Data Sheet'!E20:E22-1*'Data Sheet'!E19),0)} -> 12319.29 | G9: {=IFERROR(SUM('Data Sheet'!F18,'Data Sheet'!F20:F22-1*'Data Sheet'!F19),0)} -> 12679.72 | H9: {=IFERROR(SUM('Data Sheet'!G18,'Data Sheet'!G20:G22-1*'Data Sheet'!G19),0)} -> 13850.17 | I9: {=IFERROR(SUM('Data Sheet'!H18,'Data Sheet'!H20:H22-1*'Data Sheet'!H19),0)} -> 17940.63 | J9: {=IFERROR(SUM('Data Sheet'!I18,'Data Sheet'!I20:I22-1*'Data Sheet'!I19),0)} -> 23147.24 | ... L9: {=IFERROR(SUM('Data Sheet'!K18,'Data Sheet'!K20:K22-1*'Data Sheet'!K19),0)} -> 22331.27
B10: COGS % Sales | C10: =C9/C6 -> 0.6875596 | D10: =D9/D6 -> 0.57598365 | E10: =E9/E6 -> 0.68224291 | F10: =F9/F6 -> 0.64029141 | G10: =G9/G6 -> 0.62735952 | H10: =H9/H6 -> 0.63788071 | I10: =I9/I6 -> 0.61648938 | J10: =J9/J6 -> 0.67115646 | ... L10: =L9/L6 -> 0.65863034
B12: Gross Profit | C12: =HistoricalFS!C6-HistoricalFS!C9 -> 4458.99 | D12: =HistoricalFS!D6-HistoricalFS!D9 -> 6386.53 | E12: =HistoricalFS!E6-HistoricalFS!E9 -> 5346.12 | F12: =HistoricalFS!F6-HistoricalFS!F9 -> 6920.84 | G12: =HistoricalFS!G6-HistoricalFS!G9 -> 7531.53 | H12: =HistoricalFS!H6-HistoricalFS!H9 -> 7862.62 | I12: =HistoricalFS!I6-HistoricalFS!I9 -> 11160.65 | J12: =HistoricalFS!J6-HistoricalFS!J9 -> 11341.35 | ... L12: =HistoricalFS!L6-HistoricalFS!L9 -> 11574.35
B13: Gross Margin | C13: =C12/C6 -> 0.3124404 | D13: =D12/D6 -> 0.42401635 | E13: =E12/E6 -> 0.31775709 | F13: =F12/F6 -> 0.35970859 | G13: =G12/G6 -> 0.37264048 | H13: =H12/H6 -> 0.36211929 | I13: =I12/I6 -> 0.38351062 | J13: =J12/J6 -> 0.32884354 | ... L13: =L12/L6 -> 0.34136966
B15: Selling & General Expenses | C15: =IFERROR(SUM('Data Sheet'!B23:B24),0) -> 2132.61 | D15: =IFERROR(SUM('Data Sheet'!C23:C24),0) -> 2335.57 | E15: =IFERROR(SUM('Data Sheet'!D23:D24),0) -> 2426.37 | F15: =IFERROR(SUM('Data Sheet'!E23:E24),0) -> 2569.38 | G15: =IFERROR(SUM('Data Sheet'!F23:F24),0) -> 2896.41 | H15: =IFERROR(SUM('Data Sheet'!G23:G24),0) -> 2822.12 | I15: =IFERROR(SUM('Data Sheet'!H23:H24),0) -> 3707.1 | J15: =IFERROR(SUM('Data Sheet'!I23:I24),0) -> 4462.05 | ... L15: =IFERROR(SUM('Data Sheet'!K23:K24),0) -> 5158.14
B16: S&G Exp % Sales | C16: =C15/C6 -> 0.14943149 | D16: =D15/D6 -> 0.15506384 | E16: =E15/E6 -> 0.14421604 | F16: =F15/F6 -> 0.13354276 | G16: =G15/G6 -> 0.14330682 | H16: =H15/H6 -> 0.12997501 | I16: =I15/I6 -> 0.12738615 | J16: =J15/J6 -> 0.12937757 | ... L16: =L15/L6 -> 0.1521323
B18: EBITDA | C18: =C12-C15 -> 2326.38 | D18: =D12-D15 -> 4050.96 | E18: =E12-E15 -> 2919.75 | F18: =F12-F15 -> 4351.46 | G18: =G12-G15 -> 4635.12 | H18: =H12-H15 -> 5040.5 | I18: =I12-I15 -> 7453.55 | J18: =J12-J15 -> 6879.3 | ... L18: =L12-L15 -> 6416.21
B19: EBITDA Margin | C19: =C18/C6 -> 0.16300891 | D19: =D18/D6 -> 0.26895251 | E19: =E18/E6 -> 0.17354105 | F19: =F18/F6 -> 0.22616583 | G19: =G18/G6 -> 0.22933366 | H19: =H18/H6 -> 0.23214428 | I19: =I18/I6 -> 0.25612447 | J19: =J18/J6 -> 0.19946597 | ... L19: =L18/L6 -> 0.18923736
B21: Interest | C21: =IFERROR('Data Sheet'!B27,0) -> 49 | D21: =IFERROR('Data Sheet'!C27,0) -> 37.33 | E21: =IFERROR('Data Sheet'!D27,0) -> 41.47 | F21: =IFERROR('Data Sheet'!E27,0) -> 110.47 | G21: =IFERROR('Data Sheet'!F27,0) -> 102.33 | H21: =IFERROR('Data Sheet'!G27,0) -> 91.63 | I21: =IFERROR('Data Sheet'!H27,0) -> 95.41 | J21: =IFERROR('Data Sheet'!I27,0) -> 144.45 | ... L21: =IFERROR('Data Sheet'!K27,0) -> 227.02
B22: Interest % Sales | C22: =C21/C6 -> 0.0034334187 | D22: =D21/D6 -> 0.0024784242 | E22: =E21/E6 -> 0.0024648505 | F22: =F21/F6 -> 0.0057416452 | G22: =G21/G6 -> 0.0050630218 | H22: =H21/H6 -> 0.0042200933 | I22: =I21/I6 -> 0.0032785499 | J22: =J21/J6 -> 0.0041883417 | ... L22: =L21/L6 -> 0.0066956451
B24: Depreciation | C24: =IFERROR('Data Sheet'!B26,0) -> 275.58 | D24: =IFERROR('Data Sheet'!C26,0) -> 334.79 | E24: =IFERROR('Data Sheet'!D26,0) -> 360.47 | F24: =IFERROR('Data Sheet'!E26,0) -> 622.14 | G24: =IFERROR('Data Sheet'!F26,0) -> 780.5 | H24: =IFERROR('Data Sheet'!G26,0) -> 791.27 | I24: =IFERROR('Data Sheet'!H26,0) -> 816.36 | J24: =IFERROR('Data Sheet'!I26,0) -> 858.02 | ... L24: =IFERROR('Data Sheet'!K26,0) -> 1026.34
B25: Depreciation % Sales | C25: =C24/C6 -> 0.019309827 | D25: =D24/D6 -> 0.022227475 | E25: =E24/E6 -> 0.021425239 | F25: =F24/F6 -> 0.03233554 | G25: =G24/G6 -> 0.038617107 | H25: =H24/H6 -> 0.036442576 | I25: =I24/I6 -> 0.028052374 | J25: =J24/J6 -> 0.024878373 | ... L25: =L24/L6 -> 0.030270498
B27: Earnings Before Tax | C27: =C18-SUM(C21+C24) -> 2001.8 | D27: =D18-SUM(D21+D24) -> 3678.84 | E27: =E18-SUM(E21+E24) -> 2517.81 | F27: =F18-SUM(F21+F24) -> 3618.85 | G27: =G18-SUM(G21+G24) -> 3752.29 | H27: =H18-SUM(H21+H24) -> 4157.6 | I27: =I18-SUM(I21+I24) -> 6541.78 | J27: =J18-SUM(J21+J24) -> 5876.83 | ... L27: =L18-SUM(L21+L24) -> 5162.85
B28: EBT Margin | C28: =C27/C6 -> 0.14026566 | D28: =D27/D6 -> 0.24424661 | E28: =E27/E6 -> 0.14965096 | F28: =F27/F6 -> 0.18808865 | G28: =G27/G6 -> 0.18565353 | H28: =H27/H6 -> 0.19148161 | I28: =I27/I6 -> 0.22479355 | J28: =J27/J6 -> 0.17039925 | ... L28: =L27/L6 -> 0.15227122
B30: Tax | C30: =IFERROR('Data Sheet'!B29,0) -> 844.49 | D30: =IFERROR('Data Sheet'!C29,0) -> 943.29 | E30: =IFERROR('Data Sheet'!D29,0) -> 1040.96 | F30: =IFERROR('Data Sheet'!E29,0) -> 1098.06 | G30: =IFERROR('Data Sheet'!F29,0) -> 854.85 | H30: =IFERROR('Data Sheet'!G29,0) -> 1097.6 | I30: =IFERROR('Data Sheet'!H29,0) -> 1102.91 | J30: =IFERROR('Data Sheet'!I29,0) -> 1493.5 | ... L30: =IFERROR('Data Sheet'!K29,0) -> 1393.36
B31: Effective Tax Rate | C31: =C30/C27 -> 0.42186532 | D31: =D30/D27 -> 0.25640963 | E31: =E30/E27 -> 0.41343866 | F31: =F30/F27 -> 0.30342788 | G31: =G30/G27 -> 0.22782088 | H31: =H30/H27 -> 0.26399846 | I31: =I30/I27 -> 0.16859479 | J31: =J30/J27 -> 0.25413361 | ... L31: =L30/L27 -> 0.26988195
B33: Net Profit | C33: =C27-C30 -> 1157.31 | D33: =D27-D30 -> 2735.55 | E33: =E27-E30 -> 1476.85 | F33: =F27-F30 -> 2520.79 | G33: =G27-G30 -> 2897.44 | H33: =H27-H30 -> 3060 | I33: =I27-I30 -> 5438.87 | J33: =J27-J30 -> 4383.33 | ... L33: =L27-L30 -> 3769.49
B34: Net Margin | C34: =C33/C6 -> 0.081092444 | D34: =D33/D6 -> 0.18161943 | E34: =E33/E6 -> 0.087779465 | F34: =F33/F6 -> 0.13101731 | G34: =G33/G6 -> 0.14335778 | H34: =H33/H6 -> 0.14093076 | I34: =I33/I6 -> 0.18689453 | J34: =J33/J6 -> 0.12709508 | ... L34: =L33/L6 -> 0.11117596
B36: No. of Equity Shares | C36: =IFERROR('Data Sheet'!B93,0) -> 95.92 | D36: =IFERROR('Data Sheet'!C93,0) -> 95.92 | E36: =IFERROR('Data Sheet'!D93,0) -> 95.92 | F36: =IFERROR('Data Sheet'!E93,0) -> 95.92 | G36: =IFERROR('Data Sheet'!F93,0) -> 95.92 | H36: =IFERROR('Data Sheet'!G93,0) -> 95.92 | I36: =IFERROR('Data Sheet'!H93,0) -> 95.92 | J36: =IFERROR('Data Sheet'!I93,0) -> 95.92 | ... L36: =IFERROR('Data Sheet'!K93,0) -> 95.92
B38: Earnings per Share | C38: =IFERROR(C33/C36,0) -> 12.065367 | D38: =IFERROR(D33/D36,0) -> 28.519078 | E38: =IFERROR(E33/E36,0) -> 15.396685 | F38: =IFERROR(F33/F36,0) -> 26.280129 | G38: =IFERROR(G33/G36,0) -> 30.206839 | H38: =IFERROR(H33/H36,0) -> 31.901585 | I38: =IFERROR(I33/I36,0) -> 56.702148 | J38: =IFERROR(J33/J36,0) -> 45.697769 | ... L38: =IFERROR(L33/L36,0) -> 39.298269
B39: EPS Growth % | C39: - | D39: =IFERROR(D38/C38-1,0) -> 1.3637141 | E39: =IFERROR(E38/D38-1,0) -> -0.46012685 | F39: =IFERROR(F38/E38-1,0) -> 0.70686935 | G39: =IFERROR(G38/F38-1,0) -> 0.14941744 | H39: =IFERROR(H38/G38-1,0) -> 0.056104699 | I39: =IFERROR(I38/H38-1,0) -> 0.7774085 | J39: =IFERROR(J38/I38-1,0) -> -0.1940734 | K39: =IFERROR(K38/J38-1,0) -> -0.085368886 | L39: =IFERROR(L38/K38-1,0) -> -0.059773567
B41: Dividend per share | C41: =IFERROR('Data Sheet'!B31/HistoricalFS!C36,0) -> 7.5 | D41: =IFERROR('Data Sheet'!C31/HistoricalFS!D36,0) -> 10.300042 | E41: =IFERROR('Data Sheet'!D31/HistoricalFS!E36,0) -> 8.6999583 | F41: =IFERROR('Data Sheet'!E31/HistoricalFS!F36,0) -> 10.5 | G41: =IFERROR('Data Sheet'!F31/HistoricalFS!G36,0) -> 12 | H41: =IFERROR('Data Sheet'!G31/HistoricalFS!H36,0) -> 17.849979 | I41: =IFERROR('Data Sheet'!H31/HistoricalFS!I36,0) -> 19.150021 | J41: =IFERROR('Data Sheet'!I31/HistoricalFS!J36,0) -> 25.650021 | ... L41: =IFERROR('Data Sheet'!K31/HistoricalFS!L36,0) -> 24.800042
B42: Dividend payout Ratio | C42: =IFERROR(C41/C38,0) -> 0.62161392 | D42: =IFERROR(D41/D38,0) -> 0.3611632 | E42: =IFERROR(E41/E38,0) -> 0.565054 | F42: =IFERROR(F41/F38,0) -> 0.39954141 | G42: =IFERROR(G41/G38,0) -> 0.39726103 | H42: =IFERROR(H41/H38,0) -> 0.55953268 | I42: =IFERROR(I41/I38,0) -> 0.33773008 | J42: =IFERROR(J41/J38,0) -> 0.561297 | ... L42: =IFERROR(L41/L38,0) -> 0.63107211
B44: Retained Earnings | C44: =IFERROR(IF(C38>C41,1-C42,0),0) -> 0.37838608 | D44: =IFERROR(IF(D38>D41,1-D42,0),0) -> 0.6388368 | E44: =IFERROR(IF(E38>E41,1-E42,0),0) -> 0.434946 | F44: =IFERROR(IF(F38>F41,1-F42,0),0) -> 0.60045859 | G44: =IFERROR(IF(G38>G41,1-G42,0),0) -> 0.60273897 | H44: =IFERROR(IF(H38>H41,1-H42,0),0) -> 0.44046732 | I44: =IFERROR(IF(I38>I41,1-I42,0),0) -> 0.66226992 | J44: =IFERROR(IF(J38>J41,1-J42,0),0) -> 0.438703 | ... L44: =IFERROR(IF(L38>L41,1-L42,0),0) -> 0.36892789
B47: Balance Sheet
B48: Equity Share Capital | C48: =IFERROR('Data Sheet'!B57,0) -> 95.92 | D48: =IFERROR('Data Sheet'!C57,0) -> 95.92 | E48: =IFERROR('Data Sheet'!D57,0) -> 95.92 | F48: =IFERROR('Data Sheet'!E57,0) -> 95.92 | G48: =IFERROR('Data Sheet'!F57,0) -> 95.92 | H48: =IFERROR('Data Sheet'!G57,0) -> 95.92 | I48: =IFERROR('Data Sheet'!H57,0) -> 95.92 | J48: =IFERROR('Data Sheet'!I57,0) -> 95.92 | ... L48: =IFERROR('Data Sheet'!K57,0) -> 95.92
B49: Reserves | C49: =IFERROR('Data Sheet'!B58,0) -> 6428.9 | D49: =IFERROR('Data Sheet'!C58,0) -> 7507.97 | E49: =IFERROR('Data Sheet'!D58,0) -> 8314.31 | F49: =IFERROR('Data Sheet'!E58,0) -> 9374.63 | G49: =IFERROR('Data Sheet'!F58,0) -> 10034.24 | H49: =IFERROR('Data Sheet'!G58,0) -> 12710.37 | I49: =IFERROR('Data Sheet'!H58,0) -> 13715.64 | J49: =IFERROR('Data Sheet'!I58,0) -> 15896.31 | ... L49: =IFERROR('Data Sheet'!K58,0) -> 19303.89
B50: Borrowings | C50: =IFERROR('Data Sheet'!B59,0) -> 323.29 | D50: =IFERROR('Data Sheet'!C59,0) -> 560.34 | E50: =IFERROR('Data Sheet'!D59,0) -> 533.43 | F50: =IFERROR('Data Sheet'!E59,0) -> 1319.6 | G50: =IFERROR('Data Sheet'!F59,0) -> 1118.5 | H50: =IFERROR('Data Sheet'!G59,0) -> 1093.12 | I50: =IFERROR('Data Sheet'!H59,0) -> 1586.88 | J50: =IFERROR('Data Sheet'!I59,0) -> 1932.62 | ... L50: =IFERROR('Data Sheet'!K59,0) -> 2290.29
B51: Other Liabilities | C51: =IFERROR('Data Sheet'!B60,0) -> 3710.92 | D51: =IFERROR('Data Sheet'!C60,0) -> 4240.96 | E51: =IFERROR('Data Sheet'!D60,0) -> 4819.82 | F51: =IFERROR('Data Sheet'!E60,0) -> 5458.69 | G51: =IFERROR('Data Sheet'!F60,0) -> 4889.31 | H51: =IFERROR('Data Sheet'!G60,0) -> 6455.93 | I51: =IFERROR('Data Sheet'!H60,0) -> 7559.99 | J51: =IFERROR('Data Sheet'!I60,0) -> 7854.48 | ... L51: =IFERROR('Data Sheet'!K60,0) -> 8665.15
B52: Total Liabilities | C52: =IFERROR('Data Sheet'!B61,0) -> 10559.03 | D52: =IFERROR('Data Sheet'!C61,0) -> 12405.19 | E52: =IFERROR('Data Sheet'!D61,0) -> 13763.48 | F52: =IFERROR('Data Sheet'!E61,0) -> 16248.84 | G52: =IFERROR('Data Sheet'!F61,0) -> 16137.97 | H52: =IFERROR('Data Sheet'!G61,0) -> 20355.34 | I52: =IFERROR('Data Sheet'!H61,0) -> 22958.43 | J52: =IFERROR('Data Sheet'!I61,0) -> 25779.33 | ... L52: =IFERROR('Data Sheet'!K61,0) -> 30355.25
B54: Fixed Assets Net Block | C54: =IFERROR('Data Sheet'!B62,0) -> 3416.35 | D54: =IFERROR('Data Sheet'!C62,0) -> 3303.74 | E54: =IFERROR('Data Sheet'!D62,0) -> 3732.24 | F54: =IFERROR('Data Sheet'!E62,0) -> 6496.56 | G54: =IFERROR('Data Sheet'!F62,0) -> 6272.31 | H54: =IFERROR('Data Sheet'!G62,0) -> 5858.52 | I54: =IFERROR('Data Sheet'!H62,0) -> 5519.06 | J54: =IFERROR('Data Sheet'!I62,0) -> 5770.46 | ... L54: =IFERROR('Data Sheet'!K62,0) -> 9220.1
B55: Capital Work in Progress | C55: =IFERROR('Data Sheet'!B63,0) -> 106.59 | D55: =IFERROR('Data Sheet'!C63,0) -> 257.54 | E55: =IFERROR('Data Sheet'!D63,0) -> 1405.11 | F55: =IFERROR('Data Sheet'!E63,0) -> 209.67 | G55: =IFERROR('Data Sheet'!F63,0) -> 140.24 | H55: =IFERROR('Data Sheet'!G63,0) -> 182.98 | I55: =IFERROR('Data Sheet'!H63,0) -> 426.43 | J55: =IFERROR('Data Sheet'!I63,0) -> 1019.59 | ... L55: =IFERROR('Data Sheet'!K63,0) -> 1254.49
B56: Investments | C56: =IFERROR('Data Sheet'!B64,0) -> 2712.13 | D56: =IFERROR('Data Sheet'!C64,0) -> 2651.99 | E56: =IFERROR('Data Sheet'!D64,0) -> 2140.7 | F56: =IFERROR('Data Sheet'!E64,0) -> 2568.58 | G56: =IFERROR('Data Sheet'!F64,0) -> 2018.85 | H56: =IFERROR('Data Sheet'!G64,0) -> 4736.8 | I56: =IFERROR('Data Sheet'!H64,0) -> 3247.53 | J56: =IFERROR('Data Sheet'!I64,0) -> 4261.71 | ... L56: =IFERROR('Data Sheet'!K64,0) -> 4724.75
B57: Other Assets | C57: =IFERROR('Data Sheet'!B65-SUM('Data Sheet'!B67:B69),0) -> 714.68 | D57: =IFERROR('Data Sheet'!C65-SUM('Data Sheet'!C67:C69),0) -> 1317.17 | E57: =IFERROR('Data Sheet'!D65-SUM('Data Sheet'!D67:D69),0) -> 1691.84 | F57: =IFERROR('Data Sheet'!E65-SUM('Data Sheet'!E67:E69),0) -> 1471.96 | G57: =IFERROR('Data Sheet'!F65-SUM('Data Sheet'!F67:F69),0) -> 1738.71 | H57: =IFERROR('Data Sheet'!G65-SUM('Data Sheet'!G67:G69),0) -> 2565.52 | I57: =IFERROR('Data Sheet'!H65-SUM('Data Sheet'!H67:H69),0) -> 2876.66 | J57: =IFERROR('Data Sheet'!I65-SUM('Data Sheet'!I67:I69),0) -> 3036.17 | ... L57: =IFERROR('Data Sheet'!K65-SUM('Data Sheet'!K67:K69),0) -> 3341.01
B58: Total Non- Current Assets | C58: =IFERROR(SUM(C54:C57),0) -> 6949.75 | D58: =IFERROR(SUM(D54:D57),0) -> 7530.44 | E58: =IFERROR(SUM(E54:E57),0) -> 8969.89 | F58: =IFERROR(SUM(F54:F57),0) -> 10746.77 | G58: =IFERROR(SUM(G54:G57),0) -> 10170.11 | H58: =IFERROR(SUM(H54:H57),0) -> 13343.82 | I58: =IFERROR(SUM(I54:I57),0) -> 12069.68 | J58: =IFERROR(SUM(J54:J57),0) -> 14087.93 | ... L58: =IFERROR(SUM(L54:L57),0) -> 18540.35
B60: Receivables | C60: =IFERROR('Data Sheet'!B67,0) -> 1186.84 | D60: =IFERROR('Data Sheet'!C67,0) -> 1446.6 | E60: =IFERROR('Data Sheet'!D67,0) -> 1730.63 | F60: =IFERROR('Data Sheet'!E67,0) -> 1907.33 | G60: =IFERROR('Data Sheet'!F67,0) -> 1795.22 | H60: =IFERROR('Data Sheet'!G67,0) -> 2602.17 | I60: =IFERROR('Data Sheet'!H67,0) -> 3871.44 | J60: =IFERROR('Data Sheet'!I67,0) -> 4636.94 | ... L60: =IFERROR('Data Sheet'!K67,0) -> 4313.65
B61: Inventory | C61: =IFERROR('Data Sheet'!B68,0) -> 1998.24 | D61: =IFERROR('Data Sheet'!C68,0) -> 2626.94 | E61: =IFERROR('Data Sheet'!D68,0) -> 2658.31 | F61: =IFERROR('Data Sheet'!E68,0) -> 3149.86 | G61: =IFERROR('Data Sheet'!F68,0) -> 3389.81 | H61: =IFERROR('Data Sheet'!G68,0) -> 3798.6 | I61: =IFERROR('Data Sheet'!H68,0) -> 6152.98 | J61: =IFERROR('Data Sheet'!I68,0) -> 6210.64 | ... L61: =IFERROR('Data Sheet'!K68,0) -> 6719.27
B62: Cash & Bank | C62: =IFERROR('Data Sheet'!B69,0) -> 424.2 | D62: =IFERROR('Data Sheet'!C69,0) -> 801.21 | E62: =IFERROR('Data Sheet'!D69,0) -> 404.65 | F62: =IFERROR('Data Sheet'!E69,0) -> 444.88 | G62: =IFERROR('Data Sheet'!F69,0) -> 782.83 | H62: =IFERROR('Data Sheet'!G69,0) -> 610.75 | I62: =IFERROR('Data Sheet'!H69,0) -> 864.33 | J62: =IFERROR('Data Sheet'!I69,0) -> 843.82 | ... L62: =IFERROR('Data Sheet'!K69,0) -> 781.98
B63: Total Current Assets | C63: =IFERROR(SUM(C60:C62),0) -> 3609.28 | D63: =IFERROR(SUM(D60:D62),0) -> 4874.75 | E63: =IFERROR(SUM(E60:E62),0) -> 4793.59 | F63: =IFERROR(SUM(F60:F62),0) -> 5502.07 | G63: =IFERROR(SUM(G60:G62),0) -> 5967.86 | H63: =IFERROR(SUM(H60:H62),0) -> 7011.52 | I63: =IFERROR(SUM(I60:I62),0) -> 10888.75 | J63: =IFERROR(SUM(J60:J62),0) -> 11691.4 | ... L63: =IFERROR(SUM(L60:L62),0) -> 11814.9
B65: Total Assets | C65: =IFERROR(C58+C63,0) -> 10559.03 | D65: =IFERROR(D58+D63,0) -> 12405.19 | E65: =IFERROR(E58+E63,0) -> 13763.48 | F65: =IFERROR(F58+F63,0) -> 16248.84 | G65: =IFERROR(G58+G63,0) -> 16137.97 | H65: =IFERROR(H58+H63,0) -> 20355.34 | I65: =IFERROR(I58+I63,0) -> 22958.43 | J65: =IFERROR(J58+J63,0) -> 25779.33 | ... L65: =IFERROR(L58+L63,0) -> 30355.25
B67: Check | C67: =C65=C52 -> TRUE | D67: =D65=D52 -> TRUE | E67: =E65=E52 -> TRUE | F67: =F65=F52 -> TRUE | G67: =G65=G52 -> TRUE | H67: =H65=H52 -> TRUE | I67: =I65=I52 -> TRUE | J67: =J65=J52 -> TRUE | ... L67: =L65=L52 -> TRUE
B70: Cash Flow Statements
B71: Operating Activities
B72: Profit from operations | C72: =IFERROR('Cash Flow Data'!E4,0) -> 23481 | D72: =IFERROR('Cash Flow Data'!F4,0) -> 28573 | E72: =IFERROR('Cash Flow Data'!G4,0) -> 36737 | F72: =IFERROR('Cash Flow Data'!H4,0) -> 44497 | G72: =IFERROR('Cash Flow Data'!I4,0) -> 54764 | H72: =IFERROR('Cash Flow Data'!J4,0) -> 65619 | I72: =IFERROR('Cash Flow Data'!K4,0) -> 70781 | J72: =IFERROR('Cash Flow Data'!L4,0) -> 79722 | ... L72: =IFERROR('Cash Flow Data'!N4,0) -> 117642
B73: Loans Advances | C73: =IFERROR('Cash Flow Data'!E5,0) -> -106601 | D73: =IFERROR('Cash Flow Data'!F5,0) -> -101890 | E73: =IFERROR('Cash Flow Data'!G5,0) -> -120305 | F73: =IFERROR('Cash Flow Data'!H5,0) -> -176608 | G73: =IFERROR('Cash Flow Data'!I5,0) -> -185500 | H73: =IFERROR('Cash Flow Data'!J5,0) -> -155681 | I73: =IFERROR('Cash Flow Data'!K5,0) -> -248946 | J73: =IFERROR('Cash Flow Data'!L5,0) -> -254569 | ... L73: =IFERROR('Cash Flow Data'!N5,0) -> -169918
B74: Operating investments | C74: =IFERROR('Cash Flow Data'!E6,0) -> -39116 | D74: =IFERROR('Cash Flow Data'!F6,0) -> -17326 | E74: =IFERROR('Cash Flow Data'!G6,0) -> -28231 | F74: =IFERROR('Cash Flow Data'!H6,0) -> -51458 | G74: =IFERROR('Cash Flow Data'!I6,0) -> -101070 | H74: =IFERROR('Cash Flow Data'!J6,0) -> -50157 | I74: =IFERROR('Cash Flow Data'!K6,0) -> -10849 | J74: =IFERROR('Cash Flow Data'!L6,0) -> -64182 | ... L74: =IFERROR('Cash Flow Data'!N6,0) -> -180363
B75: Operating Deposits | C75: =IFERROR('Cash Flow Data'!E7,0) -> 95590 | D75: =IFERROR('Cash Flow Data'!F7,0) -> 97261 | E75: =IFERROR('Cash Flow Data'!G7,0) -> 145241 | F75: =IFERROR('Cash Flow Data'!H7,0) -> 134128 | G75: =IFERROR('Cash Flow Data'!I7,0) -> 223704 | H75: =IFERROR('Cash Flow Data'!J7,0) -> 187514 | I75: =IFERROR('Cash Flow Data'!K7,0) -> 224282 | J75: =IFERROR('Cash Flow Data'!L7,0) -> 324660 | ... L75: =IFERROR('Cash Flow Data'!N7,0) -> 334011
B76: Other WC items | C76: =IFERROR('Cash Flow Data'!E8,0) -> -716 | D76: =IFERROR('Cash Flow Data'!F8,0) -> 18348 | E76: =IFERROR('Cash Flow Data'!G8,0) -> -6218 | F76: =IFERROR('Cash Flow Data'!H8,0) -> -932 | G76: =IFERROR('Cash Flow Data'!I8,0) -> 2110 | H76: =IFERROR('Cash Flow Data'!J8,0) -> 8203 | I76: =IFERROR('Cash Flow Data'!K8,0) -> -32389 | J76: =IFERROR('Cash Flow Data'!L8,0) -> -48450 | ... L76: =IFERROR('Cash Flow Data'!N8,0) -> 45578
B77: Working capital changes | C77: =IFERROR('Cash Flow Data'!E9,0) -> -50844 | D77: =IFERROR('Cash Flow Data'!F9,0) -> -3607 | E77: =IFERROR('Cash Flow Data'!G9,0) -> -9513 | F77: =IFERROR('Cash Flow Data'!H9,0) -> -94870 | G77: =IFERROR('Cash Flow Data'!I9,0) -> -60756 | H77: =IFERROR('Cash Flow Data'!J9,0) -> -10121 | I77: =IFERROR('Cash Flow Data'!K9,0) -> -67902 | J77: =IFERROR('Cash Flow Data'!L9,0) -> -42541 | ... L77: =IFERROR('Cash Flow Data'!N9,0) -> 29308
B78: Direct taxes | C78: =IFERROR('Cash Flow Data'!E10,0) -> -7073 | D78: =IFERROR('Cash Flow Data'!F10,0) -> -7685 | E78: =IFERROR('Cash Flow Data'!G10,0) -> -10010 | F78: =IFERROR('Cash Flow Data'!H10,0) -> -12498 | G78: =IFERROR('Cash Flow Data'!I10,0) -> -10877 | H78: =IFERROR('Cash Flow Data'!J10,0) -> -13021 | I78: =IFERROR('Cash Flow Data'!K10,0) -> -14838 | J78: =IFERROR('Cash Flow Data'!L10,0) -> -16367 | ... L78: =IFERROR('Cash Flow Data'!N10,0) -> -19709
B79: Cash from Operating Activities | C79: =SUM(C72:C78) -> -85279 | D79: =SUM(D72:D78) -> 13674 | E79: =SUM(E72:E78) -> 7701 | F79: =SUM(F72:F78) -> -157741 | G79: =SUM(G72:G78) -> -77625 | H79: =SUM(H72:H78) -> 32356 | I79: =SUM(I72:I78) -> -79861 | J79: =SUM(J72:J78) -> -21727 | ... L79: =SUM(L72:L78) -> 156549
B81: Investing Activities
B82: Fixed assets purchased | C82: =IFERROR('Cash Flow Data'!E12,0) -> -877 | D82: =IFERROR('Cash Flow Data'!F12,0) -> -1158 | E82: =IFERROR('Cash Flow Data'!G12,0) -> -848 | F82: =IFERROR('Cash Flow Data'!H12,0) -> -1621 | G82: =IFERROR('Cash Flow Data'!I12,0) -> -1636 | H82: =IFERROR('Cash Flow Data'!J12,0) -> -1696 | I82: =IFERROR('Cash Flow Data'!K12,0) -> -2236 | J82: =IFERROR('Cash Flow Data'!L12,0) -> -3467 | ... L82: =IFERROR('Cash Flow Data'!N12,0) -> -4076
B83: Fixed assets sold | C83: =IFERROR('Cash Flow Data'!E13,0) -> 12 | D83: =IFERROR('Cash Flow Data'!F13,0) -> 10 | E83: =IFERROR('Cash Flow Data'!G13,0) -> 10 | F83: =IFERROR('Cash Flow Data'!H13,0) -> 22 | G83: =IFERROR('Cash Flow Data'!I13,0) -> 19 | H83: =IFERROR('Cash Flow Data'!J13,0) -> 15 | I83: =IFERROR('Cash Flow Data'!K13,0) -> 20 | J83: =IFERROR('Cash Flow Data'!L13,0) -> 43 | ... L83: =IFERROR('Cash Flow Data'!N13,0) -> 101
B84: Investments sold | C84: =IFERROR('Cash Flow Data'!E14,0) -> 0 | D84: =IFERROR('Cash Flow Data'!F14,0) -> 0 | E84: =IFERROR('Cash Flow Data'!G14,0) -> 0 | F84: =IFERROR('Cash Flow Data'!H14,0) -> 0 | G84: =IFERROR('Cash Flow Data'!I14,0) -> 0 | H84: =IFERROR('Cash Flow Data'!J14,0) -> 0 | I84: =IFERROR('Cash Flow Data'!K14,0) -> 0 | J84: =IFERROR('Cash Flow Data'!L14,0) -> 0 | ... L84: =IFERROR('Cash Flow Data'!N14,0) -> 192
B85: Invest in subsidiaries | C85: =IFERROR('Cash Flow Data'!E15,0) -> 0 | D85: =IFERROR('Cash Flow Data'!F15,0) -> 0 | E85: =IFERROR('Cash Flow Data'!G15,0) -> 0 | F85: =IFERROR('Cash Flow Data'!H15,0) -> 0 | G85: =IFERROR('Cash Flow Data'!I15,0) -> 0 | H85: =IFERROR('Cash Flow Data'!J15,0) -> 0 | I85: =IFERROR('Cash Flow Data'!K15,0) -> 0 | J85: =IFERROR('Cash Flow Data'!L15,0) -> 0 | ... L85: =IFERROR('Cash Flow Data'!N15,0) -> -67
B86: Acquisition of companies | C86: =IFERROR('Cash Flow Data'!E16,0) -> 0 | D86: =IFERROR('Cash Flow Data'!F16,0) -> 0 | E86: =IFERROR('Cash Flow Data'!G16,0) -> -14 | F86: =IFERROR('Cash Flow Data'!H16,0) -> 0 | G86: =IFERROR('Cash Flow Data'!I16,0) -> 0 | H86: =IFERROR('Cash Flow Data'!J16,0) -> 0 | I86: =IFERROR('Cash Flow Data'!K16,0) -> 0 | J86: =IFERROR('Cash Flow Data'!L16,0) -> 0 | ... L86: =IFERROR('Cash Flow Data'!N16,0) -> 0
B87: Other investing items | C87: =IFERROR('Cash Flow Data'!E17,0) -> 28 | D87: =IFERROR('Cash Flow Data'!F17,0) -> 1 | E87: =IFERROR('Cash Flow Data'!G17,0) -> 11 | F87: =IFERROR('Cash Flow Data'!H17,0) -> 95 | G87: =IFERROR('Cash Flow Data'!I17,0) -> 214 | H87: =IFERROR('Cash Flow Data'!J17,0) -> -142 | I87: =IFERROR('Cash Flow Data'!K17,0) -> 165 | J87: =IFERROR('Cash Flow Data'!L17,0) -> 432 | ... L87: =IFERROR('Cash Flow Data'!N17,0) -> 200
B88: Cash from Investment Activities | C88: =SUM(C82:C87) -> -837 | D88: =SUM(D82:D87) -> -1147 | E88: =SUM(E82:E87) -> -841 | F88: =SUM(F82:F87) -> -1504 | G88: =SUM(G82:G87) -> -1403 | H88: =SUM(H82:H87) -> -1823 | I88: =SUM(I82:I87) -> -2051 | J88: =SUM(J82:J87) -> -2992 | ... L88: =SUM(L82:L87) -> -3650
B90: Financing Activities
B91: Proceeds from shares | C91: =IFERROR('Cash Flow Data'!E19,0) -> 1223 | D91: =IFERROR('Cash Flow Data'!F19,0) -> 2262 | E91: =IFERROR('Cash Flow Data'!G19,0) -> 13006 | F91: =IFERROR('Cash Flow Data'!H19,0) -> 26690 | G91: =IFERROR('Cash Flow Data'!I19,0) -> 1849 | H91: =IFERROR('Cash Flow Data'!J19,0) -> 1760 | I91: =IFERROR('Cash Flow Data'!K19,0) -> 2610 | J91: =IFERROR('Cash Flow Data'!L19,0) -> 3416 | ... L91: =IFERROR('Cash Flow Data'!N19,0) -> 6346
B92: Proceeds from debentures | C92: =IFERROR('Cash Flow Data'!E20,0) -> 0 | D92: =IFERROR('Cash Flow Data'!F20,0) -> 0 | E92: =IFERROR('Cash Flow Data'!G20,0) -> 0 | F92: =IFERROR('Cash Flow Data'!H20,0) -> 0 | G92: =IFERROR('Cash Flow Data'!I20,0) -> 744 | H92: =IFERROR('Cash Flow Data'!J20,0) -> 356 | I92: =IFERROR('Cash Flow Data'!K20,0) -> 8313 | J92: =IFERROR('Cash Flow Data'!L20,0) -> 23000 | ... L92: =IFERROR('Cash Flow Data'!N20,0) -> 1182
B93: Redemption of debentures | C93: =IFERROR('Cash Flow Data'!E21,0) -> 0 | D93: =IFERROR('Cash Flow Data'!F21,0) -> 0 | E93: =IFERROR('Cash Flow Data'!G21,0) -> 0 | F93: =IFERROR('Cash Flow Data'!H21,0) -> -2875 | G93: =IFERROR('Cash Flow Data'!I21,0) -> 0 | H93: =IFERROR('Cash Flow Data'!J21,0) -> -1105 | I93: =IFERROR('Cash Flow Data'!K21,0) -> -3650 | J93: =IFERROR('Cash Flow Data'!L21,0) -> -12077 | ... L93: =IFERROR('Cash Flow Data'!N21,0) -> -500
B94: Proceeds from borrowings | C94: =IFERROR('Cash Flow Data'!E22,0) -> 0 | D94: =IFERROR('Cash Flow Data'!F22,0) -> 0 | E94: =IFERROR('Cash Flow Data'!G22,0) -> 0 | F94: =IFERROR('Cash Flow Data'!H22,0) -> 3266 | G94: =IFERROR('Cash Flow Data'!I22,0) -> 28358 | H94: =IFERROR('Cash Flow Data'!J22,0) -> 0 | I94: =IFERROR('Cash Flow Data'!K22,0) -> 44308 | J94: =IFERROR('Cash Flow Data'!L22,0) -> 18007 | ... L94: =IFERROR('Cash Flow Data'!N22,0) -> 0
B95: Repayment of borrowings | C95: =IFERROR('Cash Flow Data'!E23,0) -> 0 | D95: =IFERROR('Cash Flow Data'!F23,0) -> 0 | E95: =IFERROR('Cash Flow Data'!G23,0) -> 0 | F95: =IFERROR('Cash Flow Data'!H23,0) -> 0 | G95: =IFERROR('Cash Flow Data'!I23,0) -> 0 | H95: =IFERROR('Cash Flow Data'!J23,0) -> -8389 | I95: =IFERROR('Cash Flow Data'!K23,0) -> 0 | J95: =IFERROR('Cash Flow Data'!L23,0) -> 0 | ... L95: =IFERROR('Cash Flow Data'!N23,0) -> -97063
B96: Dividends paid | C96: =IFERROR('Cash Flow Data'!E24,0) -> -2009 | D96: =IFERROR('Cash Flow Data'!F24,0) -> -2408 | E96: =IFERROR('Cash Flow Data'!G24,0) -> -2831 | F96: =IFERROR('Cash Flow Data'!H24,0) -> -4096 | G96: =IFERROR('Cash Flow Data'!I24,0) -> -6631 | H96: =IFERROR('Cash Flow Data'!J24,0) -> 0 | I96: =IFERROR('Cash Flow Data'!K24,0) -> -3592 | J96: =IFERROR('Cash Flow Data'!L24,0) -> -8605 | ... L96: =IFERROR('Cash Flow Data'!N24,0) -> -14826
B97: Other financing items | C97: =IFERROR('Cash Flow Data'!E25,0) -> 38601 | D97: =IFERROR('Cash Flow Data'!F25,0) -> -5746 | E97: =IFERROR('Cash Flow Data'!G25,0) -> 47203 | F97: =IFERROR('Cash Flow Data'!H25,0) -> 145 | G97: =IFERROR('Cash Flow Data'!I25,0) -> 75 | H97: =IFERROR('Cash Flow Data'!J25,0) -> 56 | I97: =IFERROR('Cash Flow Data'!K25,0) -> 136 | J97: =IFERROR('Cash Flow Data'!L25,0) -> 199 | ... L97: =IFERROR('Cash Flow Data'!N25,0) -> 2383
B98: Cash from Financing Activities | C98: =SUM(C91:C97) -> 37815 | D98: =SUM(D91:D97) -> -5892 | E98: =SUM(E91:E97) -> 57378 | F98: =SUM(F91:F97) -> 23130 | G98: =SUM(G91:G97) -> 24395 | H98: =SUM(H91:H97) -> -7322 | I98: =SUM(I91:I97) -> 48125 | J98: =SUM(J91:J97) -> 23940 | ... L98: =SUM(L91:L97) -> -102478
B100: Net Cash Flow | C100: =IFERROR(SUM(C79+C88+C98),0) -> -48301 | D100: =IFERROR(SUM(D79+D88+D98),0) -> 6635 | E100: =IFERROR(SUM(E79+E88+E98),0) -> 64238 | F100: =IFERROR(SUM(F79+F88+F98),0) -> -136115 | G100: =IFERROR(SUM(G79+G88+G98),0) -> -54633 | H100: =IFERROR(SUM(H79+H88+H98),0) -> 23211 | I100: =IFERROR(SUM(I79+I88+I98),0) -> -33787 | J100: =IFERROR(SUM(J79+J88+J98),0) -> -779 | ... L100: =IFERROR(SUM(L79+L88+L98),0) -> 50421

Sheet Data Room>

Sheet List of Stocks
A2: COMPANY_NAME | B2: BSE | C2: NSE | D2: Industry
A3: 20 MICRONS LTD | B3: 533022 | C3: 20MICRONS | D3: Mining
A4: 21ST CENTURY MANAGEMENT SERVICES LTD | B4: 526921 | C4: 21STCENMGM | D4: Other Financial Services
A5: 3I INFOTECH LTD | B5: 532628 | C5: 3IINFOTECH | D5: IT Consulting & Software
A6: 3M (INDIA) LTD | B6: 523395 | C6: 3M(INDIA) | D6: Diversified
A7: 3M INDIA LTD | B7: 523395 | C7: 3MINDIA | D7: Diversified
A8: 3P LAND HOLDINGS LTD | B8: 516092 | C8: 3PLAND | D8: Paper & Paper Products
A9: 5PAISA CAPITAL LTD | B9: 540776 | C9: 5PAISA | D9: Other Financial Services
A10: 63 MOONS TECHNOLOGIES LTD | B10: 526881 | C10: 63MOONS | D10: IT Consulting & Software
A11: 7NR RETAIL LTD | B11: 540615 | C11: Not Listed | D11: Specialty Retail
A12: 7SEAS ENTERTAINMENT LTD | B12: 540874 | C12: Not Listed | D12: Movies & Entertainment
A13: 8K MILES SOFTWARE SERVICES LTD | B13: 512161 | C13: 8KMILES | D13: Internet Software & Services
A14: A & M FEBCON LTD | B14: 540697 | C14: Not Listed | D14: Industrial Machinery
A15: A AND M JUMBO BAGS LTD | B15: Not Listed | C15: AMJUMBO | D15: SME
A16: A INFRASTRUCTURE LTD | B16: 539620 | C16: Not Listed | D16: Cement & Cement Products
A17: A K SPINTEX LTD | B17: 539300 | C17: Not Listed | D17: Textiles
A18: A K CAPITAL SERVICES LTD | B18: 530499 | C18: Not Listed | D18: Finance (including NBFCs)
A19: A.F. Enterprises Ltd | B19: 538351 | C19: AFEL | D19: Investment Companies
A20: A-1 ACID LTD | B20: 542012 | C20: Not Listed | D20: Comm.Trading & Distribution
A21: A2Z INFRA ENGINEERING LTD | B21: 533292 | C21: A2ZINFRA | D21: Utilities:Non-Elec.
A22: AADHAAR VENTURES (INDIA) LTD | B22: 531611 | C22: Not Listed | D22: Finance (including NBFCs)
A23: AADHAAR VENTURES INDIA LTD | B23: 531611 | C23: Not Listed | D23: Finance (including NBFCs)
A24: AAKASH EXPLORATION SERVICES LTD | B24: Not Listed | C24: AAKASH | D24: SME
A25: AANANDA LAKSHMI SPINNING MILLS LTD | B25: 539096 | C25: Not Listed | D25: Textiles
A26: AANCHAL ISPAT LTD | B26: 538812 | C26: Not Listed | D26: Iron & Steel/Interm.Products
A27: AAR COMMERCIAL COMPANY LTD | B27: 539632 | C27: Not Listed | D27: Distributors
A28: Aar Shyam India Investment Company Ltd | B28: 542377 | C28: AARSHYAM | D28: Finance (including NBFCs)
A29: AAREY DRUGS & PHARMACEUTICALS LTD | B29: 524412 | C29: Not Listed | D29: Pharmaceuticals
A30: AARON INDUSTRIES LTD | B30: Not Listed | C30: AARON | D30: SME
A31: Aartech Solonics Ltd | B31: 542580 | C31: AARTECH | D31: Heavy Electrical Equipment
A32: AARTI DRUGS LTD | B32: 524348 | C32: AARTIDRUGS | D32: Pharmaceuticals
A33: AARTI INDUSTRIES LTD | B33: 524208 | C33: AARTIIND | D33: Commodity Chemicals
A34: AARV INFRATEL LTD | B34: 526488 | C34: Not Listed | D34: Textiles
A35: AARVEE DENIMS & EXPORTS LTD | B35: 514274 | C35: AARVEEDEN | D35: Textiles
A36: AARVI ENCON LTD | B36: Not Listed | C36: AARVI | D36: SME
A37: AASHEE INFOTECH LTD | B37: 519319 | C37: Not Listed | D37: Internet Software & Services
A38: AASWA TRADING & EXPORTS LTD | B38: 512038 | C38: Not Listed | D38: Comm.Trading & Distribution
A39: AAVAS FINANCIERS LTD | B39: 541988 | C39: AAVAS | D39: Housing Finance
A40: AAYUSH FOOD AND HERBS LTD | B40: 539528 | C40: Not Listed | D40: Packaged Foods
A41: ABAN OFFSHORE LTD | B41: 523204 | C41: ABAN | D41: Exploration & Production
A42: ABANS ENTERPRISES LTD | B42: 512165 | C42: Not Listed | D42: Comm.Trading & Distribution
A43: ABB INDIA LTD | B43: 500002 | C43: ABB | D43: Heavy Electrical Equipment
A44: ABBOTT (INDIA) LTD | B44: 500488 | C44: ABBOT(INDIA) | D44: Pharmaceuticals
A45: ABBOTT INDIA LTD | B45: 500488 | C45: ABBOTINDIA | D45: Pharmaceuticals
A46: ABC (INDIA) LTD | B46: 520123 | C46: Not Listed | D46: Surface Transportation
A47: ABC GAS INTERNATIONAL LTD | B47: 513119 | C47: Not Listed | D47: Copper
A48: ABC INDIA LTD | B48: 520123 | C48: Not Listed | D48: Surface Transportation
... A56: ABIRAMI FINANCIAL SERVICES INDIA LTD | B56: 511756 | C56: Not Listed | D56: Finance (including NBFCs)
A57: ABM INTERNATIONAL LTD | B57: Not Listed | C57: ABMINTLTD | D57: Others
A58: ABM KNOWLEDGEWARE LTD | B58: 531161 | C58: Not Listed | D58: IT Software Products
A59: ACC LTD | B59: 500410 | C59: ACC | D59: Cement & Cement Products
A60: ACCEL LTD | B60: 517494 | C60: Not Listed | D60: Storage Media & Peripherals
A61: ACCELYA KALE SOLUTIONS LTD | B61: 532268 | C61: ACCELYA | D61: IT Consulting & Software
A62: ACCORD SYNERGY LTD | B62: Not Listed | C62: ACCORD | D62: SME
A63: ACCURACY SHIPPING LTD | B63: Not Listed | C63: ACCURACY | D63: SME
A64: ACE EDUTREND LTD | B64: 530093 | C64: Not Listed | D64: Education
A65: ACE INTEGRATED SOLUTIONS LTD | B65: Not Listed | C65: ACEINTEG | D65: SME
A66: ACE MEN ENGG WORKS LTD | B66: 539661 | C66: Not Listed | D66: Distributors
A67: ACE SOFTWARE EXPORTS LTD | B67: 531525 | C67: Not Listed | D67: IT Software Products
A68: Achal Investments Ltd | B68: 538570 | C68: ACHAL | D68: Other Financial Services
A69: ACI INFOCOM LTD | B69: 517356 | C69: Not Listed | D69: Storage Media & Peripherals
A70: ACKNIT INDUSTRIES LTD | B70: 530043 | C70: Not Listed | D70: Other Apparels & Accessories
A71: ACME RESOURCES LTD | B71: 539391 | C71: Not Listed | D71: Finance (including NBFCs)
A72: ACROW INDIA LTD. | B72: 513149 | C72: ACROW | D72: Iron &amp; Steel Products
A73: ACRYSIL LTD | B73: 524091 | C73: Not Listed | D73: Plastic Products
A74: ACTION CONSTRUCTION EQUIPMENT LTD | B74: 532762 | C74: ACE | D74: Transport Related Services
A75: ACTION FINANCIAL SERVICES (INDIA) LTD | B75: 511706 | C75: Not Listed | D75: Other Financial Services
A76: ACTION FINANCIAL SERVICES INDIA LTD | B76: 511706 | C76: Not Listed | D76: Other Financial Services
A77: ACTIVE CLOTHING CO LTD | B77: 541144 | C77: Not Listed | D77: Other Apparels & Accessories
... A135: AGRI-TECH INDIA LTD | B135: 537292 | C135: AGRITECH | D135: Other Agricultural Products
A136: AGRO PHOS (INDIA) LTD | B136: Not Listed | C136: AGROPHOS | D136: SME
A137: AGRO PHOS INDIA LTD | B137: Not Listed | C137: AGROPHOS | D137: SME
A138: AGRO TECH FOODS LTD | B138: 500215 | C138: ATFL | D138: Other Agricultural Products
A139: AHIMSA INDUSTRIES LTD | B139: Not Listed | C139: AHIMSA | D139: SME
A140: AHLADA ENGINEERS LTD | B140: Not Listed | C140: AHLADA | D140: SME
A141: AHLUWALIA CONTRACTS (INDIA) LTD | B141: 532811 | C141: AHLUCONT | D141: Realty
A142: AHLUWALIA CONTRACTS INDIA LTD | B142: 532811 | C142: AHLUCONT | D142: Realty
A143: AHMEDABAD STEELCRAFT LTD | B143: 522273 | C143: Not Listed | D143: Iron & Steel/Interm.Products
A144: AI CHAMPDANY INDUSTRIES LTD | B144: 532806 | C144: Not Listed | D144: Jute & Jute Products
A145: AIA ENGINEERING LTD | B145: 532683 | C145: AIAENG | D145: Other Industrial Goods
A146: AIMCO PESTICIDES LTD | B146: 524288 | C146: Not Listed | D146: Agrochemicals
A147: AIRAN LTD | B147: Not Listed | C147: AIRAN | D147: SME
A148: AIRO LAM LTD | B148: Not Listed | C148: AIROLAM | D148: SME
A149: AISHWARYA TELECOM LTD | B149: 532975 | C149: Not Listed | D149: Telecom Equipment
A150: AJANTA PHARMA LTD | B150: 532331 | C150: AJANTPHARM | D150: Pharmaceuticals
A151: AJANTA SOYA LTD | B151: 519216 | C151: Not Listed | D151: Edible Oils
A152: AJCON GLOBAL SERVICES LTD | B152: 511692 | C152: Not Listed | D152: Other Financial Services
A153: AJEL LTD | B153: 530713 | C153: Not Listed | D153: IT Consulting & Software
A154: AJMERA REALTY & INFRA (INDIA) LTD | B154: 513349 | C154: AJMERA | D154: Realty
A155: AJMERA REALTY & INFRA INDIA LTD | B155: 513349 | C155: AJMERA | D155: Realty
A156: AJOONI BIOTECH LTD | B156: Not Listed | C156: AJOONI | D156: SME
A157: AJWA FUN WORLD & RESORT LTD | B157: 526628 | C157: Not Listed | D157: Other Leisure Facilities
A158: AKAR AUTO INDUSTRIES LTD | B158: 530621 | C158: Not Listed | D158: Industrial Machinery
A159: AKASH INFRA PROJECTS LTD | B159: Not Listed | C159: AKASH | D159: SME
A160: AKASHDEEP METAL INDUSTRIES LTD | B160: 538778 | C160: Not Listed | D160: Finance (including NBFCs)
A161: AKG EXIM LTD | B161: Not Listed | C161: AKG | D161: SME
A162: AKI (INDIA) LTD | B162: 542020 | C162: Not Listed | D162: Other Apparels & Accessories
A163: AKI INDIA LTD | B163: 542020 | C163: Not Listed | D163: Other Apparels & Accessories
A164: AKM LACE AND EMBROTEX LTD | B164: 540718 | C164: Not Listed | D164: Textiles
A165: AKME STAR HOUSING FINANCE LTD | B165: 539017 | C165: Not Listed | D165: Housing Finance
...

Sheet Data Sheet
A1: COMPANY NAME | B1: ASIAN PAINTS LTD | E1: =IF(B2<>B3, "A NEW VERSION OF THE WORKSHEET IS AVAILABLE", "")
A2: LATEST VERSION | B2: 2.1 | E2: PLEASE DO NOT MAKE ANY CHANGES TO THIS SHEET
A3: CURRENT VERSION | B3: 2.1
A5: META
A6: Number of shares | B6: =IF(B9>0, B9/B8, 0) -> 95.864573
A7: Face Value | B7: 1
A8: Current Price | B8: 2519
A9: Market Capitalization | B9: 241482.86
A15: PROFIT & LOSS
A16: Report Date | B16: 42460 | C16: 42825 | D16: 43190 | E16: 43555 | F16: 43921 | G16: 44286 | H16: 44651 | I16: 45016 | J16: 45382 | K16: 45747
A17: Sales | B17: 14271.49 | C17: 15061.99 | D17: 16824.55 | E17: 19240.13 | F17: 20211.25 | G17: 21712.79 | H17: 29101.28 | I17: 34488.59 | J17: 35494.73 | K17: 33905.62
A18: Raw Material Cost | B18: 6569.83 | C18: 7452.6 | D18: 8128.17 | E18: 9974.4 | F18: 9981.99 | G18: 10425.55 | H18: 17123.25 | I18: 18985.53 | J18: 17410.84 | K18: 17504.51
A19: Change in Inventory | B19: -199.33 | C19: 528.6 | D19: -142.13 | E19: 293.26 | F19: 239.15 | G19: 92.45 | H19: 1324.97 | I19: 309.73 | J19: -363.8 | K19: 205
A20: Power and Fuel | B20: 114.48 | C20: 106.02 | D20: 110.3 | E20: 119.63 | F20: 97.79 | G20: 86.05 | H20: 117.23 | I20: 138.29 | J20: 133.25 | K20: 148.58
A21: Other Mfr. Exp | B21: 1535.22 | C21: 1662.75 | D21: 1691.68 | E21: 1862.35 | F21: 1946.12 | G21: 2068.31 | H21: 2880.45 | I21: 2916.2 | J21: 2767.18 | K21: 2687.4
A22: Employee Cost | B22: 994.98 | C22: 1039.89 | D22: 1121.89 | E22: 1242.69 | F22: 1371.27 | G22: 1547.61 | H22: 1794.61 | I22: 2036.41 | J22: 2334.92 | K22: 2605.78
A23: Selling and admin | B23: 3912.3 | C23: 4364.04 | D23: 2254.92 | E23: 2366.87 | F23: 2311.51 | G23: 2245.69 | H23: 2941.98 | I23: 3500.84 | J23: 3811.86 | K23: 3874.94
A24: Other Expenses | B24: -1779.69 | C24: -2028.47 | D24: 171.45 | E24: 202.51 | F24: 584.9 | G24: 576.43 | H24: 765.12 | I24: 961.21 | J24: 1087.9 | K24: 1283.2
A25: Other Income | B25: 213.39 | C25: 337.9 | D25: 336.41 | E25: 273.77 | F25: 355.05 | G25: 331.65 | H25: 295.88 | I25: 431.46 | J25: 820.96 | K25: 350.22
A26: Depreciation | B26: 275.58 | C26: 334.79 | D26: 360.47 | E26: 622.14 | F26: 780.5 | G26: 791.27 | H26: 816.36 | I26: 858.02 | J26: 853 | K26: 1026.34
A27: Interest | B27: 49 | C27: 37.33 | D27: 41.47 | E27: 110.47 | F27: 102.33 | G27: 91.63 | H27: 95.41 | I27: 144.45 | J27: 205.17 | K27: 227.02
... A31: Dividend Amount | B31: 719.4 | C31: 987.98 | D31: 834.5 | E31: 1007.16 | F31: 1151.04 | G31: 1712.17 | H31: 1836.87 | I31: 2460.35 | J31: 3194.14 | K31: 2378.82
A32: EBITDA | B32: =HistoricalFS!C18 -> 2326.38 | C32: =HistoricalFS!D18 -> 4050.96 | D32: =HistoricalFS!E18 -> 2919.75 | E32: =HistoricalFS!F18 -> 4351.46 | F32: =HistoricalFS!G18 -> 4635.12 | G32: =HistoricalFS!H18 -> 5040.5 | H32: =HistoricalFS!I18 -> 7453.55 | I32: =HistoricalFS!J18 -> 6879.3 | ... K32: =HistoricalFS!L18 -> 6416.21
A40: Quarters
A41: Report Date | B41: 45016 | C41: 45107 | D41: 45199 | E41: 45291 | F41: 45382 | G41: 45473 | H41: 45565 | I41: 45657 | J41: 45747 | K41: 45838
A42: Sales | B42: 8787.34 | C42: 9182.31 | D42: 8478.57 | E42: 9103.09 | F42: 8730.76 | G42: 8969.73 | H42: 8027.54 | I42: 8549.44 | J42: 8358.91 | K42: 8938.55
A43: Expenses | B43: 6922.58 | C43: 7061.02 | D43: 6762.34 | E43: 7047 | F43: 7039.39 | G43: 7275.96 | H43: 6788.03 | I43: 6912.71 | J43: 6922.71 | K43: 7313.58
A44: Other Income | B44: 104.17 | C44: 227.74 | D44: 194.33 | E44: 186.46 | F44: 212.43 | G44: 192.93 | H44: 24.53 | I44: 192.82 | J44: -60.06 | K44: 229.11
A45: Depreciation | B45: 220.17 | C45: 198.32 | D45: 208.72 | E45: 220.35 | F45: 225.61 | G45: 227.7 | H45: 241.99 | I45: 255.55 | J45: 301.1 | K45: 300.87
A46: Interest | B46: 38.91 | C46: 45.75 | D46: 50.9 | E46: 54.42 | F46: 54.1 | G46: 55.38 | H46: 63.01 | I46: 55.84 | J46: 52.79 | K46: 44.5
A47: Profit before tax | B47: 1709.85 | C47: 2104.96 | D47: 1650.94 | E47: 1967.78 | F47: 1624.09 | G47: 1603.62 | H47: 959.04 | I47: 1518.16 | J47: 1022.25 | K47: 1508.71
A48: Tax | B48: 451.44 | C48: 530.12 | D48: 418.55 | E48: 492.62 | F48: 348.79 | G48: 416.83 | H48: 265.38 | I48: 389.73 | J48: 321.42 | K48: 391.66
A49: Net profit | B49: 1234.14 | C49: 1550.37 | D49: 1205.42 | E49: 1447.72 | F49: 1256.72 | G49: 1169.98 | H49: 694.64 | I49: 1110.48 | J49: 692.13 | K49: 1099.77
A50: Operating Profit | B50: 1864.76 | C50: 2121.29 | D50: 1716.23 | E50: 2056.09 | F50: 1691.37 | G50: 1693.77 | H50: 1239.51 | I50: 1636.73 | J50: 1436.2 | K50: 1624.97
A55: BALANCE SHEET
A56: Report Date | B56: 42460 | C56: 42825 | D56: 43190 | E56: 43555 | F56: 43921 | G56: 44286 | H56: 44651 | I56: 45016 | J56: 45382 | K56: 45747
A57: Equity Share Capital | B57: 95.92 | C57: 95.92 | D57: 95.92 | E57: 95.92 | F57: 95.92 | G57: 95.92 | H57: 95.92 | I57: 95.92 | J57: 95.92 | K57: 95.92
A58: Reserves | B58: 6428.9 | C58: 7507.97 | D58: 8314.31 | E58: 9374.63 | F58: 10034.24 | G58: 12710.37 | H58: 13715.64 | I58: 15896.31 | J58: 18632.38 | K58: 19303.89
A59: Borrowings | B59: 323.29 | C59: 560.34 | D59: 533.43 | E59: 1319.6 | F59: 1118.5 | G59: 1093.12 | H59: 1586.88 | I59: 1932.62 | J59: 2474.38 | K59: 2290.29
A60: Other Liabilities | B60: 3710.92 | C60: 4240.96 | D60: 4819.82 | E60: 5458.69 | F60: 4889.31 | G60: 6455.93 | H60: 7559.99 | I60: 7854.48 | J60: 8698.09 | K60: 8665.15
A61: Total | B61: 10559.03 | C61: 12405.19 | D61: 13763.48 | E61: 16248.84 | F61: 16137.97 | G61: 20355.34 | H61: 22958.43 | I61: 25779.33 | J61: 29900.77 | K61: 30355.25
A62: Net Block | B62: 3416.35 | C62: 3303.74 | D62: 3732.24 | E62: 6496.56 | F62: 6272.31 | G62: 5858.52 | H62: 5519.06 | I62: 5770.46 | J62: 7146.62 | K62: 9220.1
A63: Capital Work in Progress | B63: 106.59 | C63: 257.54 | D63: 1405.11 | E63: 209.67 | F63: 140.24 | G63: 182.98 | H63: 426.43 | I63: 1019.59 | J63: 2698.37 | K63: 1254.49
A64: Investments | B64: 2712.13 | C64: 2651.99 | D64: 2140.7 | E64: 2568.58 | F64: 2018.85 | G64: 4736.8 | H64: 3247.53 | I64: 4261.71 | J64: 4587.92 | K64: 4724.75
A65: Other Assets | B65: 4323.96 | C65: 6191.92 | D65: 6485.43 | E65: 6974.03 | F65: 7706.57 | G65: 9577.04 | H65: 13765.41 | I65: 14727.57 | J65: 15467.86 | K65: 15155.91
A66: Total | B66: 10559.03 | C66: 12405.19 | D66: 13763.48 | E66: 16248.84 | F66: 16137.97 | G66: 20355.34 | H66: 22958.43 | I66: 25779.33 | J66: 29900.77 | K66: 30355.25
A67: Receivables | B67: 1186.84 | C67: 1446.6 | D67: 1730.63 | E67: 1907.33 | F67: 1795.22 | G67: 2602.17 | H67: 3871.44 | I67: 4636.94 | J67: 4889.05 | K67: 4313.65
... A70: No. of Equity Shares | B70: 959197790 | C70: 959197790 | D70: 959197790 | E70: 959197790 | F70: 959197790 | G70: 959197790 | H70: 959197790 | I70: 959197790 | J70: 959197790 | K70: 959197790
A71: New Bonus Shares
A72: Face value | B72: 1 | C72: 1 | D72: 1 | E72: 1 | F72: 1 | G72: 1 | H72: 1 | I72: 1 | J72: 1 | K72: 1
A80: CASH FLOW:
A81: Report Date | B81: 42460 | C81: 42825 | D81: 43190 | E81: 43555 | F81: 43921 | G81: 44286 | H81: 44651 | I81: 45016 | J81: 45382 | K81: 45747
A82: Cash from Operating Activity | B82: 2242.95 | C82: 1527.33 | D82: 2113.44 | E82: 2469.54 | F82: 3038.15 | G82: 3683.35 | H82: 986.49 | I82: 4193.43 | J82: 6103.6 | K82: 4423.96
A83: Cash from Investing Activity | B83: -866.21 | C83: -681.11 | D83: -1556.14 | E83: -917.79 | F83: -517.91 | G83: -540.54 | H83: -316.75 | I83: -1282.34 | J83: -2548.48 | K83: -940.91
A84: Cash from Financing Activity | B84: -848.98 | C84: -756.43 | D84: -1379.14 | E84: -1117.46 | F84: -2871.46 | G84: -650.4 | H84: -1807.61 | I84: -2140.05 | J84: -2982.5 | K84: -3752.58
A85: Net Cash Flow | B85: 527.76 | C85: 89.79 | D85: -821.84 | E85: 434.29 | F85: -351.22 | G85: 2492.41 | H85: -1137.87 | I85: 771.04 | J85: 572.62 | K85: -269.53
A90: PRICE: | B90: 868.4 | C90: 1073.5 | D90: 1120.4 | E90: 1492.7 | F90: 1666.5 | G90: 2537.4 | H90: 3079.95 | I90: 2761.65 | J90: 2846.75 | K90: =B8 -> 2519
A92: DERIVED:
A93: Adjusted Equity Shares in Cr | B93: 95.92 | C93: 95.92 | D93: 95.92 | E93: 95.92 | F93: 95.92 | G93: 95.92 | H93: 95.92 | I93: 95.92 | J93: 95.92 | K93: 95.92
A96: price to earnings | B96: =B90/HistoricalFS!C38 -> 71.974603 | C96: =C90/HistoricalFS!D38 -> 37.641469 | D96: =D90/HistoricalFS!E38 -> 72.768912 | E96: =E90/HistoricalFS!F38 -> 56.799568 | F96: =F90/HistoricalFS!G38 -> 55.169626 | G96: =G90/HistoricalFS!H38 -> 79.538369 | H96: =H90/HistoricalFS!I38 -> 54.318048 | I96: =I90/HistoricalFS!J38 -> 60.432928 | ... K96: =K90/HistoricalFS!L38 -> 64.099515
A98: Market cap | B98: =B93*B90 -> 83296.928 | C98: =C93*C90 -> 102970.12 | D98: =D93*D90 -> 107468.77 | E98: =E93*E90 -> 143179.78 | F98: =F93*F90 -> 159850.68 | G98: =G93*G90 -> 243387.41 | H98: =H93*H90 -> 295428.8 | I98: =I93*I90 -> 264897.47 | ... K98: =K93*K90 -> 241622.48
A99: Debt | B99: =B59 -> 323.29 | C99: =C59 -> 560.34 | D99: =D59 -> 533.43 | E99: =E59 -> 1319.6 | F99: =F59 -> 1118.5 | G99: =G59 -> 1093.12 | H99: =H59 -> 1586.88 | I99: =I59 -> 1932.62 | ... K99: =K59 -> 2290.29
A100: Cash | B100: =B69 -> 424.2 | C100: =C69 -> 801.21 | D100: =D69 -> 404.65 | E100: =E69 -> 444.88 | F100: =F69 -> 782.83 | G100: =G69 -> 610.75 | H100: =H69 -> 864.33 | I100: =I69 -> 843.82 | ... K100: =K69 -> 781.98
A101: EV | B101: =B98+B99-B100 -> 83196.018 | C101: =C98+C99-C100 -> 102729.25 | D101: =D98+D99-D100 -> 107597.55 | E101: =E98+E99-E100 -> 144054.5 | F101: =F98+F99-F100 -> 160186.35 | G101: =G98+G99-G100 -> 243869.78 | H101: =H98+H99-H100 -> 296151.35 | I101: =I98+I99-I100 -> 265986.27 | ... K101: =K98+K99-K100 -> 243130.79
A103: EV/EBTIDA | B103: =B101/HistoricalFS!C18 -> 35.762007 | C103: =C101/HistoricalFS!D18 -> 25.359236 | D103: =D101/HistoricalFS!E18 -> 36.85163 | E103: =E101/HistoricalFS!F18 -> 33.104867 | F103: =F101/HistoricalFS!G18 -> 34.559267 | G103: =G101/HistoricalFS!H18 -> 48.382061 | H103: =H101/HistoricalFS!I18 -> 39.732926 | I103: =I101/HistoricalFS!J18 -> 38.664729 | ... K103: =K101/HistoricalFS!L18 -> 37.89321
A104: EV/Sales | B104: =B101/B17 -> 5.8295257 | C104: =C101/C17 -> 6.8204301 | D104: =D101/D17 -> 6.3952705 | E104: =E101/E17 -> 7.4871897 | F104: =F101/F17 -> 7.9256033 | G104: =G101/G17 -> 11.231619 | H104: =H101/H17 -> 10.176575 | I104: =I101/I17 -> 7.7122975 | ... K104: =K101/K17 -> 7.1708109
A106: Book Value of Equity | B106: =B57+B58 -> 6524.82 | C106: =C57+C58 -> 7603.89 | D106: =D57+D58 -> 8410.23 | E106: =E57+E58 -> 9470.55 | F106: =F57+F58 -> 10130.16 | G106: =G57+G58 -> 12806.29 | H106: =H57+H58 -> 13811.56 | I106: =I57+I58 -> 15992.23 | ... K106: =K57+K58 -> 19399.81
A107: P/B | B107: =B98/B106 -> 12.766165 | C107: =C98/C106 -> 13.541769 | D107: =D98/D106 -> 12.778339 | E107: =E98/E106 -> 15.118423 | F107: =F98/F106 -> 15.77968 | G107: =G98/G106 -> 19.005302 | H107: =H98/H106 -> 21.389966 | I107: =I98/I106 -> 16.564136 | ... K107: =K98/K106 -> 12.454889
A109: CE | B109: =B66-B60 -> 6848.11 | C109: =C66-C60 -> 8164.23 | D109: =D66-D60 -> 8943.66 | E109: =E66-E60 -> 10790.15 | F109: =F66-F60 -> 11248.66 | G109: =G66-G60 -> 13899.41 | H109: =H66-H60 -> 15398.44 | I109: =I66-I60 -> 17924.85 | ... K109: =K66-K60 -> 21690.1
A110: EBIT | B110: ='Data Sheet'!B32-'Data Sheet'!B26 -> 2050.8 | C110: ='Data Sheet'!C32-'Data Sheet'!C26 -> 3716.17 | D110: ='Data Sheet'!D32-'Data Sheet'!D26 -> 2559.28 | E110: ='Data Sheet'!E32-'Data Sheet'!E26 -> 3729.32 | F110: ='Data Sheet'!F32-'Data Sheet'!F26 -> 3854.62 | G110: ='Data Sheet'!G32-'Data Sheet'!G26 -> 4249.23 | H110: ='Data Sheet'!H32-'Data Sheet'!H26 -> 6637.19 | I110: ='Data Sheet'!I32-'Data Sheet'!I26 -> 6021.28 | ... K110: ='Data Sheet'!K32-'Data Sheet'!K26 -> 5389.87
A111: ROCE | B111: =B110/B109 -> 0.29946949 | C111: =C110/C109 -> 0.45517703 | D111: =D110/D109 -> 0.28615578 | E111: =E110/E109 -> 0.34562263 | F111: =F110/F109 -> 0.34267371 | G111: =G110/G109 -> 0.30571298 | H111: =H110/H109 -> 0.43103003 | I111: =I110/I109 -> 0.33591801 | ... K111: =K110/K109 -> 0.24849447

Sheet Data
B2: S.No. | C2: Name | D2: CMP Rs. | E2: No. Eq. Shares Cr. | F2: Mar Cap Rs.Cr. | G2: Debt Rs.Cr. | H2: Cash End Rs.Cr. | I2: Net Debt | J2: EV | K2: Sales Rs.Cr. | L2: EBITDA | M2: EBIT 12M Rs.Cr. | N2: Dep 12M Rs.Cr. | O2: NP 12M Rs.Cr.
B3: 1 | C3: Asian Paints | D3: 2518.6 | E3: 95.92 | F3: =D3*E3 -> 241584.11 | G3: 2290.29 | H3: 781.98 | I3: =G3-H3 -> 1508.31 | J3: =F3+G3-H3 -> 243092.42 | K3: 33874.44 | L3: =M3+N3 -> 6686.91 | M3: 5587.4 | N3: 1099.51 | O3: 3639.97
B4: 2 | C4: Berger Paints | D4: 533 | E4: 116.59 | F4: =D4*E4 -> 62142.47 | G4: 670.27 | H4: 500.48 | I4: =G4-H4 -> 169.79 | J4: =F4+G4-H4 -> 62312.26 | K4: 11654.46 | L4: =M4+N4 -> 1985.61 | M4: 1624.65 | N4: 360.96 | O4: 1143.82
B5: 3 | C5: Kansai Nerolac | D5: 239.99 | E5: 80.85 | F5: =D5*E5 -> 19403.192 | G5: 296.39 | H5: 290.06 | I5: =G5-H5 -> 6.33 | J5: =F5+G5-H5 -> 19409.521 | K5: 7851.94 | L5: =M5+N5 -> 1073.79 | M5: 867.29 | N5: 206.5 | O5: 1100.05
B6: 4 | C6: Akzo Nobel | D6: 3410.6 | E6: 4.55 | F6: =D6*E6 -> 15518.23 | G6: 62.1 | H6: 299.5 | I6: =G6-H6 -> -237.4 | J6: =F6+G6-H6 -> 15280.83 | K6: 4050 | L6: =M6+N6 -> 633.7 | M6: 547.9 | N6: 85.8 | O6: 405
B7: 5 | C7: Indigo Paints | D7: 1099.7 | E7: 4.76 | F7: =D7*E7 -> 5234.572 | G7: 19.7 | H7: 37.1 | I7: =G7-H7 -> -17.4 | J7: =F7+G7-H7 -> 5217.172 | K7: 1278.1 | L7: =M7+N7 -> 248.54 | M7: 194.95 | N7: 53.59 | O7: 143.84
B8: 6 | C8: Sirca Paints | D8: 462.75 | E8: 5.48 | F8: =D8*E8 -> 2535.87 | G8: 0 | H8: 54.16 | I8: =G8-H8 -> -54.16 | J8: =F8+G8-H8 -> 2481.71 | K8: 409.37 | L8: =M8+N8 -> 79.9 | M8: 72.03 | N8: 7.87 | O8: 53.11
B9: 7 | C9: Shalimar Paints | D9: 71.73 | E9: 8.37 | F9: =D9*E9 -> 600.3801 | G9: 163.86 | H9: 45.47 | I9: =G9-H9 -> 118.39 | J9: =F9+G9-H9 -> 718.7701 | K9: 624.19 | L9: =M9+N9 -> -32.52 | M9: -48.97 | N9: 16.45 | O9: -69.79
B10: 8 | C10: Kamdhenu Venture | D10: 10.21 | E10: 31.44 | F10: =D10*E10 -> 321.0024 | G10: 26.98 | H10: 5.9 | I10: =G10-H10 -> 21.08 | J10: =F10+G10-H10 -> 342.0824 | K10: 261.89 | L10: =M10+N10 -> 16.77 | M10: 11.36 | N10: 5.41 | O10: 5.94
B11: 9 | C11: Siddhika Coatins | D11: 190 | E11: 0.62 | F11: =D11*E11 -> 117.8 | G11: 0 | H11: 5.76 | I11: =G11-H11 -> -5.76 | J11: =F11+G11-H11 -> 112.04 | K11: 48.01 | L11: =M11+N11 -> 10.44 | M11: 10.17 | N11: 0.27 | O11: 8.03
B12: 10 | C12: Retina Paints | D12: 76.5 | E12: 1.53 | F12: =D12*E12 -> 117.045 | G12: 8.12 | H12: 0.36 | I12: =G12-H12 -> 7.76 | J12: =F12+G12-H12 -> 124.805 | K12: 11.66 | L12: =M12+N12 -> 2.02 | M12: 1.72 | N12: 0.3 | O12: 0.74

Sheet Raw FS
B2: Particulars | C2: 42430 | D2: 42795 | E2: 43160 | F2: 43525 | G2: 43891 | H2: 44256 | I2: 44621 | J2: 44986 | K2: 45352 | L2: 45717
B4: Equity Capital | C4: 96 | D4: 96 | E4: 96 | F4: 96 | G4: 96 | H4: 96 | I4: 96 | J4: 96 | K4: 96 | L4: 96
B5: Reserves | C5: 6429 | D5: 7508 | E5: 8314 | F5: 9375 | G5: 10034 | H5: 12710 | I5: 13716 | J5: 15896 | K5: 18632 | L5: 19304
B6: Borrowings -
B7: Long term Borrowings | C7: 73 | D7: 41 | E7: 28 | F7: 19 | G7: 19 | H7: 15 | I7: 45 | J7: 76 | K7: 54 | L7: 260
B8: Short term Borrowings | C8: 231 | D8: 504 | E8: 492 | F8: 597 | G8: 321 | H8: 334 | I8: 731 | J8: 896 | K8: 1053 | L8: 604
B9: Lease Liabilities | C9: 0 | D9: 0 | E9: 0 | F9: 693 | G9: 764 | H9: 745 | I9: 811 | J9: 960 | K9: 1367 | L9: 1427
B10: Other Borrowings | C10: 20 | D10: 15 | E10: 13 | F10: 11 | G10: 15 | H10: 0 | I10: 0 | J10: 0 | K10: 0 | L10: 0
B11: Other Liabilities -
B12: Non controlling int | C12: 384 | D12: 375 | E12: 328 | F12: 361 | G12: 404 | H12: 423 | I12: 388 | J12: 454 | K12: 695 | L12: 659
B13: Trade Payables | C13: 1565 | D13: 1923 | E13: 2160 | F13: 2394 | G13: 2137 | H13: 3379 | I13: 4164 | J13: 3635 | K13: 3831 | L13: 3848
B14: Advance from Customers | C14: 12 | D14: 17 | E14: 16 | F14: 13 | G14: 29 | H14: 41 | I14: 76 | J14: 108 | K14: 154 | L14: 173
B15: Other liability items | C15: 1750 | D15: 1925 | E15: 2316 | F15: 2690 | G15: 2320 | H15: 2613 | I15: 2932 | J15: 3657 | K15: 4017 | L15: 3985
B16: Total Liabilities | C16: 10559 | D16: 12405 | E16: 13763 | F16: 16249 | G16: 16138 | H16: 20355 | I16: 22958 | J16: 25779 | K16: 29901 | L16: 30355
B18: Fixed Assets -
B19: Land | C19: 429 | D19: 408 | E19: 586 | F19: 605 | G19: 640 | H19: 644 | I19: 644 | J19: 804 | K19: 1126 | L19: 1050
B20: Building | C20: 923 | D20: 931 | E20: 957 | F20: 2402 | G20: 2257 | H20: 2249 | I20: 2325 | J20: 2883 | K20: 3390 | L20: 4136
B21: Plant Machinery | C21: 1793 | D21: 1980 | E21: 2157 | F21: 4006 | G21: 4208 | H21: 4340 | I21: 4531 | J21: 4825 | K21: 5422 | L21: 7576
B22: Equipments | C22: 97 | D22: 119 | E22: 200 | F22: 221 | G22: 241 | H22: 243 | I22: 253 | J22: 270 | K22: 298 | L22: 325
B23: Furniture n fittings | C23: 49 | D23: 59 | E23: 72 | F23: 88 | G23: 94 | H23: 99 | I23: 113 | J23: 146 | K23: 175 | L23: 203
B24: Vehicles | C24: 11 | D24: 14 | E24: 27 | F24: 47 | G24: 43 | H24: 38 | I24: 32 | J24: 36 | K24: 40 | L24: 39
B25: Intangible Assets | C25: 339 | D25: 276 | E25: 468 | F25: 512 | G25: 505 | H25: 476 | I25: 345 | J25: 422 | K25: 850 | L25: 827
B26: Other fixed assets | C26: 103 | D26: 128 | E26: 238 | F26: 261 | G26: 293 | H26: 302 | I26: 294 | J26: 289 | K26: 321 | L26: 328
B27: Gross Block | C27: 3744 | D27: 3914 | E27: 4705 | F27: 8141 | G27: 8282 | H27: 8392 | I27: 8538 | J27: 9676 | K27: 11622 | L27: 14484
B28: Accumulated Depreciation | C28: 327 | D28: 610 | E28: 973 | F28: 1644 | G28: 2010 | H28: 2533 | I28: 3019 | J28: 3905 | K28: 4475 | L28: 5264
B29: Net Block | C29: =C27-C28 -> 3417 | D29: =D27-D28 -> 3304 | E29: =E27-E28 -> 3732 | F29: =F27-F28 -> 6497 | G29: =G27-G28 -> 6272 | H29: =H27-H28 -> 5859 | I29: =I27-I28 -> 5519 | J29: =J27-J28 -> 5771 | ... L29: =L27-L28 -> 9220
B31: CWIP | C31: 107 | D31: 258 | E31: 1405 | F31: 210 | G31: 140 | H31: 183 | I31: 426 | J31: 1020 | K31: 2698 | L31: 1254
B32: Investments | C32: 2712 | D32: 2652 | E32: 2141 | F32: 2569 | G32: 2019 | H32: 4737 | I32: 3248 | J32: 4262 | K32: 4588 | L32: 4725
B34: Other Assets -
B35: Inventories | C35: 1998 | D35: 2627 | E35: 2658 | F35: 3150 | G35: 3390 | H35: 3799 | I35: 6153 | J35: 6211 | K35: 5923 | L35: 6719
B36: Trade receivables | C36: 1187 | D36: 1447 | E36: 1731 | F36: 1907 | G36: 1795 | H36: 2602 | I36: 3871 | J36: 4637 | K36: 4889 | L36: 4314
B37: Cash Equivalents | C37: 424 | D37: 801 | E37: 405 | F37: 445 | G37: 783 | H37: 611 | I37: 864 | J37: 844 | K37: 1084 | L37: 782
B38: Loans n Advances | C38: 9 | D38: 14 | E38: 13 | F38: 16 | G38: 12 | H38: 11 | I38: 8 | J38: 12 | K38: 17 | L38: 22
B39: Other asset items | C39: 705 | D39: 1303 | E39: 1678 | F39: 1456 | G39: 1727 | H39: 2555 | I39: 2869 | J39: 3024 | K39: 3555 | L39: 3319
B40: Total Assets | C40: 10559 | D40: 12405 | E40: 13763 | F40: 16249 | G40: 16138 | H40: 20355 | I40: 22958 | J40: 25779 | K40: 29901 | L40: 30355

Sheet Cash Flow Data
C2: 41699 | D2: 42064 | E2: 42430 | F2: 42795 | G2: 43160 | H2: 43525 | I2: 43891 | J2: 44256 | K2: 44621 | L2: 44986 | M2: 45352 | N2: 45717
B3: Cash from Operating Activity - | C3: 4211 | D3: -21281 | E3: -34435 | F3: 17282 | G3: 17214 | H3: -62872 | I3: -16869 | J3: 42476 | K3: -11960 | L3: 20814 | M3: 19069 | N3: 127242
B4: Profit from operations | C4: 15791 | D4: 19196 | E4: 23481 | F4: 28573 | G4: 36737 | H4: 44497 | I4: 54764 | J4: 65619 | K4: 70781 | L4: 79722 | M4: 91618 | N4: 117642
B5: Loans Advances | C5: -70042 | D5: -70356 | E5: -106601 | F5: -101890 | G5: -120305 | H5: -176608 | I5: -185500 | J5: -155681 | K5: -248946 | L5: -254569 | M5: -312488 | N5: -169918
B6: Operating investments | C6: -8677 | D6: -45020 | E6: -39116 | F6: -17326 | G6: -28231 | H6: -51458 | I6: -101070 | J6: -50157 | K6: -10849 | L6: -64182 | M6: -88412 | N6: -180363
B7: Operating Deposits | C7: 70989 | D7: 83203 | E7: 95590 | F7: 97261 | G7: 145241 | H7: 134128 | I7: 223704 | J7: 187514 | K7: 224282 | L7: 324660 | M7: 336965 | N7: 334011
B8: Other WC items | C8: 358 | D8: -2656 | E8: -716 | F8: 18348 | G8: -6218 | H8: -932 | I8: 2110 | J8: 8203 | K8: -32389 | L8: -48450 | M8: 14229 | N8: 45578
B9: Working capital changes | C9: -7372 | D9: -34829 | E9: -50844 | F9: -3607 | G9: -9513 | H9: -94870 | I9: -60756 | J9: -10121 | K9: -67902 | L9: -42541 | M9: -49706 | N9: 29308
B10: Direct taxes | C10: -4209 | D10: -5647 | E10: -7073 | F10: -7685 | G10: -10010 | H10: -12498 | I10: -10877 | J10: -13021 | K10: -14838 | L10: -16367 | M10: -22843 | N10: -19709
B11: Cash from Investing Activity - | C11: -1099 | D11: -800 | E11: -837 | F11: -1146 | G11: -842 | H11: -1503 | I11: -1403 | J11: -1823 | K11: -2051 | L11: -2992 | M11: 16600 | N11: -3651
B12: Fixed assets purchased | C12: -853 | D12: -772 | E12: -877 | F12: -1158 | G12: -848 | H12: -1621 | I12: -1636 | J12: -1696 | K12: -2236 | L12: -3467 | M12: -4287 | N12: -4076
B13: Fixed assets sold | C13: 13 | D13: 33 | E13: 12 | F13: 10 | G13: 10 | H13: 22 | I13: 19 | J13: 15 | K13: 20 | L13: 43 | M13: 100 | N13: 101
B14: Investments sold | C14: 0 | D14: 0 | E14: 0 | F14: 0 | G14: 0 | H14: 0 | I14: 0 | J14: 0 | K14: 0 | L14: 0 | M14: 9501 | N14: 192
... B26: Net Cash Flow | C26: 12382 | D26: -3387 | E26: 2542 | F26: 10242 | G26: 73750 | H26: -41244 | I26: 6122 | J26: 33332 | K26: 34113 | L26: 41762 | M26: 31687 | N26: 21113
